Workbook

Sheet 컬렉션
A1: # | B1: 장 | C1: 타이틀 | D1: 한자 | E1: 달성 조건 | F1: 설명 | G1: 상세 설명 | H1: 칸 수 | I1: 비용 | J1: 등급 | K1: 점수 | L1: 효과 (읽는 글) | M1: 효과 종류 | N1: 대상 | O1: 능력치 | P1: 값 | Q1: 함께 참전 | R1: 함께 최소 | S1: 적진에 | T1: 도시 키
A2: 1 | B2: ① 황건 · 반동탁 (184~192) | C2: 도원결의 | D2: 桃園結義 | E2: =INDEX(칸!$I$2:$I$416,MATCH(A2,칸!$A$2:$A$416,1)) | F2: 삼국지의 시작. 세 사람은 복숭아나무 뜰에서 의형제를 맺었다고 한다. | G2: 황건적이 일어난 해, 탁현의 유비 · 관우 · 장비는 장비의 집 뒤뜰 복숭아밭에서 의형제를 맺었다. 같은 날 태어나지 못했으나 같은 날 죽기를 바란다는 맹세는 세 사람의 평생을 묶었다. | H2: =COUNTIF(칸!$A$2:$A$416,A2) | I2: =SUMIF(칸!$A$2:$A$416,A2,칸!$H$2:$H$416) | J2: =INDEX(비용표!$A$13:$A$17,MATCH(I2,비용표!$B$13:$B$17,1)) | K2: =INDEX(비용표!$C$13:$C$17,MATCH(I2,비용표!$B$13:$B$17,1)) | L2: 유비·관우·장비 함께 참전 시 유비·관우·장비 HP+2 | M2: 능력치 | N2: 유비·관우·장비 | O2: HP | P2: 2 | Q2: 유비·관우·장비
A3: 2 | B3: ① 황건 · 반동탁 (184~192) | C3: 황건적 토벌 | D3: 討黃巾賊 | E3: =INDEX(칸!$I$2:$I$416,MATCH(A3,칸!$A$2:$A$416,1)) | F3: 태평도의 장각이 일으킨 난. 훗날 천하를 나눌 세 사람이 같은 전장에 섰다. | G3: 태평도의 교주 장각이 「창천은 이미 죽었다」며 수십만 신도를 일으켰다. 토벌에 나선 관군과 의병 가운데 유비 · 조조 · 손견이 있었다 — 훗날 천하를 셋으로 나눌 이들의 첫 전장이다. | H3: =COUNTIF(칸!$A$2:$A$416,A3) | I3: =SUMIF(칸!$A$2:$A$416,A3,칸!$H$2:$H$416) | J3: =INDEX(비용표!$A$13:$A$17,MATCH(I3,비용표!$B$13:$B$17,1)) | K3: =INDEX(비용표!$C$13:$C$17,MATCH(I3,비용표!$B$13:$B$17,1)) | L3: 도적떼 약탈률 −1%p (도적 1명당 10% → 9%) | M3: 도시 | P3: 1 | T3: raidLoot
A4: 3 | B4: ① 황건 · 반동탁 (184~192) | C4: 온주참화웅 | D4: 溫酒斬華雄 | E4: =INDEX(칸!$I$2:$I$416,MATCH(A4,칸!$A$2:$A$416,1)) | F4: 데운 술이 식기 전에 화웅의 목을 베어 돌아왔다. | G4: 사수관 앞에서 동탁의 맹장 화웅이 연합군 장수들을 잇달아 베자, 마궁수에 불과하던 관우가 나섰다. 조조가 따라 준 데운 술이 식기도 전에 관우는 화웅의 목을 들고 돌아왔다고 연의는 전한다. | H4: =COUNTIF(칸!$A$2:$A$416,A4) | I4: =SUMIF(칸!$A$2:$A$416,A4,칸!$H$2:$H$416) | J4: =INDEX(비용표!$A$13:$A$17,MATCH(I4,비용표!$B$13:$B$17,1)) | K4: =INDEX(비용표!$C$13:$C$17,MATCH(I4,비용표!$B$13:$B$17,1)) | L4: 적진에 화웅 시 관우 무력+2 | M4: 능력치 | N4: 관우 | O4: 무력 | P4: 2 | S4: 화웅
A5: 4 | B5: ① 황건 · 반동탁 (184~192) | C5: 호뢰관 삼영전여포 | D5: 虎牢關三英戰呂布 | E5: =INDEX(칸!$I$2:$I$416,MATCH(A5,칸!$A$2:$A$416,1)) | F5: 세 형제가 함께 덤벼서야 여포를 물러나게 했다. | G5: 호뢰관에 나선 여포를 당할 자가 없자 장비가 맞붙었고, 관우와 유비가 차례로 뛰어들었다. 세 사람이 한꺼번에 덤벼서야 여포는 말머리를 돌렸다 — 연의가 그린 삼국 최고의 일기토다. | H5: =COUNTIF(칸!$A$2:$A$416,A5) | I5: =SUMIF(칸!$A$2:$A$416,A5,칸!$H$2:$H$416) | J5: =INDEX(비용표!$A$13:$A$17,MATCH(I5,비용표!$B$13:$B$17,1)) | K5: =INDEX(비용표!$C$13:$C$17,MATCH(I5,비용표!$B$13:$B$17,1)) | L5: 적진에 여포 시 장비 무력+2 | M5: 능력치 | N5: 장비 | O5: 무력 | P5: 2 | S5: 여포
A6: 5 | B6: ① 황건 · 반동탁 (184~192) | C6: 반동탁 연합군 | D6: 反董卓聯合軍 | E6: =INDEX(칸!$I$2:$I$416,MATCH(A6,칸!$A$2:$A$416,1)) | F6: 열여덟 제후가 낙양을 향해 모였고, 맹주는 원소였다. | G6: 동탁이 황제를 갈아 치우자 관동의 제후들이 군사를 일으켜 원소를 맹주로 세웠다. 그러나 제후들은 서로를 견제하며 나아가지 않았고, 연합은 공을 다투다 흩어졌다. | H6: =COUNTIF(칸!$A$2:$A$416,A6) | I6: =SUMIF(칸!$A$2:$A$416,A6,칸!$H$2:$H$416) | J6: =INDEX(비용표!$A$13:$A$17,MATCH(I6,비용표!$B$13:$B$17,1)) | K6: =INDEX(비용표!$C$13:$C$17,MATCH(I6,비용표!$B$13:$B$17,1)) | L6: 원소 통솔+2 | M6: 능력치 | N6: 원소 | O6: 통솔 | P6: 2
A7: 6 | B7: ① 황건 · 반동탁 (184~192) | C7: 장안 천도 | D7: 長安遷都 | E7: =INDEX(칸!$I$2:$I$416,MATCH(A7,칸!$A$2:$A$416,1)) | F7: 동탁은 낙양을 불태우고 황제와 백성을 장안으로 끌고 갔다. | G7: 연합군에 밀린 동탁은 낙양의 궁궐과 민가를 불사르고 황제와 백성 수백만을 장안으로 끌고 갔다. 길에서 쓰러진 백성이 헤아릴 수 없었고, 낙양은 폐허가 되었다. | H7: =COUNTIF(칸!$A$2:$A$416,A7) | I7: =SUMIF(칸!$A$2:$A$416,A7,칸!$H$2:$H$416) | J7: =INDEX(비용표!$A$13:$A$17,MATCH(I7,비용표!$B$13:$B$17,1)) | K7: =INDEX(비용표!$C$13:$C$17,MATCH(I7,비용표!$B$13:$B$17,1)) | L7: 동탁 HP+1 | M7: 능력치 | N7: 동탁 | O7: HP | P7: 1
A8: 7 | B8: ① 황건 · 반동탁 (184~192) | C8: 칠성보도 헌상 | D8: 獻七星寶刀 | E8: =INDEX(칸!$I$2:$I$416,MATCH(A8,칸!$A$2:$A$416,1)) | F8: 동탁을 찌르려던 칼은 들키는 순간 헌상품이 되었다. | G8: 왕윤에게서 칠성보도를 빌린 조조는 동탁의 침소에서 칼을 뽑았으나, 거울에 비친 모습에 동탁이 돌아보았다. 조조는 칼을 바치러 왔다며 무릎을 꿇었고, 그 길로 낙양을 빠져나갔다. | H8: =COUNTIF(칸!$A$2:$A$416,A8) | I8: =SUMIF(칸!$A$2:$A$416,A8,칸!$H$2:$H$416) | J8: =INDEX(비용표!$A$13:$A$17,MATCH(I8,비용표!$B$13:$B$17,1)) | K8: =INDEX(비용표!$C$13:$C$17,MATCH(I8,비용표!$B$13:$B$17,1)) | L8: 적진에 동탁 시 조조 무력+2 | M8: 능력치 | N8: 조조 | O8: 무력 | P8: 2 | S8: 동탁
A9: 8 | B9: ① 황건 · 반동탁 (184~192) | C9: 진궁의 결별 | D9: 陳宮決別 | E9: =INDEX(칸!$I$2:$I$416,MATCH(A9,칸!$A$2:$A$416,1)) | F9: 「차라리 내가 천하를 버릴지언정」 — 진궁은 그 밤에 조조를 떠났다. | G9: 동탁을 피해 달아나던 조조를 현령 진궁이 풀어 주고 함께 길을 떠났다. 그러나 여백사 일가를 오해로 죽이고도 「내가 천하를 버릴지언정」이라 말하는 조조를 보고, 진궁은 그 밤에 떠났다. | H9: =COUNTIF(칸!$A$2:$A$416,A9) | I9: =SUMIF(칸!$A$2:$A$416,A9,칸!$H$2:$H$416) | J9: =INDEX(비용표!$A$13:$A$17,MATCH(I9,비용표!$B$13:$B$17,1)) | K9: =INDEX(비용표!$C$13:$C$17,MATCH(I9,비용표!$B$13:$B$17,1)) | L9: 적진에 조조 시 진궁 통솔+1 | M9: 능력치 | N9: 진궁 | O9: 통솔 | P9: 1 | S9: 조조
A10: 9 | B10: ① 황건 · 반동탁 (184~192) | C10: 형양의 추격 | D10: 滎陽追擊 | E10: =INDEX(칸!$I$2:$I$416,MATCH(A10,칸!$A$2:$A$416,1)) | F10: 「천하에 조홍은 없어도 되지만 공은 없어선 안 됩니다.」 — 조홍은 제 말을 내주었다. | G10: 연합군 중 홀로 동탁을 추격한 조조는 형양에서 서영에게 크게 졌다. 말을 잃고 쓰러진 조조에게 조홍이 제 말을 내주며 「천하에 조홍은 없어도 되지만 공은 없어선 안 됩니다」라 했다. | H10: =COUNTIF(칸!$A$2:$A$416,A10) | I10: =SUMIF(칸!$A$2:$A$416,A10,칸!$H$2:$H$416) | J10: =INDEX(비용표!$A$13:$A$17,MATCH(I10,비용표!$B$13:$B$17,1)) | K10: =INDEX(비용표!$C$13:$C$17,MATCH(I10,비용표!$B$13:$B$17,1)) | L10: 조조 함께 참전 시 조홍 HP+2 | M10: 능력치 | N10: 조홍 | O10: HP | P10: 2 | Q10: 조조
A11: 10 | B11: ① 황건 · 반동탁 (184~192) | C11: 손견과 전국옥새 | D11: 孫堅得玉璽 | E11: =INDEX(칸!$I$2:$I$416,MATCH(A11,칸!$A$2:$A$416,1)) | F11: 불탄 낙양의 우물에서 건져 올린 황제의 옥새. | G11: 불탄 낙양에 먼저 들어간 손견은 궁궐 우물에서 황제의 옥새를 건졌다. 옥새를 숨긴 채 강동으로 돌아가려던 손견은 원소 · 유표와 원수가 되었다. | H11: =COUNTIF(칸!$A$2:$A$416,A11) | I11: =SUMIF(칸!$A$2:$A$416,A11,칸!$H$2:$H$416) | J11: =INDEX(비용표!$A$13:$A$17,MATCH(I11,비용표!$B$13:$B$17,1)) | K11: =INDEX(비용표!$C$13:$C$17,MATCH(I11,비용표!$B$13:$B$17,1)) | L11: 손견 통솔+2 | M11: 능력치 | N11: 손견 | O11: 통솔 | P11: 2
A12: 11 | B12: ① 황건 · 반동탁 (184~192) | C12: 현산의 손견 | D12: 峴山伏兵 | E12: =INDEX(칸!$I$2:$I$416,MATCH(A12,칸!$A$2:$A$416,1)) | F12: 강동의 호랑이는 괴월의 매복에 걸려 현산에서 쓰러졌다. | G12: 원술의 명으로 형주를 친 손견은 유표의 장수 황조를 몰아붙였다. 그러나 괴월의 계책으로 현산에 숨은 복병에게 돌과 화살을 맞아, 강동의 호랑이는 서른일곱에 쓰러졌다. | H12: =COUNTIF(칸!$A$2:$A$416,A12) | I12: =SUMIF(칸!$A$2:$A$416,A12,칸!$H$2:$H$416) | J12: =INDEX(비용표!$A$13:$A$17,MATCH(I12,비용표!$B$13:$B$17,1)) | K12: =INDEX(비용표!$C$13:$C$17,MATCH(I12,비용표!$B$13:$B$17,1)) | L12: 적진에 손견 시 괴월 지력+2 | M12: 능력치 | N12: 괴월 | O12: 지력 | P12: 2 | S12: 손견
A13: 12 | B13: ① 황건 · 반동탁 (184~192) | C13: 백마의종 | D13: 白馬義從 | E13: =INDEX(칸!$I$2:$I$416,MATCH(A13,칸!$A$2:$A$416,1)) | F13: 흰 말만 골라 탄 공손찬의 기병대는 이민족도 두려워했다. | G13: 공손찬은 흰 말을 탄 활 잘 쏘는 기병 수천을 골라 「백마의종」이라 불렀다. 북방의 오환은 흰 말만 보면 달아났다고 하니, 그 이름만으로도 변경을 지켰다. | H13: =COUNTIF(칸!$A$2:$A$416,A13) | I13: =SUMIF(칸!$A$2:$A$416,A13,칸!$H$2:$H$416) | J13: =INDEX(비용표!$A$13:$A$17,MATCH(I13,비용표!$B$13:$B$17,1)) | K13: =INDEX(비용표!$C$13:$C$17,MATCH(I13,비용표!$B$13:$B$17,1)) | L13: 공손찬 통솔+2 | M13: 능력치 | N13: 공손찬 | O13: 통솔 | P13: 2
A14: 13 | B14: ① 황건 · 반동탁 (184~192) | C14: 계교 전투 | D14: 界橋之戰 | E14: =INDEX(칸!$I$2:$I$416,MATCH(A14,칸!$A$2:$A$416,1)) | F14: 국의의 강노병이 백마의종을 무너뜨렸다. | G14: 원소와 공손찬이 기주를 두고 계교에서 맞섰다. 원소의 장수 국의는 강노병 팔백을 방패 뒤에 숨겼다가 백마의종이 코앞에 오자 일제히 쏘아 무너뜨렸다. | H14: =COUNTIF(칸!$A$2:$A$416,A14) | I14: =SUMIF(칸!$A$2:$A$416,A14,칸!$H$2:$H$416) | J14: =INDEX(비용표!$A$13:$A$17,MATCH(I14,비용표!$B$13:$B$17,1)) | K14: =INDEX(비용표!$C$13:$C$17,MATCH(I14,비용표!$B$13:$B$17,1)) | L14: 적진에 공손찬 시 국의 무력+2 | M14: 능력치 | N14: 국의 | O14: 무력 | P14: 2 | S14: 공손찬
A15: 14 | B15: ② 군웅할거 (192~199) | C15: 이각과 곽사 | D15: 李傕郭汜 | E15: =INDEX(칸!$I$2:$I$416,MATCH(A15,칸!$A$2:$A$416,1)) | F15: 동탁이 죽은 뒤 장안을 차지한 두 장수는 곧 서로를 공격했다. | G15: 왕윤과 여포가 동탁을 죽이자, 그 부장 이각과 곽사는 장안을 들이쳐 조정을 손에 넣었다. 그러나 둘은 곧 서로를 의심해 장안 한복판에서 싸웠고, 황제와 대신들은 인질이 되었다. | H15: =COUNTIF(칸!$A$2:$A$416,A15) | I15: =SUMIF(칸!$A$2:$A$416,A15,칸!$H$2:$H$416) | J15: =INDEX(비용표!$A$13:$A$17,MATCH(I15,비용표!$B$13:$B$17,1)) | K15: =INDEX(비용표!$C$13:$C$17,MATCH(I15,비용표!$B$13:$B$17,1)) | L15: 이각·곽사 함께 참전 시 이각·곽사 HP+1 | M15: 능력치 | N15: 이각·곽사 | O15: HP | P15: 1 | Q15: 이각·곽사
A16: 15 | B16: ② 군웅할거 (192~199) | C16: 헌제의 동귀 | D16: 獻帝東歸 | E16: =INDEX(칸!$I$2:$I$416,MATCH(A16,칸!$A$2:$A$416,1)) | F16: 이각 · 곽사에게 쫓기던 황제를, 순욱의 「봉천자」 계책대로 조조가 허도로 맞았다. | G16: 이각과 곽사에게 쫓기던 헌제는 한섬 · 서황의 호위를 받아 폐허가 된 낙양으로 돌아왔다. 순욱은 「천자를 받들어 천하를 호령하라」 권했고, 조조는 황제를 허도로 맞았다. | H16: =COUNTIF(칸!$A$2:$A$416,A16) | I16: =SUMIF(칸!$A$2:$A$416,A16,칸!$H$2:$H$416) | J16: =INDEX(비용표!$A$13:$A$17,MATCH(I16,비용표!$B$13:$B$17,1)) | K16: =INDEX(비용표!$C$13:$C$17,MATCH(I16,비용표!$B$13:$B$17,1)) | L16: 헌제의 「황제옹립」 SP 7 → 6 | M16: 고유기술SP | N16: 헌제 | P16: -1
A17: 16 | B17: ② 군웅할거 (192~199) | C17: 둔전제 | D17: 屯田制 | E17: =INDEX(칸!$I$2:$I$416,MATCH(A17,칸!$A$2:$A$416,1)) | F17: 유민에게 땅과 소를 주어 군량을 쌓았다. 조조 패업의 밑돌이다. | G17: 전란으로 굶주린 유민이 넘치자 조조는 한호 · 조지의 건의로 둔전을 열었다. 백성과 병사에게 땅과 소를 나눠 농사를 짓게 하니 한 해에 백만 섬이 쌓였다. | H17: =COUNTIF(칸!$A$2:$A$416,A17) | I17: =SUMIF(칸!$A$2:$A$416,A17,칸!$H$2:$H$416) | J17: =INDEX(비용표!$A$13:$A$17,MATCH(I17,비용표!$B$13:$B$17,1)) | K17: =INDEX(비용표!$C$13:$C$17,MATCH(I17,비용표!$B$13:$B$17,1)) | L17: 군량 충전 속도 +5% | M17: 도시 | P17: 5 | T17: grainRate
A18: 17 | B18: ② 군웅할거 (192~199) | C18: 서주 양도 | D18: 三讓徐州 | E18: =INDEX(칸!$I$2:$I$416,MATCH(A18,칸!$A$2:$A$416,1)) | F18: 도겸은 세 번 서주를 내밀었고 유비는 세 번 사양했다. | G18: 조조의 공격에 시달리던 서주목 도겸은 죽음을 앞두고 유비에게 서주를 맡기려 했다. 유비는 세 번 사양하다 미축 · 손건의 간청에 받아들였다. | H18: =COUNTIF(칸!$A$2:$A$416,A18) | I18: =SUMIF(칸!$A$2:$A$416,A18,칸!$H$2:$H$416) | J18: =INDEX(비용표!$A$13:$A$17,MATCH(I18,비용표!$B$13:$B$17,1)) | K18: =INDEX(비용표!$C$13:$C$17,MATCH(I18,비용표!$B$13:$B$17,1)) | L18: 유비 통솔+1 | M18: 능력치 | N18: 유비 | O18: 통솔 | P18: 1
A19: 18 | B19: ② 군웅할거 (192~199) | C19: 술 취한 장비 | D19: 張飛醉失徐州 | E19: =INDEX(칸!$I$2:$I$416,MATCH(A19,칸!$A$2:$A$416,1)) | F19: 장비가 취해 매질한 조표는 그날 밤 여포에게 성문을 열었다. | G19: 서주를 지키던 장비는 술자리에서 조표를 매질했다. 앙심을 품은 조표가 사위 여포에게 밤중에 성문을 열어 주어, 장비는 서주를 잃고 형님을 볼 낯이 없었다. | H19: =COUNTIF(칸!$A$2:$A$416,A19) | I19: =SUMIF(칸!$A$2:$A$416,A19,칸!$H$2:$H$416) | J19: =INDEX(비용표!$A$13:$A$17,MATCH(I19,비용표!$B$13:$B$17,1)) | K19: =INDEX(비용표!$C$13:$C$17,MATCH(I19,비용표!$B$13:$B$17,1)) | L19: 적진에 장비 시 조표 무력+2 | M19: 능력치 | N19: 조표 | O19: 무력 | P19: 2 | S19: 장비
A20: 19 | B20: ② 군웅할거 (192~199) | C20: 원문사극 | D20: 轅門射戟 | E20: =INDEX(칸!$I$2:$I$416,MATCH(A20,칸!$A$2:$A$416,1)) | F20: 군문 밖 백오십 보의 화극을 맞히면 싸우지 말라. | G20: 원술의 장수 기령이 유비를 치러 오자 여포가 두 사람을 불렀다. 군문 밖 백오십 보에 화극을 세우고 「한 발에 맞히면 싸우지 말라」 하더니, 화살은 정확히 화극의 곁가지에 꽂혔다. | H20: =COUNTIF(칸!$A$2:$A$416,A20) | I20: =SUMIF(칸!$A$2:$A$416,A20,칸!$H$2:$H$416) | J20: =INDEX(비용표!$A$13:$A$17,MATCH(I20,비용표!$B$13:$B$17,1)) | K20: =INDEX(비용표!$C$13:$C$17,MATCH(I20,비용표!$B$13:$B$17,1)) | L20: 여포 HP+1 | M20: 능력치 | N20: 여포 | O20: HP | P20: 1
A21: 20 | B21: ② 군웅할거 (192~199) | C21: 공융과 태사자 | D21: 太史慈救北海 | E21: =INDEX(칸!$I$2:$I$416,MATCH(A21,칸!$A$2:$A$416,1)) | F21: 포위된 북해를 구하러 태사자가 홀로 적진을 뚫었다. | G21: 황건 잔당에 포위된 북해의 공융을 위해, 은혜를 입은 태사자가 홀로 포위를 뚫고 유비에게 구원을 청했다. 유비가 「공북해가 이 유비를 아는가」 하며 기뻐 군사를 냈다. | H21: =COUNTIF(칸!$A$2:$A$416,A21) | I21: =SUMIF(칸!$A$2:$A$416,A21,칸!$H$2:$H$416) | J21: =INDEX(비용표!$A$13:$A$17,MATCH(I21,비용표!$B$13:$B$17,1)) | K21: =INDEX(비용표!$C$13:$C$17,MATCH(I21,비용표!$B$13:$B$17,1)) | L21: 태사자 함께 참전 시 공융 통솔+2 | M21: 능력치 | N21: 공융 | O21: 통솔 | P21: 2 | Q21: 태사자
A22: 21 | B22: ② 군웅할거 (192~199) | C22: 인중여포 마중적토 | D22: 人中呂布馬中赤兔 | E22: =INDEX(칸!$I$2:$I$416,MATCH(A22,칸!$A$2:$A$416,1)) | F22: 삼국지 역사상 최강의 사나이. 사람 중에는 여포, 말 중에는 적토. | G22: 「사람 중에는 여포, 말 중에는 적토마.」 방천화극을 들고 적토마를 탄 여포는 당대 누구도 정면으로 이기지 못한 무인이었다. 다만 그 곁의 진궁 · 고순 · 장료의 말을 끝내 듣지 않았다. | H22: =COUNTIF(칸!$A$2:$A$416,A22) | I22: =SUMIF(칸!$A$2:$A$416,A22,칸!$H$2:$H$416) | J22: =INDEX(비용표!$A$13:$A$17,MATCH(I22,비용표!$B$13:$B$17,1)) | K22: =INDEX(비용표!$C$13:$C$17,MATCH(I22,비용표!$B$13:$B$17,1)) | L22: 여포의 「인중여포 마중적토」 SP 6 → 5 | M22: 고유기술SP | N22: 여포 | P22: -1
A23: 22 | B23: ② 군웅할거 (192~199) | C23: 함진영 | D23: 陷陣營 | E23: =INDEX(칸!$I$2:$I$416,MATCH(A23,칸!$A$2:$A$416,1)) | F23: 칠백 명으로 공격하면 반드시 깨뜨렸다는 고순의 정예. | G23: 여포의 장수 고순은 칠백 명을 거느렸는데, 갑옷과 무기가 정예하여 「함진영」이라 불렀다. 공격하면 반드시 적진을 깨뜨렸으나, 여포는 그를 믿으면서도 끝내 중히 쓰지 않았다. | H23: =COUNTIF(칸!$A$2:$A$416,A23) | I23: =SUMIF(칸!$A$2:$A$416,A23,칸!$H$2:$H$416) | J23: =INDEX(비용표!$A$13:$A$17,MATCH(I23,비용표!$B$13:$B$17,1)) | K23: =INDEX(비용표!$C$13:$C$17,MATCH(I23,비용표!$B$13:$B$17,1)) | L23: 고순 통솔+1 | M23: 능력치 | N23: 고순 | O23: 통솔 | P23: 1
A24: 23 | B24: ② 군웅할거 (192~199) | C24: 하비성 백문루 | D24: 白門樓 | E24: =INDEX(칸!$I$2:$I$416,MATCH(A24,칸!$A$2:$A$416,1)) | F24: 부하들이 등을 돌렸고, 여포는 백문루에서 묶였다. | G24: 조조가 사수와 기수를 터 하비성을 물에 잠기게 하자 여포의 부하들이 등을 돌렸다. 후성 · 송헌 · 위속이 진궁을 묶어 바쳤고, 여포는 백문루에서 사로잡혀 목숨을 잃었다. | H24: =COUNTIF(칸!$A$2:$A$416,A24) | I24: =SUMIF(칸!$A$2:$A$416,A24,칸!$H$2:$H$416) | J24: =INDEX(비용표!$A$13:$A$17,MATCH(I24,비용표!$B$13:$B$17,1)) | K24: =INDEX(비용표!$C$13:$C$17,MATCH(I24,비용표!$B$13:$B$17,1)) | L24: 여포 함께 참전 시 진궁 지력+2 | M24: 능력치 | N24: 진궁 | O24: 지력 | P24: 2 | Q24: 여포
A25: 24 | B25: ② 군웅할거 (192~199) | C25: 진등 부자 | D25: 陳登父子 | E25: =INDEX(칸!$I$2:$I$416,MATCH(A25,칸!$A$2:$A$416,1)) | F25: 진등은 겉으로 여포를 섬기며 안으로 조조와 손을 잡았다. | G25: 서주의 진규 · 진등 부자는 겉으로 여포를 섬기며 안으로 조조와 통했다. 진등이 조조에게서 받은 광릉태수의 인수가, 여포를 무너뜨린 마지막 고리가 되었다. | H25: =COUNTIF(칸!$A$2:$A$416,A25) | I25: =SUMIF(칸!$A$2:$A$416,A25,칸!$H$2:$H$416) | J25: =INDEX(비용표!$A$13:$A$17,MATCH(I25,비용표!$B$13:$B$17,1)) | K25: =INDEX(비용표!$C$13:$C$17,MATCH(I25,비용표!$B$13:$B$17,1)) | L25: 진등 지력+2 | M25: 능력치 | N25: 진등 | O25: 지력 | P25: 2
A26: 25 | B26: ② 군웅할거 (192~199) | C26: 원술 칭제 | D26: 袁術稱帝 | E26: =INDEX(칸!$I$2:$I$416,MATCH(A26,칸!$A$2:$A$416,1)) | F26: 옥새를 품고 황제를 칭했으나 마지막엔 꿀물 한 그릇을 찾았다. | G26: 손견이 남긴 옥새를 손에 넣은 원술은 수춘에서 스스로 황제를 칭했다. 그러나 사치와 실정에 백성과 장수가 등을 돌렸고, 마지막에는 꿀물 한 그릇을 찾다 피를 토하고 죽었다. | H26: =COUNTIF(칸!$A$2:$A$416,A26) | I26: =SUMIF(칸!$A$2:$A$416,A26,칸!$H$2:$H$416) | J26: =INDEX(비용표!$A$13:$A$17,MATCH(I26,비용표!$B$13:$B$17,1)) | K26: =INDEX(비용표!$C$13:$C$17,MATCH(I26,비용표!$B$13:$B$17,1)) | L26: 최대 군량 +2 | M26: 도시 | P26: 2 | T26: grainCap
A27: 26 | B27: ② 군웅할거 (192~199) | C27: 역경 함락 | D27: 易京陷落 | E27: =INDEX(칸!$I$2:$I$416,MATCH(A27,칸!$A$2:$A$416,1)) | F27: 높은 누대에 숨은 공손찬은 땅굴을 판 원소군 앞에 스스로 불을 질렀다. | G27: 원소에게 밀린 공손찬은 역경에 수십 장 높이의 누대를 쌓고 틀어박혔다. 원소군이 땅굴을 파고 들어와 누대를 무너뜨리자, 공손찬은 처자를 죽이고 스스로 불을 질렀다. | H27: =COUNTIF(칸!$A$2:$A$416,A27) | I27: =SUMIF(칸!$A$2:$A$416,A27,칸!$H$2:$H$416) | J27: =INDEX(비용표!$A$13:$A$17,MATCH(I27,비용표!$B$13:$B$17,1)) | K27: =INDEX(비용표!$C$13:$C$17,MATCH(I27,비용표!$B$13:$B$17,1)) | L27: 공손찬 HP+1 | M27: 능력치 | N27: 공손찬 | O27: HP | P27: 1
A28: 27 | B28: ② 군웅할거 (192~199) | C28: 신정산의 일기토 | D28: 神亭山一騎討 | E28: =INDEX(칸!$I$2:$I$416,MATCH(A28,칸!$A$2:$A$416,1)) | F28: 태사자는 두 자루 극을 들고 소패왕과 맞붙었다. | G28: 신정산에서 정찰하던 손책과 맞닥뜨린 태사자는 홀로 덤벼들었다. 둘은 말에서 떨어져 뒤엉켰고, 손책은 태사자의 단극을, 태사자는 손책의 투구를 빼앗았다. 이후 태사자는 손책의 장수가 되었다. | H28: =COUNTIF(칸!$A$2:$A$416,A28) | I28: =SUMIF(칸!$A$2:$A$416,A28,칸!$H$2:$H$416) | J28: =INDEX(비용표!$A$13:$A$17,MATCH(I28,비용표!$B$13:$B$17,1)) | K28: =INDEX(비용표!$C$13:$C$17,MATCH(I28,비용표!$B$13:$B$17,1)) | L28: 태사자 무력+1 | M28: 능력치 | N28: 태사자 | O28: 무력 | P28: 1
A29: 28 | B29: ② 군웅할거 (192~199) | C29: 내사는 장소에게 | D29: 內事問張昭 | E29: =INDEX(칸!$I$2:$I$416,MATCH(A29,칸!$A$2:$A$416,1)) | F29: 「안의 일은 장소에게, 밖의 일은 주유에게 물어라.」 — 손책의 유언. | G29: 자객의 화살에 쓰러진 손책은 열여덟 살 아우 손권에게 인수를 넘겼다. 「안의 일은 장소에게, 밖의 일은 주유에게 물어라」 — 손권은 그 두 사람과 함께 강동을 지켜 냈다. | H29: =COUNTIF(칸!$A$2:$A$416,A29) | I29: =SUMIF(칸!$A$2:$A$416,A29,칸!$H$2:$H$416) | J29: =INDEX(비용표!$A$13:$A$17,MATCH(I29,비용표!$B$13:$B$17,1)) | K29: =INDEX(비용표!$C$13:$C$17,MATCH(I29,비용표!$B$13:$B$17,1)) | L29: 장소 통솔+2 | M29: 능력치 | N29: 장소 | O29: 통솔 | P29: 2
A30: 29 | B30: ② 군웅할거 (192~199) | C30: 완성의 밤 | D30: 宛城之夜 | E30: =INDEX(칸!$I$2:$I$416,MATCH(A30,칸!$A$2:$A$416,1)) | F30: 조조는 이 밤 장자와 조카, 그리고 명마 절영을 잃었다. | G30: 장수의 항복을 받아들인 조조는 완성에서 그 숙모를 취했다. 분노한 장수가 가후의 계책으로 밤에 들이치니, 조조는 장자 조앙과 조카, 맹장 전위, 명마 절영을 잃고 겨우 살아났다. | H30: =COUNTIF(칸!$A$2:$A$416,A30) | I30: =SUMIF(칸!$A$2:$A$416,A30,칸!$H$2:$H$416) | J30: =INDEX(비용표!$A$13:$A$17,MATCH(I30,비용표!$B$13:$B$17,1)) | K30: =INDEX(비용표!$C$13:$C$17,MATCH(I30,비용표!$B$13:$B$17,1)) | L30: 장수 통솔+2 | M30: 능력치 | N30: 장수 | O30: 통솔 | P30: 2
A31: 30 | B31: ② 군웅할거 (192~199) | C31: 가후의 계책 | D31: 賈詡之計 | E31: =INDEX(칸!$I$2:$I$416,MATCH(A31,칸!$A$2:$A$416,1)) | F31: 추격하지 말라 할 때 추격하고, 추격하라 할 때 물러서게 했다. | G31: 물러나는 조조를 장수가 추격하려 하자 가후가 말렸다. 장수가 듣지 않고 쫓다 지고 오자, 가후는 「이제 다시 쫓으라」 했고 이번에는 크게 이겼다 — 적의 마음을 읽은 계책이었다. | H31: =COUNTIF(칸!$A$2:$A$416,A31) | I31: =SUMIF(칸!$A$2:$A$416,A31,칸!$H$2:$H$416) | J31: =INDEX(비용표!$A$13:$A$17,MATCH(I31,비용표!$B$13:$B$17,1)) | K31: =INDEX(비용표!$C$13:$C$17,MATCH(I31,비용표!$B$13:$B$17,1)) | L31: 가후 통솔+1 | M31: 능력치 | N31: 가후 | O31: 통솔 | P31: 1
A32: 31 | B32: ② 군웅할거 (192~199) | C32: 청매자주 영웅론 | D32: 青梅煮酒論英雄 | E32: =INDEX(칸!$I$2:$I$416,MATCH(A32,칸!$A$2:$A$416,1)) | F32: 「천하의 영웅은 그대와 나뿐이오」 — 유비는 젓가락을 떨어뜨렸다. | G32: 조조는 유비를 불러 매실을 안주 삼아 술을 데우며 천하의 영웅을 논했다. 「천하의 영웅은 그대와 나뿐」이라는 말에 유비가 젓가락을 떨어뜨리자, 마침 친 천둥소리에 놀란 척 둘러댔다. | H32: =COUNTIF(칸!$A$2:$A$416,A32) | I32: =SUMIF(칸!$A$2:$A$416,A32,칸!$H$2:$H$416) | J32: =INDEX(비용표!$A$13:$A$17,MATCH(I32,비용표!$B$13:$B$17,1)) | K32: =INDEX(비용표!$C$13:$C$17,MATCH(I32,비용표!$B$13:$B$17,1)) | L32: 적진에 유비 시 조조 지력+2 | M32: 능력치 | N32: 조조 | O32: 지력 | P32: 2 | S32: 유비
A33: 32 | B33: ② 군웅할거 (192~199) | C33: 의대조 | D33: 衣帶詔 | E33: =INDEX(칸!$I$2:$I$416,MATCH(A33,칸!$A$2:$A$416,1)) | F33: 황제의 옷 띠 속에 조조를 치라는 피의 밀서가 꿰매져 있었다. | G33: 조조의 전횡에 헌제는 피로 쓴 밀조를 옷 띠 속에 꿰매 동승에게 내렸다. 유비 · 마등이 이름을 올렸으나 계획은 탄로 나, 동승의 일족은 몰살되고 유비는 서주로 달아났다. | H33: =COUNTIF(칸!$A$2:$A$416,A33) | I33: =SUMIF(칸!$A$2:$A$416,A33,칸!$H$2:$H$416) | J33: =INDEX(비용표!$A$13:$A$17,MATCH(I33,비용표!$B$13:$B$17,1)) | K33: =INDEX(비용표!$C$13:$C$17,MATCH(I33,비용표!$B$13:$B$17,1)) | L33: 유비 함께 참전 시 헌제 HP+1 | M33: 능력치 | N33: 헌제 | O33: HP | P33: 1 | Q33: 유비
A34: 33 | B34: ③ 관도 (200~207) | C34: 토산의 세 가지 약속 | D34: 土山約三事 | E34: =INDEX(칸!$I$2:$I$416,MATCH(A34,칸!$A$2:$A$416,1)) | F34: 장료의 설득에 관우는 세 가지를 약속받고서야 항복했다. | G34: 하비에서 포위된 관우를 장료가 찾아와 설득했다. 관우는 한에 항복하되 조조에게 항복하지 않는다, 두 형수를 모신다, 유비의 소식을 들으면 떠난다 — 세 가지를 약속받고서야 칼을 내려놓았다. | H34: =COUNTIF(칸!$A$2:$A$416,A34) | I34: =SUMIF(칸!$A$2:$A$416,A34,칸!$H$2:$H$416) | J34: =INDEX(비용표!$A$13:$A$17,MATCH(I34,비용표!$B$13:$B$17,1)) | K34: =INDEX(비용표!$C$13:$C$17,MATCH(I34,비용표!$B$13:$B$17,1)) | L34: 장료 지력+1 | M34: 능력치 | N34: 장료 | O34: 지력 | P34: 1
A35: 34 | B35: ③ 관도 (200~207) | C35: 십승십패론 | D35: 十勝十敗論 | E35: =INDEX(칸!$I$2:$I$416,MATCH(A35,칸!$A$2:$A$416,1)) | F35: 곽가는 조조가 원소를 이길 열 가지 이유를 들었다. | G35: 원소의 오만한 편지에 조조가 근심하자, 곽가는 조조가 원소를 이길 열 가지와 원소가 질 열 가지를 들었다(『부자』). 도량 · 결단 · 용병 · 덕 — 그 말은 관도대전의 예언이 되었다. | H35: =COUNTIF(칸!$A$2:$A$416,A35) | I35: =SUMIF(칸!$A$2:$A$416,A35,칸!$H$2:$H$416) | J35: =INDEX(비용표!$A$13:$A$17,MATCH(I35,비용표!$B$13:$B$17,1)) | K35: =INDEX(비용표!$C$13:$C$17,MATCH(I35,비용표!$B$13:$B$17,1)) | L35: 곽가 통솔+2 | M35: 능력치 | N35: 곽가 | O35: 통솔 | P35: 2
A36: 35 | B36: ③ 관도 (200~207) | C36: 왕좌지재 | D36: 王佐之才 | E36: =INDEX(칸!$I$2:$I$416,MATCH(A36,칸!$A$2:$A$416,1)) | F36: 조조는 순욱을 「나의 자방」이라 불렀다. | G36: 조조는 원소를 떠나 찾아온 순욱을 보고 「나의 자방이 왔다」며 기뻐했다. 순욱은 조카 순유와 함께 조조의 모든 큰 결정에 함께했고, 허도를 지키며 천하를 경영했다. | H36: =COUNTIF(칸!$A$2:$A$416,A36) | I36: =SUMIF(칸!$A$2:$A$416,A36,칸!$H$2:$H$416) | J36: =INDEX(비용표!$A$13:$A$17,MATCH(I36,비용표!$B$13:$B$17,1)) | K36: =INDEX(비용표!$C$13:$C$17,MATCH(I36,비용표!$B$13:$B$17,1)) | L36: 순욱 함께 참전 시 순유 통솔+2 | M36: 능력치 | N36: 순유 | O36: 통솔 | P36: 2 | Q36: 순욱
A37: 36 | B37: ③ 관도 (200~207) | C37: 원소의 모사들 | D37: 袁紹謀士 | E37: =INDEX(칸!$I$2:$I$416,MATCH(A37,칸!$A$2:$A$416,1)) | F37: 책사는 넘쳤으나 주군은 끝내 어느 말도 듣지 않았다. | G37: 원소의 막하에는 전풍 · 저수 · 심배 · 봉기 · 곽도 · 허유가 있었으나 서로를 헐뜯었다. 원소는 옳은 말을 하는 자를 가두고 듣기 좋은 말만 들었으니, 책사는 많아도 계책은 없었다. | H37: =COUNTIF(칸!$A$2:$A$416,A37) | I37: =SUMIF(칸!$A$2:$A$416,A37,칸!$H$2:$H$416) | J37: =INDEX(비용표!$A$13:$A$17,MATCH(I37,비용표!$B$13:$B$17,1)) | K37: =INDEX(비용표!$C$13:$C$17,MATCH(I37,비용표!$B$13:$B$17,1)) | L37: 전풍·저수 함께 참전 시 전풍·저수 MP+1 | M37: 능력치 | N37: 전풍·저수 | O37: MP | P37: 1 | Q37: 전풍·저수
A38: 37 | B38: ③ 관도 (200~207) | C38: 하북의 두 기둥 | D38: 河北雙壁 | E38: =INDEX(칸!$I$2:$I$416,MATCH(A38,칸!$A$2:$A$416,1)) | F38: 원소군 최강의 두 장수. 둘이 함께면 당할 자가 없다 했다. | G38: 안량과 문추는 원소군을 대표하는 맹장으로 하북의 두 기둥이라 불렸다. 그러나 안량은 백마에서 관우에게, 문추는 연진에서 조조군에게 차례로 쓰러져 원소의 사기를 꺾었다. | H38: =COUNTIF(칸!$A$2:$A$416,A38) | I38: =SUMIF(칸!$A$2:$A$416,A38,칸!$H$2:$H$416) | J38: =INDEX(비용표!$A$13:$A$17,MATCH(I38,비용표!$B$13:$B$17,1)) | K38: =INDEX(비용표!$C$13:$C$17,MATCH(I38,비용표!$B$13:$B$17,1)) | L38: 안량·문추 함께 참전 시 안량·문추 무력+1 | M38: 능력치 | N38: 안량·문추 | O38: 무력 | P38: 1 | Q38: 안량·문추
A39: 38 | B39: ③ 관도 (200~207) | C39: 관도대전 | D39: 官渡之戰 | E39: =INDEX(칸!$I$2:$I$416,MATCH(A39,칸!$A$2:$A$416,1)) | F39: 관우는 안량과 문추를 단숨에 제압하고, 조조와 원소의 대결은 조조의 승리로 막을 내린다. | G39: 서기 200년, 원소의 십만 대군과 조조의 작은 군대가 관도에서 맞섰다. 관우가 백마에서 안량을 베고, 문추가 연진에서 쓰러졌으며, 조조는 끝내 오소를 불태워 북방의 패자가 되었다. | H39: =COUNTIF(칸!$A$2:$A$416,A39) | I39: =SUMIF(칸!$A$2:$A$416,A39,칸!$H$2:$H$416) | J39: =INDEX(비용표!$A$13:$A$17,MATCH(I39,비용표!$B$13:$B$17,1)) | K39: =INDEX(비용표!$C$13:$C$17,MATCH(I39,비용표!$B$13:$B$17,1)) | L39: 조조·관우 함께 참전, 적진에 안량·문추 시 관우 AT+0.5 | M39: 능력치 | N39: 관우 | O39: AT | P39: 0.5 | Q39: 조조·관우 | S39: 안량·문추
A40: 39 | B40: ③ 관도 (200~207) | C40: 오소 기습 | D40: 火燒烏巢 | E40: =INDEX(칸!$I$2:$I$416,MATCH(A40,칸!$A$2:$A$416,1)) | F40: 허유가 넘어오자 조조는 직접 오소의 군량고를 불태웠다. | G40: 관도의 대치가 길어지자 원소의 책사 허유가 조조에게 넘어와 오소의 군량고를 알렸다. 조조는 직접 오천 기를 이끌고 밤에 오소를 불태웠고, 지키던 순우경은 사로잡혔다. | H40: =COUNTIF(칸!$A$2:$A$416,A40) | I40: =SUMIF(칸!$A$2:$A$416,A40,칸!$H$2:$H$416) | J40: =INDEX(비용표!$A$13:$A$17,MATCH(I40,비용표!$B$13:$B$17,1)) | K40: =INDEX(비용표!$C$13:$C$17,MATCH(I40,비용표!$B$13:$B$17,1)) | L40: 최대 군량 +2 | M40: 도시 | P40: 2 | T40: grainCap
A41: 40 | B41: ③ 관도 (200~207) | C41: 오관참육장 | D41: 過五關斬六將 | E41: =INDEX(칸!$I$2:$I$416,MATCH(A41,칸!$A$2:$A$416,1)) | F41: 형님을 찾아 다섯 관문을 지나며 여섯 장수를 베었다. | G41: 유비의 소식을 들은 관우는 조조가 내린 재물을 봉해 두고 두 형수를 모셔 길을 떠났다. 통행증 없이 다섯 관문을 지나며 여섯 장수를 베었다 — 연의가 그린 관우의 천리행이다. | H41: =COUNTIF(칸!$A$2:$A$416,A41) | I41: =SUMIF(칸!$A$2:$A$416,A41,칸!$H$2:$H$416) | J41: =INDEX(비용표!$A$13:$A$17,MATCH(I41,비용표!$B$13:$B$17,1)) | K41: =INDEX(비용표!$C$13:$C$17,MATCH(I41,비용표!$B$13:$B$17,1)) | L41: 관우 통솔+2 | M41: 능력치 | N41: 관우 | O41: 통솔 | P41: 2
A42: 41 | B42: ③ 관도 (200~207) | C42: 고성의 재회 | D42: 古城相會 | E42: =INDEX(칸!$I$2:$I$416,MATCH(A42,칸!$A$2:$A$416,1)) | F42: 흩어졌던 형제와 장수들이 고성에서 다시 모였다. | G42: 여남을 떠돌던 유비, 고성을 차지한 장비, 천리를 달려온 관우가 마침내 고성에서 다시 만났다. 조운 · 주창 · 손건 · 간옹 · 미축도 모여들어, 흩어졌던 유비 집단이 다시 섰다. | H42: =COUNTIF(칸!$A$2:$A$416,A42) | I42: =SUMIF(칸!$A$2:$A$416,A42,칸!$H$2:$H$416) | J42: =INDEX(비용표!$A$13:$A$17,MATCH(I42,비용표!$B$13:$B$17,1)) | K42: =INDEX(비용표!$C$13:$C$17,MATCH(I42,비용표!$B$13:$B$17,1)) | L42: 관우 함께 참전 시 주창 통솔+2 | M42: 능력치 | N42: 주창 | O42: 통솔 | P42: 2 | Q42: 관우
A43: 42 | B43: ③ 관도 (200~207) | C43: 발시담정 | D43: 拔矢啖睛 | E43: =INDEX(칸!$I$2:$I$416,MATCH(A43,칸!$A$2:$A$416,1)) | F43: 눈에 박힌 화살을 뽑아 「부모의 정혈을 버릴 수 없다」며 삼켰다. | G43: 여포와 싸우던 하후돈은 조성의 화살에 왼눈을 맞았다. 연의는 그가 화살을 뽑으며 딸려 나온 눈알을 「부모의 정혈을 버릴 수 없다」며 삼키고 조성을 찔러 죽였다고 전한다. | H43: =COUNTIF(칸!$A$2:$A$416,A43) | I43: =SUMIF(칸!$A$2:$A$416,A43,칸!$H$2:$H$416) | J43: =INDEX(비용표!$A$13:$A$17,MATCH(I43,비용표!$B$13:$B$17,1)) | K43: =INDEX(비용표!$C$13:$C$17,MATCH(I43,비용표!$B$13:$B$17,1)) | L43: 하후돈 무력+1 | M43: 능력치 | N43: 하후돈 | O43: 무력 | P43: 1
A44: 43 | B44: ③ 관도 (200~207) | C44: 백랑산 | D44: 白狼山 | E44: =INDEX(칸!$I$2:$I$416,MATCH(A44,칸!$A$2:$A$416,1)) | F44: 먼 북방의 오환을 장료의 선봉이 무너뜨렸다. | G44: 원씨 형제가 오환으로 달아나자 조조는 곽가의 권유로 먼 북방 원정에 나섰다. 백랑산에서 장료가 선봉을 맡아 오환의 선우 답돈을 베고 북방을 평정했다. | H44: =COUNTIF(칸!$A$2:$A$416,A44) | I44: =SUMIF(칸!$A$2:$A$416,A44,칸!$H$2:$H$416) | J44: =INDEX(비용표!$A$13:$A$17,MATCH(I44,비용표!$B$13:$B$17,1)) | K44: =INDEX(비용표!$C$13:$C$17,MATCH(I44,비용표!$B$13:$B$17,1)) | L44: 장료 HP+1 | M44: 능력치 | N44: 장료 | O44: HP | P44: 1
A45: 44 | B45: ④ 형주 · 적벽 (201~209) | C45: 적로의 단계 도약 | D45: 躍馬檀溪 | E45: =INDEX(칸!$I$2:$I$416,MATCH(A45,칸!$A$2:$A$416,1)) | F45: 주인을 해친다는 흉마가 단계를 뛰어넘어 유비를 살렸다. | G45: 형주의 연회에서 채모가 자신을 해치려는 것을 알아챈 유비는 말을 몰아 달아났다. 단계의 급류에 막히자 「적로야, 오늘 나를 해치려느냐」 외쳤고, 적로는 세 길을 뛰어 건넜다. | H45: =COUNTIF(칸!$A$2:$A$416,A45) | I45: =SUMIF(칸!$A$2:$A$416,A45,칸!$H$2:$H$416) | J45: =INDEX(비용표!$A$13:$A$17,MATCH(I45,비용표!$B$13:$B$17,1)) | K45: =INDEX(비용표!$C$13:$C$17,MATCH(I45,비용표!$B$13:$B$17,1)) | L45: 유비 지력+2 | M45: 능력치 | N45: 유비 | O45: 지력 | P45: 2
A46: 45 | B46: ④ 형주 · 적벽 (201~209) | C46: 팔문금쇄진 | D46: 八門金鎖陣 | E46: =INDEX(칸!$I$2:$I$416,MATCH(A46,칸!$A$2:$A$416,1)) | F46: 서서는 조인의 진법을 한눈에 꿰뚫었다. | G46: 신야를 친 조인이 팔문금쇄진을 펼쳤으나 유비의 군사 서서가 한눈에 꿰뚫었다. 생문으로 들어가 경문으로 나오게 하니 진은 무너지고, 조인은 크게 패했다. | H46: =COUNTIF(칸!$A$2:$A$416,A46) | I46: =SUMIF(칸!$A$2:$A$416,A46,칸!$H$2:$H$416) | J46: =INDEX(비용표!$A$13:$A$17,MATCH(I46,비용표!$B$13:$B$17,1)) | K46: =INDEX(비용표!$C$13:$C$17,MATCH(I46,비용표!$B$13:$B$17,1)) | L46: 적진에 조인 시 서서 통솔+2 | M46: 능력치 | N46: 서서 | O46: 통솔 | P46: 2 | S46: 조인
A47: 46 | B47: ④ 형주 · 적벽 (201~209) | C47: 서서의 어머니 | D47: 徐母之書 | E47: =INDEX(칸!$I$2:$I$416,MATCH(A47,칸!$A$2:$A$416,1)) | F47: 거짓 편지 한 통에 서서는 유비를 떠났고 평생 계책을 내지 않았다. | G47: 조조는 서서를 얻으려고 그 어머니를 잡아 두었다. 연의에서는 정욱이 어머니의 필적을 흉내 낸 가짜 편지를 보냈고, 서서는 떠나며 제갈량을 천거하고 평생 조조에게 계책을 내지 않았다. | H47: =COUNTIF(칸!$A$2:$A$416,A47) | I47: =SUMIF(칸!$A$2:$A$416,A47,칸!$H$2:$H$416) | J47: =INDEX(비용표!$A$13:$A$17,MATCH(I47,비용표!$B$13:$B$17,1)) | K47: =INDEX(비용표!$C$13:$C$17,MATCH(I47,비용표!$B$13:$B$17,1)) | L47: 정욱 MP+1 | M47: 능력치 | N47: 정욱 | O47: MP | P47: 1
A48: 47 | B48: ④ 형주 · 적벽 (201~209) | C48: 삼고초려 | D48: 三顧草廬 | E48: =INDEX(칸!$I$2:$I$416,MATCH(A48,칸!$A$2:$A$416,1)) | F48: 세 번 찾아간 끝에 와룡이 융중을 나섰다. | G48: 서서의 천거로 유비는 관우 · 장비와 함께 융중의 초가를 찾았다. 두 번 허탕을 치고 눈보라 속에 세 번째 찾아가서야 제갈량을 만났고, 와룡은 비로소 산을 나섰다. | H48: =COUNTIF(칸!$A$2:$A$416,A48) | I48: =SUMIF(칸!$A$2:$A$416,A48,칸!$H$2:$H$416) | J48: =INDEX(비용표!$A$13:$A$17,MATCH(I48,비용표!$B$13:$B$17,1)) | K48: =INDEX(비용표!$C$13:$C$17,MATCH(I48,비용표!$B$13:$B$17,1)) | L48: 유비의 「삼고초려」 SP 6 → 5 | M48: 고유기술SP | N48: 유비 | P48: -1
A49: 48 | B49: ④ 형주 · 적벽 (201~209) | C49: 박망파의 불 | D49: 火燒博望坡 | E49: =INDEX(칸!$I$2:$I$416,MATCH(A49,칸!$A$2:$A$416,1)) | F49: 출사 후 첫 계책. 박망파의 갈대숲이 불타올랐다. | G49: 하후돈이 신야로 쳐들어오자, 출사 직후의 제갈량이 박망파의 갈대숲에 불을 놓았다. 관우 · 장비 · 조운이 길목을 끊으니 하후돈은 크게 패했고, 관우 · 장비는 그제야 제갈량을 믿었다. | H49: =COUNTIF(칸!$A$2:$A$416,A49) | I49: =SUMIF(칸!$A$2:$A$416,A49,칸!$H$2:$H$416) | J49: =INDEX(비용표!$A$13:$A$17,MATCH(I49,비용표!$B$13:$B$17,1)) | K49: =INDEX(비용표!$C$13:$C$17,MATCH(I49,비용표!$B$13:$B$17,1)) | L49: 제갈량 MP+1 | M49: 능력치 | N49: 제갈량 | O49: MP | P49: 1
A50: 49 | B50: ④ 형주 · 적벽 (201~209) | C50: 형주의 항복 | D50: 荊州投降 | E50: =INDEX(칸!$I$2:$I$416,MATCH(A50,칸!$A$2:$A$416,1)) | F50: 유표가 죽자 채모는 어린 유종을 앞세워 형주를 조조에게 바쳤다. | G50: 유표가 죽자 채모와 괴월은 어린 유종을 세우고 형주를 조조에게 바쳤다. 싸우지 않고 형주를 얻은 조조는 유비를 쫓아 남으로 내려왔다. | H50: =COUNTIF(칸!$A$2:$A$416,A50) | I50: =SUMIF(칸!$A$2:$A$416,A50,칸!$H$2:$H$416) | J50: =INDEX(비용표!$A$13:$A$17,MATCH(I50,비용표!$B$13:$B$17,1)) | K50: =INDEX(비용표!$C$13:$C$17,MATCH(I50,비용표!$B$13:$B$17,1)) | L50: 채모 지력+1 | M50: 능력치 | N50: 채모 | O50: 지력 | P50: 1
A51: 50 | B51: ④ 형주 · 적벽 (201~209) | C51: 장판파 단기구주 | D51: 長坂坡單騎救主 | E51: =INDEX(칸!$I$2:$I$416,MATCH(A51,칸!$A$2:$A$416,1)) | F51: 조운은 아두를 품고 조조의 백만 대군 사이를 홀로 지났다. | G51: 장판에서 조조군에 따라잡혀 유비의 가솔이 흩어졌다. 조운은 홀로 적진을 오가며 어린 아두를 품에 안고 빠져나왔고, 그 길에 하후은의 청강검을 빼앗았다. | H51: =COUNTIF(칸!$A$2:$A$416,A51) | I51: =SUMIF(칸!$A$2:$A$416,A51,칸!$H$2:$H$416) | J51: =INDEX(비용표!$A$13:$A$17,MATCH(I51,비용표!$B$13:$B$17,1)) | K51: =INDEX(비용표!$C$13:$C$17,MATCH(I51,비용표!$B$13:$B$17,1)) | L51: 조운 통솔+2 | M51: 능력치 | N51: 조운 | O51: 통솔 | P51: 2
A52: 51 | B52: ④ 형주 · 적벽 (201~209) | C52: 장판교의 일갈 | D52: 長坂橋喝 | E52: =INDEX(칸!$I$2:$I$416,MATCH(A52,칸!$A$2:$A$416,1)) | F52: 「내가 연인 장익덕이다!」 — 하후걸은 그 소리에 말에서 떨어졌다. | G52: 장판교에 홀로 선 장비가 장팔사모를 비껴들고 「내가 연인 장익덕이다!」 외쳤다. 하후걸이 놀라 말에서 떨어지자 조조군은 다리 앞에서 물러났고, 장비는 다리를 끊고 돌아갔다. | H52: =COUNTIF(칸!$A$2:$A$416,A52) | I52: =SUMIF(칸!$A$2:$A$416,A52,칸!$H$2:$H$416) | J52: =INDEX(비용표!$A$13:$A$17,MATCH(I52,비용표!$B$13:$B$17,1)) | K52: =INDEX(비용표!$C$13:$C$17,MATCH(I52,비용표!$B$13:$B$17,1)) | L52: 장비의 「장판하뢰」 SP 6 → 5 | M52: 고유기술SP | N52: 장비 | P52: -1
A53: 52 | B53: ④ 형주 · 적벽 (201~209) | C53: 상옥추제 | D53: 上屋抽梯 | E53: =INDEX(칸!$I$2:$I$416,MATCH(A53,칸!$A$2:$A$416,1)) | F53: 누각에 오르자 사다리가 치워졌다. 유기는 그제야 살 길을 물었다. | G53: 계모 채씨의 견제에 목숨이 위태롭던 유표의 장자 유기는 제갈량을 누각으로 이끌고 사다리를 치웠다. 그제야 제갈량은 「밖으로 나가 강하를 지키라」는 계책을 일러 주었다. | H53: =COUNTIF(칸!$A$2:$A$416,A53) | I53: =SUMIF(칸!$A$2:$A$416,A53,칸!$H$2:$H$416) | J53: =INDEX(비용표!$A$13:$A$17,MATCH(I53,비용표!$B$13:$B$17,1)) | K53: =INDEX(비용표!$C$13:$C$17,MATCH(I53,비용표!$B$13:$B$17,1)) | L53: 유기 HP+1 | M53: 능력치 | N53: 유기 | O53: HP | P53: 1
A54: 53 | B54: ④ 형주 · 적벽 (201~209) | C54: 노숙의 합종 | D54: 魯肅聯劉 | E54: =INDEX(칸!$I$2:$I$416,MATCH(A54,칸!$A$2:$A$416,1)) | F54: 조문을 핑계로 형주에 온 노숙은 유비와 손을 잡자 했다. | G54: 유표의 조문을 핑계로 형주에 온 노숙은 장판에서 쫓기던 유비를 만나 손권과 손을 잡자 했다. 그 길로 제갈량이 노숙을 따라 강동으로 건너가니, 적벽의 동맹이 여기서 시작되었다. | H54: =COUNTIF(칸!$A$2:$A$416,A54) | I54: =SUMIF(칸!$A$2:$A$416,A54,칸!$H$2:$H$416) | J54: =INDEX(비용표!$A$13:$A$17,MATCH(I54,비용표!$B$13:$B$17,1)) | K54: =INDEX(비용표!$C$13:$C$17,MATCH(I54,비용표!$B$13:$B$17,1)) | L54: 노숙 지력+1 | M54: 능력치 | N54: 노숙 | O54: 지력 | P54: 1
A55: 54 | B55: ④ 형주 · 적벽 (201~209) | C55: 설전군유 | D55: 舌戰群儒 | E55: =INDEX(칸!$I$2:$I$416,MATCH(A55,칸!$A$2:$A$416,1)) | F55: 항복을 주장하는 강동의 선비들을 제갈량이 말로 꺾었다. | G55: 항복을 주장하는 강동의 선비들이 시상에 온 제갈량을 둘러싸고 따져 물었다. 장소 · 우번 · 보즐 · 설종 · 육적 · 엄준이 차례로 나섰으나, 제갈량은 하나하나 말로 꺾었다. | H55: =COUNTIF(칸!$A$2:$A$416,A55) | I55: =SUMIF(칸!$A$2:$A$416,A55,칸!$H$2:$H$416) | J55: =INDEX(비용표!$A$13:$A$17,MATCH(I55,비용표!$B$13:$B$17,1)) | K55: =INDEX(비용표!$C$13:$C$17,MATCH(I55,비용표!$B$13:$B$17,1)) | L55: 태학 연구 시간 −5% | M55: 도시 | P55: 5 | T55: research
A56: 55 | B56: ④ 형주 · 적벽 (201~209) | C56: 책상을 베다 | D56: 斫案決戰 | E56: =INDEX(칸!$I$2:$I$416,MATCH(A56,칸!$A$2:$A$416,1)) | F56: 「다시 항복을 말하는 자는 이 책상과 같으리라.」 | G56: 조조의 대군 앞에서 조정이 항복론으로 기울자, 손권은 칼을 뽑아 책상 모서리를 베었다. 「다시 항복을 말하는 자는 이 책상과 같으리라」 — 강동은 싸우기로 했다. | H56: =COUNTIF(칸!$A$2:$A$416,A56) | I56: =SUMIF(칸!$A$2:$A$416,A56,칸!$H$2:$H$416) | J56: =INDEX(비용표!$A$13:$A$17,MATCH(I56,비용표!$B$13:$B$17,1)) | K56: =INDEX(비용표!$C$13:$C$17,MATCH(I56,비용표!$B$13:$B$17,1)) | L56: 손권 지력+1 | M56: 능력치 | N56: 손권 | O56: 지력 | P56: 1
A57: 56 | B57: ④ 형주 · 적벽 (201~209) | C57: 군영회 | D57: 群英會 | E57: =INDEX(칸!$I$2:$I$416,MATCH(A57,칸!$A$2:$A$416,1)) | F57: 술 취한 척 흘린 가짜 편지 한 통에 수군 도독 둘이 목을 잃었다. | G57: 조조의 사자로 온 옛 친구 장간을 주유는 반갑게 맞아 군영회를 열었다. 취한 척 잠든 주유 곁에서 장간은 채모 · 장윤의 가짜 내통 편지를 훔쳐 갔고, 조조는 수군 도독 둘을 베었다. | H57: =COUNTIF(칸!$A$2:$A$416,A57) | I57: =SUMIF(칸!$A$2:$A$416,A57,칸!$H$2:$H$416) | J57: =INDEX(비용표!$A$13:$A$17,MATCH(I57,비용표!$B$13:$B$17,1)) | K57: =INDEX(비용표!$C$13:$C$17,MATCH(I57,비용표!$B$13:$B$17,1)) | L57: 주유 통솔+1 | M57: 능력치 | N57: 주유 | O57: 통솔 | P57: 1
A58: 57 | B58: ④ 형주 · 적벽 (201~209) | C58: 초선차전 | D58: 草船借箭 | E58: =INDEX(칸!$I$2:$I$416,MATCH(A58,칸!$A$2:$A$416,1)) | F58: 안개 낀 강에 풀배를 띄워 사흘 만에 화살 십만 개를 얻었다. | G58: 주유가 열흘 안에 화살 십만 개를 만들라 하자 제갈량은 사흘이면 된다고 했다. 안개 낀 밤 짚단을 세운 배 스무 척으로 조조의 수채에 다가가 북을 울리니, 화살이 배마다 가득 꽂혔다. | H58: =COUNTIF(칸!$A$2:$A$416,A58) | I58: =SUMIF(칸!$A$2:$A$416,A58,칸!$H$2:$H$416) | J58: =INDEX(비용표!$A$13:$A$17,MATCH(I58,비용표!$B$13:$B$17,1)) | K58: =INDEX(비용표!$C$13:$C$17,MATCH(I58,비용표!$B$13:$B$17,1)) | L58: 대장간 제조 시간 −10% | M58: 도시 | P58: 10 | T58: forge
A59: 58 | B59: ④ 형주 · 적벽 (201~209) | C59: 고육지책 | D59: 苦肉計 | E59: =INDEX(칸!$I$2:$I$416,MATCH(A59,칸!$A$2:$A$416,1)) | F59: 때리는 자와 맞는 자가 짜고 친 계책. 감택이 항서를 날랐다. | G59: 조조를 속이려고 주유와 황개가 짜고 군령을 어긴 황개를 곤장으로 쳤다. 살이 터진 황개의 항서를 감택이 들고 가 조조를 믿게 했다 — 제 몸을 해쳐 적을 속인 계책이다. | H59: =COUNTIF(칸!$A$2:$A$416,A59) | I59: =SUMIF(칸!$A$2:$A$416,A59,칸!$H$2:$H$416) | J59: =INDEX(비용표!$A$13:$A$17,MATCH(I59,비용표!$B$13:$B$17,1)) | K59: =INDEX(비용표!$C$13:$C$17,MATCH(I59,비용표!$B$13:$B$17,1)) | L59: 주유 함께 참전 시 황개 HP+2 | M59: 능력치 | N59: 황개 | O59: HP | P59: 2 | Q59: 주유
A60: 59 | B60: ④ 형주 · 적벽 (201~209) | C60: 방통의 연환계 | D60: 連環計 | E60: =INDEX(칸!$I$2:$I$416,MATCH(A60,칸!$A$2:$A$416,1)) | F60: 배를 쇠사슬로 묶으면 뱃멀미가 없다 — 그리고 불도 피할 수 없다. | G60: 배멀미로 고생하는 조조에게 방통이 찾아와 배를 쇠사슬로 묶으라 권했다. 배는 땅처럼 단단해졌으나 불이 붙으면 피할 길이 없었다 — 적벽의 불은 여기서 이미 준비되었다. | H60: =COUNTIF(칸!$A$2:$A$416,A60) | I60: =SUMIF(칸!$A$2:$A$416,A60,칸!$H$2:$H$416) | J60: =INDEX(비용표!$A$13:$A$17,MATCH(I60,비용표!$B$13:$B$17,1)) | K60: =INDEX(비용표!$C$13:$C$17,MATCH(I60,비용표!$B$13:$B$17,1)) | L60: 방통 MP+1 | M60: 능력치 | N60: 방통 | O60: MP | P60: 1
A61: 60 | B61: ④ 형주 · 적벽 (201~209) | C61: 칠성단의 동남풍 | D61: 七星壇祭風 | E61: =INDEX(칸!$I$2:$I$416,MATCH(A61,칸!$A$2:$A$416,1)) | F61: 깃털 부채를 든 제갈량이 칠성단에서 동남풍을 빌렸다. 바람이 일자 주유는 정봉과 서성을 보내 그를 쫓았다. | G61: 화공을 쓰려면 동남풍이 필요했다. 제갈량은 칠성단을 쌓고 바람을 빌었고, 겨울 강에 바람이 돌자 주유는 그를 두려워해 정봉 · 서성을 보냈으나 제갈량은 이미 배를 타고 떠난 뒤였다. | H61: =COUNTIF(칸!$A$2:$A$416,A61) | I61: =SUMIF(칸!$A$2:$A$416,A61,칸!$H$2:$H$416) | J61: =INDEX(비용표!$A$13:$A$17,MATCH(I61,비용표!$B$13:$B$17,1)) | K61: =INDEX(비용표!$C$13:$C$17,MATCH(I61,비용표!$B$13:$B$17,1)) | L61: 제갈량의 「차동풍」 SP 6 → 5 | M61: 고유기술SP | N61: 제갈량 | P61: -1
A62: 61 | B62: ④ 형주 · 적벽 (201~209) | C62: 적벽대전 | D62: 赤壁大戰 | E62: =INDEX(칸!$I$2:$I$416,MATCH(A62,칸!$A$2:$A$416,1)) | F62: 동남풍을 탄 불배가 조조의 대함대를 삼켰다. | G62: 서기 208년, 동남풍을 탄 황개의 불배가 쇠사슬에 묶인 조조의 함대를 들이받았다. 불길은 강북의 진영까지 번졌고, 백만을 일컫던 조조군은 화용도로 달아났다. | H62: =COUNTIF(칸!$A$2:$A$416,A62) | I62: =SUMIF(칸!$A$2:$A$416,A62,칸!$H$2:$H$416) | J62: =INDEX(비용표!$A$13:$A$17,MATCH(I62,비용표!$B$13:$B$17,1)) | K62: =INDEX(비용표!$C$13:$C$17,MATCH(I62,비용표!$B$13:$B$17,1)) | L62: 주유·제갈량 함께 참전 시 진영 SP +1로 시작 | M62: 진영SP | P62: 1 | Q62: 주유·제갈량
A63: 62 | B63: ④ 형주 · 적벽 (201~209) | C63: 화용도 | D63: 華容道 | E63: =INDEX(칸!$I$2:$I$416,MATCH(A63,칸!$A$2:$A$416,1)) | F63: 옛 은혜를 잊지 못한 관우는 화용도에서 길을 열었다. | G63: 적벽에서 진 조조가 화용도의 진흙길로 달아나자 관우가 길을 막았다. 옛 은혜를 말하는 조조 앞에서 관우는 차마 칼을 들지 못하고 말머리를 돌렸다고 연의는 전한다. | H63: =COUNTIF(칸!$A$2:$A$416,A63) | I63: =SUMIF(칸!$A$2:$A$416,A63,칸!$H$2:$H$416) | J63: =INDEX(비용표!$A$13:$A$17,MATCH(I63,비용표!$B$13:$B$17,1)) | K63: =INDEX(비용표!$C$13:$C$17,MATCH(I63,비용표!$B$13:$B$17,1)) | L63: 적진에 관우 시 조조 HP+1 | M63: 능력치 | N63: 조조 | O63: HP | P63: 1 | S63: 관우
A64: 63 | B64: ④ 형주 · 적벽 (201~209) | C64: 남군 공방 | D64: 南郡攻防 | E64: =INDEX(칸!$I$2:$I$416,MATCH(A64,칸!$A$2:$A$416,1)) | F64: 조인은 주유의 공세를 버텼고, 주유는 이 싸움에서 화살을 맞았다. | G64: 적벽 뒤 주유는 조인이 지키는 남군을 일 년 넘게 공격했다. 조인은 끝까지 버티다 물러났고, 주유는 이 싸움에서 맞은 화살의 상처를 끝내 낫지 못했다. | H64: =COUNTIF(칸!$A$2:$A$416,A64) | I64: =SUMIF(칸!$A$2:$A$416,A64,칸!$H$2:$H$416) | J64: =INDEX(비용표!$A$13:$A$17,MATCH(I64,비용표!$B$13:$B$17,1)) | K64: =INDEX(비용표!$C$13:$C$17,MATCH(I64,비용표!$B$13:$B$17,1)) | L64: 조인 통솔+2 | M64: 능력치 | N64: 조인 | O64: 통솔 | P64: 2
A65: 64 | B65: ④ 형주 · 적벽 (201~209) | C65: 삼기주유 | D65: 三氣周瑜 | E65: =INDEX(칸!$I$2:$I$416,MATCH(A65,칸!$A$2:$A$416,1)) | F65: 「既生瑜 何生亮」 — 하늘은 주유를 낳고 어찌 제갈량을 또 낳았는가. 세 번 꾀에 넘어간 주유가 숨을 거두며 남긴 말. | G65: 연의에서 주유는 제갈량의 꾀에 세 번 넘어가 분을 이기지 못했다. 마지막 화살 상처가 터진 주유는 「既生瑜 何生亮」 — 하늘은 주유를 낳고 어찌 제갈량을 또 낳았는가 — 탄식하며 숨을 거두었다. | H65: =COUNTIF(칸!$A$2:$A$416,A65) | I65: =SUMIF(칸!$A$2:$A$416,A65,칸!$H$2:$H$416) | J65: =INDEX(비용표!$A$13:$A$17,MATCH(I65,비용표!$B$13:$B$17,1)) | K65: =INDEX(비용표!$C$13:$C$17,MATCH(I65,비용표!$B$13:$B$17,1)) | L65: 적진에 제갈량 시 주유 HP+1 | M65: 능력치 | N65: 주유 | O65: HP | P65: 1 | S65: 제갈량
A66: 65 | B66: ⑤ 삼국 정립 (209~219) | C66: 장사의 노장 | D66: 長沙老將 | E66: =INDEX(칸!$I$2:$I$416,MATCH(A66,칸!$A$2:$A$416,1)) | F66: 예순의 황충은 관우와 겨뤄 우열을 가리지 못했다. | G66: 장사를 치러 온 관우 앞에 예순의 노장 황충이 나섰다. 백 합을 겨뤄도 승부가 나지 않았다. 말이 넘어진 황충을 관우가 베지 않자, 이튿날 황충은 화살로 관우의 투구 끈만 맞혀 은혜를 갚았다. | H66: =COUNTIF(칸!$A$2:$A$416,A66) | I66: =SUMIF(칸!$A$2:$A$416,A66,칸!$H$2:$H$416) | J66: =INDEX(비용표!$A$13:$A$17,MATCH(I66,비용표!$B$13:$B$17,1)) | K66: =INDEX(비용표!$C$13:$C$17,MATCH(I66,비용표!$B$13:$B$17,1)) | L66: 적진에 관우 시 황충 무력+2 | M66: 능력치 | N66: 황충 | O66: 무력 | P66: 2 | S66: 관우
A67: 66 | B67: ⑤ 삼국 정립 (209~219) | C67: 감로사 | D67: 甘露寺 | E67: =INDEX(칸!$I$2:$I$416,MATCH(A67,칸!$A$2:$A$416,1)) | F67: 미인계로 붙잡으려던 혼인이 진짜 혼인이 되었다. | G67: 주유는 손권의 누이와의 혼인을 미끼로 유비를 오에 붙잡아 두려 했다. 그러나 감로사에서 유비를 본 손권의 모친 오국태가 마음에 들어 해, 거짓 혼인은 진짜 혼인이 되었다. | H67: =COUNTIF(칸!$A$2:$A$416,A67) | I67: =SUMIF(칸!$A$2:$A$416,A67,칸!$H$2:$H$416) | J67: =INDEX(비용표!$A$13:$A$17,MATCH(I67,비용표!$B$13:$B$17,1)) | K67: =INDEX(비용표!$C$13:$C$17,MATCH(I67,비용표!$B$13:$B$17,1)) | L67: 유비 함께 참전 시 손권 HP+1 | M67: 능력치 | N67: 손권 | O67: HP | P67: 1 | Q67: 유비
A68: 67 | B68: ⑤ 삼국 정립 (209~219) | C68: 동작대부 | D68: 銅雀臺賦 | E68: =INDEX(칸!$I$2:$I$416,MATCH(A68,칸!$A$2:$A$416,1)) | F68: 붓을 들면 그대로 문장이 되었다는 조식의 노래. | G68: 조조가 업에 동작대를 세우고 아들들에게 부를 짓게 하자 조식이 붓을 들어 단숨에 써 내려갔다. 그 재주에 조조는 조식을 후계자로 생각할 만큼 아꼈다. | H68: =COUNTIF(칸!$A$2:$A$416,A68) | I68: =SUMIF(칸!$A$2:$A$416,A68,칸!$H$2:$H$416) | J68: =INDEX(비용표!$A$13:$A$17,MATCH(I68,비용표!$B$13:$B$17,1)) | K68: =INDEX(비용표!$C$13:$C$17,MATCH(I68,비용표!$B$13:$B$17,1)) | L68: 조식 지력+2 | M68: 능력치 | N68: 조식 | O68: 지력 | P68: 2
A69: 68 | B69: ⑤ 삼국 정립 (209~219) | C69: 동관의 마초 | D69: 潼關馬超 | E69: =INDEX(칸!$I$2:$I$416,MATCH(A69,칸!$A$2:$A$416,1)) | F69: 아비의 원수를 갚으러 온 마초 앞에서 조조는 수염을 잘라 도망쳤다. | G69: 아버지 마등을 죽인 조조에게 복수하러 마초가 동관을 쳤다. 마초에게 쫓긴 조조는 붉은 전포를 벗고 수염까지 잘라 도망쳤고, 허저가 배를 저어 겨우 강을 건넜다. | H69: =COUNTIF(칸!$A$2:$A$416,A69) | I69: =SUMIF(칸!$A$2:$A$416,A69,칸!$H$2:$H$416) | J69: =INDEX(비용표!$A$13:$A$17,MATCH(I69,비용표!$B$13:$B$17,1)) | K69: =INDEX(비용표!$C$13:$C$17,MATCH(I69,비용표!$B$13:$B$17,1)) | L69: 마대 함께 참전 시 마초 HP+2 | M69: 능력치 | N69: 마초 | O69: HP | P69: 2 | Q69: 마대
A70: 69 | B70: ⑤ 삼국 정립 (209~219) | C70: 서천 지도 | D70: 西川地圖 | E70: =INDEX(칸!$I$2:$I$416,MATCH(A70,칸!$A$2:$A$416,1)) | F70: 장송이 바친 지도 한 장에 익주의 길이 모두 그려져 있었다. | G70: 익주의 별가 장송은 조조에게 홀대받고 돌아오는 길에 유비를 만났다. 그는 익주의 산천과 관문을 그린 지도를 바치며 법정 · 맹달과 함께 유비를 익주로 맞으려 했다. | H70: =COUNTIF(칸!$A$2:$A$416,A70) | I70: =SUMIF(칸!$A$2:$A$416,A70,칸!$H$2:$H$416) | J70: =INDEX(비용표!$A$13:$A$17,MATCH(I70,비용표!$B$13:$B$17,1)) | K70: =INDEX(비용표!$C$13:$C$17,MATCH(I70,비용표!$B$13:$B$17,1)) | L70: 도적떼 응전 시간 +1분 | M70: 도시 | P70: 1 | T70: raidResp
A71: 70 | B71: ⑤ 삼국 정립 (209~219) | C71: 낙봉파 | D71: 落鳳坡 | E71: =INDEX(칸!$I$2:$I$416,MATCH(A71,칸!$A$2:$A$416,1)) | F71: 유비의 흰 말을 빌려 탄 봉추는 장임의 화살에 쓰러졌다. | G71: 익주로 진군하던 방통은 낙봉파의 좁은 골짜기를 지났다. 유비에게 빌린 흰 말을 탄 그를 장임의 복병이 유비로 알고 화살을 퍼부으니, 봉추는 서른여섯에 쓰러졌다. | H71: =COUNTIF(칸!$A$2:$A$416,A71) | I71: =SUMIF(칸!$A$2:$A$416,A71,칸!$H$2:$H$416) | J71: =INDEX(비용표!$A$13:$A$17,MATCH(I71,비용표!$B$13:$B$17,1)) | K71: =INDEX(비용표!$C$13:$C$17,MATCH(I71,비용표!$B$13:$B$17,1)) | L71: 적진에 방통 시 장임 무력+2 | M71: 능력치 | N71: 장임 | O71: 무력 | P71: 2 | S71: 방통
A72: 71 | B72: ⑤ 삼국 정립 (209~219) | C72: 의석 엄안 | D72: 義釋嚴顏 | E72: =INDEX(칸!$I$2:$I$416,MATCH(A72,칸!$A$2:$A$416,1)) | F72: 「목을 칠 장군은 있어도 항복할 장군은 없다」 — 장비는 그 앞에 무릎을 꿇었다. | G72: 파군을 친 장비에게 사로잡힌 노장 엄안은 「목을 칠 장군은 있어도 항복할 장군은 없다」고 꾸짖었다. 장비는 그 기개에 감복해 몸소 포승을 풀고 윗자리에 앉혔다. | H72: =COUNTIF(칸!$A$2:$A$416,A72) | I72: =SUMIF(칸!$A$2:$A$416,A72,칸!$H$2:$H$416) | J72: =INDEX(비용표!$A$13:$A$17,MATCH(I72,비용표!$B$13:$B$17,1)) | K72: =INDEX(비용표!$C$13:$C$17,MATCH(I72,비용표!$B$13:$B$17,1)) | L72: 장비 함께 참전 시 엄안 HP+2 | M72: 능력치 | N72: 엄안 | O72: HP | P72: 2 | Q72: 장비
A73: 72 | B73: ⑤ 삼국 정립 (209~219) | C73: 가맹관 야전 | D73: 葭萌關夜戰 | E73: =INDEX(칸!$I$2:$I$416,MATCH(A73,칸!$A$2:$A$416,1)) | F73: 횃불을 밝히고 밤새 싸웠으나 장비와 마초는 승부를 내지 못했다. | G73: 가맹관에서 장비와 마초가 맞붙었다. 해가 지자 횃불을 밝히고 밤새 싸웠으나 승부가 나지 않았고, 마초는 얼마 뒤 유비에게 귀순했다. | H73: =COUNTIF(칸!$A$2:$A$416,A73) | I73: =SUMIF(칸!$A$2:$A$416,A73,칸!$H$2:$H$416) | J73: =INDEX(비용표!$A$13:$A$17,MATCH(I73,비용표!$B$13:$B$17,1)) | K73: =INDEX(비용표!$C$13:$C$17,MATCH(I73,비용표!$B$13:$B$17,1)) | L73: 적진에 장비 시 마초 무력+1 | M73: 능력치 | N73: 마초 | O73: 무력 | P73: 1 | S73: 장비
A74: 73 | B74: ⑤ 삼국 정립 (209~219) | C74: 익주의 유장 | D74: 益州劉璋 | E74: =INDEX(칸!$I$2:$I$416,MATCH(A74,칸!$A$2:$A$416,1)) | F74: 어진 주인이었으나 난세를 지킬 그릇은 아니었다. | G74: 유장은 아버지 유언에게서 익주를 물려받은 어진 주인이었으나, 장로를 막으려 유비를 불러들였다. 황권 · 왕루가 목숨을 걸고 말렸지만 듣지 않았고, 결국 익주를 잃었다. | H74: =COUNTIF(칸!$A$2:$A$416,A74) | I74: =SUMIF(칸!$A$2:$A$416,A74,칸!$H$2:$H$416) | J74: =INDEX(비용표!$A$13:$A$17,MATCH(I74,비용표!$B$13:$B$17,1)) | K74: =INDEX(비용표!$C$13:$C$17,MATCH(I74,비용표!$B$13:$B$17,1)) | L74: 황권 통솔+1 | M74: 능력치 | N74: 황권 | O74: 통솔 | P74: 1
A75: 74 | B75: ⑤ 삼국 정립 (209~219) | C75: 단도부회 | D75: 單刀赴會 | E75: =INDEX(칸!$I$2:$I$416,MATCH(A75,칸!$A$2:$A$416,1)) | F75: 칼 한 자루만 들고 적진의 연회에 나간 관우. | G75: 형주를 돌려 달라는 노숙의 초대에 관우는 칼 한 자루와 주창만 데리고 육구의 연회에 나갔다. 노숙의 손을 잡고 배까지 걸어 나오니, 매복한 군사들이 손을 쓰지 못했다. | H75: =COUNTIF(칸!$A$2:$A$416,A75) | I75: =SUMIF(칸!$A$2:$A$416,A75,칸!$H$2:$H$416) | J75: =INDEX(비용표!$A$13:$A$17,MATCH(I75,비용표!$B$13:$B$17,1)) | K75: =INDEX(비용표!$C$13:$C$17,MATCH(I75,비용표!$B$13:$B$17,1)) | L75: 적진에 관우 시 노숙 통솔+2 | M75: 능력치 | N75: 노숙 | O75: 통솔 | P75: 2 | S75: 관우
A76: 75 | B76: ⑤ 삼국 정립 (209~219) | C76: 유수구 | D76: 濡須口 | E76: =INDEX(칸!$I$2:$I$416,MATCH(A76,칸!$A$2:$A$416,1)) | F76: 「자식을 낳으려면 손중모 같아야 한다.」 | G76: 유수구에서 손권과 대치한 조조는 오군의 정연한 진영을 보고 탄식했다. 「자식을 낳으려면 손중모 같아야 한다. 유경승의 아들은 개돼지일 뿐이다.」 | H76: =COUNTIF(칸!$A$2:$A$416,A76) | I76: =SUMIF(칸!$A$2:$A$416,A76,칸!$H$2:$H$416) | J76: =INDEX(비용표!$A$13:$A$17,MATCH(I76,비용표!$B$13:$B$17,1)) | K76: =INDEX(비용표!$C$13:$C$17,MATCH(I76,비용표!$B$13:$B$17,1)) | L76: 손권 통솔+2 | M76: 능력치 | N76: 손권 | O76: 통솔 | P76: 2
A77: 76 | B77: ⑤ 삼국 정립 (209~219) | C77: 빈 찬합 | D77: 空食盒 | E77: =INDEX(칸!$I$2:$I$416,MATCH(A77,칸!$A$2:$A$416,1)) | F77: 조조가 보낸 찬합은 비어 있었다. 순욱은 그날 밤 약을 마셨다. | G77: 조조가 위공의 자리에 오르려 하자 순욱은 반대했다. 얼마 뒤 조조가 보낸 찬합을 열어 보니 텅 비어 있었고, 순욱은 그 뜻을 알고 약을 마셨다고 전한다. | H77: =COUNTIF(칸!$A$2:$A$416,A77) | I77: =SUMIF(칸!$A$2:$A$416,A77,칸!$H$2:$H$416) | J77: =INDEX(비용표!$A$13:$A$17,MATCH(I77,비용표!$B$13:$B$17,1)) | K77: =INDEX(비용표!$C$13:$C$17,MATCH(I77,비용표!$B$13:$B$17,1)) | L77: 순욱 통솔+1 | M77: 능력치 | N77: 순욱 | O77: 통솔 | P77: 1
A78: 77 | B78: ⑤ 삼국 정립 (209~219) | C78: 백기겁위영 | D78: 百騎劫魏營 | E78: =INDEX(칸!$I$2:$I$416,MATCH(A78,칸!$A$2:$A$416,1)) | F78: 기병 백 명으로 조조의 진영을 휘젓고 한 명도 잃지 않았다. | G78: 유수구에서 감녕은 기병 백 명을 이끌고 밤에 조조의 진영을 휘저었다. 한 사람도 잃지 않고 돌아오자 손권은 「맹덕에게 장료가 있다면 내게는 감녕이 있다」고 했다. | H78: =COUNTIF(칸!$A$2:$A$416,A78) | I78: =SUMIF(칸!$A$2:$A$416,A78,칸!$H$2:$H$416) | J78: =INDEX(비용표!$A$13:$A$17,MATCH(I78,비용표!$B$13:$B$17,1)) | K78: =INDEX(비용표!$C$13:$C$17,MATCH(I78,비용표!$B$13:$B$17,1)) | L78: 감녕 통솔+2 | M78: 능력치 | N78: 감녕 | O78: 통솔 | P78: 2
A79: 78 | B79: ⑤ 삼국 정립 (209~219) | C79: 합비 소요진 | D79: 逍遙津 | E79: =INDEX(칸!$I$2:$I$416,MATCH(A79,칸!$A$2:$A$416,1)) | F79: 팔백 기로 십만을 꺾었다. 강동의 아이들은 그 이름에 울음을 그쳤다. | G79: 손권이 십만으로 합비를 치자 장료는 팔백 명을 뽑아 새벽에 돌격했다. 소요진에서 손권은 다리가 끊겨 말을 뛰어 겨우 달아났고, 강동의 아이들은 장료의 이름만 들어도 울음을 그쳤다. | H79: =COUNTIF(칸!$A$2:$A$416,A79) | I79: =SUMIF(칸!$A$2:$A$416,A79,칸!$H$2:$H$416) | J79: =INDEX(비용표!$A$13:$A$17,MATCH(I79,비용표!$B$13:$B$17,1)) | K79: =INDEX(비용표!$C$13:$C$17,MATCH(I79,비용표!$B$13:$B$17,1)) | L79: 장료의 「장료지제」 SP 6 → 5 | M79: 고유기술SP | N79: 장료 | P79: -1
A80: 79 | B80: ⑤ 삼국 정립 (209~219) | C80: 괄목상대 | D80: 刮目相待 | E80: =INDEX(칸!$I$2:$I$416,MATCH(A80,칸!$A$2:$A$416,1)) | F80: 「선비는 사흘을 떨어져 있으면 눈을 비비고 다시 보아야 한다.」 | G80: 무예만 알던 여몽은 손권의 권유로 책을 읽기 시작했다. 훗날 노숙이 그와 이야기하고 놀라자 여몽은 「선비는 사흘을 떨어져 있으면 눈을 비비고 다시 보아야 한다」고 답했다. | H80: =COUNTIF(칸!$A$2:$A$416,A80) | I80: =SUMIF(칸!$A$2:$A$416,A80,칸!$H$2:$H$416) | J80: =INDEX(비용표!$A$13:$A$17,MATCH(I80,비용표!$B$13:$B$17,1)) | K80: =INDEX(비용표!$C$13:$C$17,MATCH(I80,비용표!$B$13:$B$17,1)) | L80: 여몽 지력+1 | M80: 능력치 | N80: 여몽 | O80: 지력 | P80: 1
A81: 80 | B81: ⑤ 삼국 정립 (209~219) | C81: 정군산 | D81: 定軍山 | E81: =INDEX(칸!$I$2:$I$416,MATCH(A81,칸!$A$2:$A$416,1)) | F81: 법정이 깃발을 흔들자 황충이 산을 내려와 하후연을 베었다. | G81: 한중을 두고 다툰 정군산에서 법정이 산 위에서 깃발을 흔들자, 노장 황충이 북을 울리며 내려와 하후연을 베었다. 이 싸움으로 유비는 한중을 얻었다. | H81: =COUNTIF(칸!$A$2:$A$416,A81) | I81: =SUMIF(칸!$A$2:$A$416,A81,칸!$H$2:$H$416) | J81: =INDEX(비용표!$A$13:$A$17,MATCH(I81,비용표!$B$13:$B$17,1)) | K81: =INDEX(비용표!$C$13:$C$17,MATCH(I81,비용표!$B$13:$B$17,1)) | L81: 황충의 「백보천양」 SP 6 → 5 | M81: 고유기술SP | N81: 황충 | P81: -1
A82: 81 | B82: ⑤ 삼국 정립 (209~219) | C82: 계륵 | D82: 鷄肋 | E82: =INDEX(칸!$I$2:$I$416,MATCH(A82,칸!$A$2:$A$416,1)) | F82: 「계륵이다.」 — 그 암호를 듣고 짐을 싼 양수는 조조의 속을 너무 잘 알았다. | G82: 한중에서 나아가지도 물러나지도 못하던 조조가 그날 밤 암호를 「계륵」이라 했다. 양수가 「먹을 것은 없으나 버리기는 아깝다는 뜻」이라며 짐을 싸자, 조조는 군심을 어지럽혔다며 그를 베었다. | H82: =COUNTIF(칸!$A$2:$A$416,A82) | I82: =SUMIF(칸!$A$2:$A$416,A82,칸!$H$2:$H$416) | J82: =INDEX(비용표!$A$13:$A$17,MATCH(I82,비용표!$B$13:$B$17,1)) | K82: =INDEX(비용표!$C$13:$C$17,MATCH(I82,비용표!$B$13:$B$17,1)) | L82: 양수 지력+2 | M82: 능력치 | N82: 양수 | O82: 지력 | P82: 2
A83: 82 | B83: ⑤ 삼국 정립 (209~219) | C83: 수엄칠군 | D83: 水淹七軍 | E83: =INDEX(칸!$I$2:$I$416,MATCH(A83,칸!$A$2:$A$416,1)) | F83: 불어난 한수가 우금의 일곱 군을 삼켰다. | G83: 관우가 번성을 포위하자 조조는 우금에게 칠군을 주어 구원하게 했다. 때마침 큰비로 한수가 넘치자 관우는 배를 타고 들이쳐 우금을 사로잡았다. 관우의 위엄이 천하를 떨게 했다. | H83: =COUNTIF(칸!$A$2:$A$416,A83) | I83: =SUMIF(칸!$A$2:$A$416,A83,칸!$H$2:$H$416) | J83: =INDEX(비용표!$A$13:$A$17,MATCH(I83,비용표!$B$13:$B$17,1)) | K83: =INDEX(비용표!$C$13:$C$17,MATCH(I83,비용표!$B$13:$B$17,1)) | L83: 관우 지력+2 | M83: 능력치 | N83: 관우 | O83: 지력 | P83: 2
A84: 83 | B84: ⑤ 삼국 정립 (209~219) | C84: 관을 멘 방덕 | D84: 抬櫬決戰 | E84: =INDEX(칸!$I$2:$I$416,MATCH(A84,칸!$A$2:$A$416,1)) | F84: 관을 짊어지고 나선 방덕은 끝내 무릎 꿇지 않았다. | G84: 방덕은 관우와 싸우러 나서며 관을 짊어지고 가 죽기를 각오했다. 관우와 백 합을 겨뤘으나 칠군이 물에 잠긴 뒤 사로잡혔고, 끝내 무릎 꿇지 않고 죽었다. | H84: =COUNTIF(칸!$A$2:$A$416,A84) | I84: =SUMIF(칸!$A$2:$A$416,A84,칸!$H$2:$H$416) | J84: =INDEX(비용표!$A$13:$A$17,MATCH(I84,비용표!$B$13:$B$17,1)) | K84: =INDEX(비용표!$C$13:$C$17,MATCH(I84,비용표!$B$13:$B$17,1)) | L84: 적진에 관우 시 방덕 HP+2 | M84: 능력치 | N84: 방덕 | O84: HP | P84: 2 | S84: 관우
A85: 84 | B85: ⑤ 삼국 정립 (209~219) | C85: 백의도강 | D85: 白衣渡江 | E85: =INDEX(칸!$I$2:$I$416,MATCH(A85,칸!$A$2:$A$416,1)) | F85: 흰옷의 상인으로 꾸민 병사들이 강을 건너 형주를 빼앗았다. | G85: 여몽은 병을 핑계로 물러나 육손에게 자리를 넘겼다. 관우가 방심하자 병사들을 흰옷의 상인으로 꾸며 강을 건너게 했고, 봉화대를 소리 없이 장악해 형주를 빼앗았다. | H85: =COUNTIF(칸!$A$2:$A$416,A85) | I85: =SUMIF(칸!$A$2:$A$416,A85,칸!$H$2:$H$416) | J85: =INDEX(비용표!$A$13:$A$17,MATCH(I85,비용표!$B$13:$B$17,1)) | K85: =INDEX(비용표!$C$13:$C$17,MATCH(I85,비용표!$B$13:$B$17,1)) | L85: 여몽의 「백의도강」 SP 6 → 5 | M85: 고유기술SP | N85: 여몽 | P85: -1
A86: 85 | B86: ⑤ 삼국 정립 (209~219) | C86: 맥성 | D86: 走麥城 | E86: =INDEX(칸!$I$2:$I$416,MATCH(A86,칸!$A$2:$A$416,1)) | F86: 구원은 오지 않았고 관우 부자는 맥성을 빠져나가지 못했다. | G86: 형주를 잃은 관우는 맥성으로 몰렸다. 요화가 상용의 유봉 · 맹달에게 구원을 청했으나 그들은 오지 않았다. 관우 부자는 성을 빠져나가다 임저에서 사로잡혔다. | H86: =COUNTIF(칸!$A$2:$A$416,A86) | I86: =SUMIF(칸!$A$2:$A$416,A86,칸!$H$2:$H$416) | J86: =INDEX(비용표!$A$13:$A$17,MATCH(I86,비용표!$B$13:$B$17,1)) | K86: =INDEX(비용표!$C$13:$C$17,MATCH(I86,비용표!$B$13:$B$17,1)) | L86: 관우 함께 참전 시 관평·주창 HP+1 | M86: 능력치 | N86: 관평·주창 | O86: HP | P86: 1 | Q86: 관우
A87: 86 | B87: ⑥ 이릉 · 남정 (220~225) | C87: 수선대 | D87: 受禪臺 | E87: =INDEX(칸!$I$2:$I$416,MATCH(A87,칸!$A$2:$A$416,1)) | F87: 사백 년 한나라가 수선대 위에서 끝났다. | G87: 조조가 죽자 아들 조비는 헌제를 압박해 수선대에서 제위를 넘겨받았다. 사백 년 한나라가 끝나고 위가 섰다. | H87: =COUNTIF(칸!$A$2:$A$416,A87) | I87: =SUMIF(칸!$A$2:$A$416,A87,칸!$H$2:$H$416) | J87: =INDEX(비용표!$A$13:$A$17,MATCH(I87,비용표!$B$13:$B$17,1)) | K87: =INDEX(비용표!$C$13:$C$17,MATCH(I87,비용표!$B$13:$B$17,1)) | L87: 조비 지력+2 | M87: 능력치 | N87: 조비 | O87: 지력 | P87: 2
A88: 87 | B88: ⑥ 이릉 · 남정 (220~225) | C88: 칠보시 | D88: 七步詩 | E88: =INDEX(칸!$I$2:$I$416,MATCH(A88,칸!$A$2:$A$416,1)) | F88: 「콩깍지를 태워 콩을 삶으니」 — 일곱 걸음 안에 지은 시. | G88: 조비는 아우 조식을 시기해, 일곱 걸음 안에 시를 짓지 못하면 죽이겠다고 했다. 조식이 「콩깍지를 태워 콩을 삶으니」라고 읊자 조비는 부끄러워 그를 놓아주었다. | H88: =COUNTIF(칸!$A$2:$A$416,A88) | I88: =SUMIF(칸!$A$2:$A$416,A88,칸!$H$2:$H$416) | J88: =INDEX(비용표!$A$13:$A$17,MATCH(I88,비용표!$B$13:$B$17,1)) | K88: =INDEX(비용표!$C$13:$C$17,MATCH(I88,비용표!$B$13:$B$17,1)) | L88: 적진에 조비 시 조식 HP+2 | M88: 능력치 | N88: 조식 | O88: HP | P88: 2 | S88: 조비
A89: 88 | B89: ⑥ 이릉 · 남정 (220~225) | C89: 아버지의 원수 | D89: 關興張苞 | E89: =INDEX(칸!$I$2:$I$416,MATCH(A89,칸!$A$2:$A$416,1)) | F89: 관우와 장비의 아들들은 의형제의 맹세까지 물려받았다. | G89: 관우와 장비가 죽은 뒤, 두 사람의 아들 관흥과 장포는 아버지들처럼 의형제를 맺었다. 둘은 이릉으로 가는 유비를 따라 아버지의 원수를 갚으러 나섰다. | H89: =COUNTIF(칸!$A$2:$A$416,A89) | I89: =SUMIF(칸!$A$2:$A$416,A89,칸!$H$2:$H$416) | J89: =INDEX(비용표!$A$13:$A$17,MATCH(I89,비용표!$B$13:$B$17,1)) | K89: =INDEX(비용표!$C$13:$C$17,MATCH(I89,비용표!$B$13:$B$17,1)) | L89: 관흥·장포 함께 참전 시 관흥·장포 무력+1 | M89: 능력치 | N89: 관흥·장포 | O89: 무력 | P89: 1 | Q89: 관흥·장포
A90: 89 | B90: ⑥ 이릉 · 남정 (220~225) | C90: 오계의 만왕 | D90: 沙摩柯 | E90: =INDEX(칸!$I$2:$I$416,MATCH(A90,칸!$A$2:$A$416,1)) | F90: 이릉의 길에서 사마가의 화살이 감녕을 쓰러뜨렸다. | G90: 유비의 동정에 무릉의 오계만왕 사마가가 군사를 이끌고 합류했다. 연의는 그의 화살이 오의 맹장 감녕을 쓰러뜨렸다고 전한다. | H90: =COUNTIF(칸!$A$2:$A$416,A90) | I90: =SUMIF(칸!$A$2:$A$416,A90,칸!$H$2:$H$416) | J90: =INDEX(비용표!$A$13:$A$17,MATCH(I90,비용표!$B$13:$B$17,1)) | K90: =INDEX(비용표!$C$13:$C$17,MATCH(I90,비용표!$B$13:$B$17,1)) | L90: 적진에 감녕 시 사마가 무력+2 | M90: 능력치 | N90: 사마가 | O90: 무력 | P90: 2 | S90: 감녕
A91: 90 | B91: ⑥ 이릉 · 남정 (220~225) | C91: 이릉대전 | D91: 夷陵之戰 | E91: =INDEX(칸!$I$2:$I$416,MATCH(A91,칸!$A$2:$A$416,1)) | F91: 칠백 리 연영이 하룻밤 불길에 사라졌다. | G91: 관우의 원수를 갚으려 유비는 대군을 이끌고 오를 쳤다. 육손은 맞서지 않고 버티다가, 무더위에 숲속에 칠백 리로 늘어선 촉의 진영에 일제히 불을 질렀다. | H91: =COUNTIF(칸!$A$2:$A$416,A91) | I91: =SUMIF(칸!$A$2:$A$416,A91,칸!$H$2:$H$416) | J91: =INDEX(비용표!$A$13:$A$17,MATCH(I91,비용표!$B$13:$B$17,1)) | K91: =INDEX(비용표!$C$13:$C$17,MATCH(I91,비용표!$B$13:$B$17,1)) | L91: 육손의 「화소연영」 SP 6 → 5 | M91: 고유기술SP | N91: 육손 | P91: -1
A92: 91 | B92: ⑥ 이릉 · 남정 (220~225) | C92: 백제성 탁고 | D92: 白帝城託孤 | E92: =INDEX(칸!$I$2:$I$416,MATCH(A92,칸!$A$2:$A$416,1)) | F92: 「그대의 재주가 조비의 열 배다. 아들이 모자라면 그대가 취하라.」 | G92: 이릉에서 진 유비는 백제성에서 병들어 제갈량을 불렀다. 「아들이 보좌할 만하면 돕고, 그렇지 못하면 그대가 취하라.」 제갈량은 울며 죽을 때까지 충성하겠다고 답했다. | H92: =COUNTIF(칸!$A$2:$A$416,A92) | I92: =SUMIF(칸!$A$2:$A$416,A92,칸!$H$2:$H$416) | J92: =INDEX(비용표!$A$13:$A$17,MATCH(I92,비용표!$B$13:$B$17,1)) | K92: =INDEX(비용표!$C$13:$C$17,MATCH(I92,비용표!$B$13:$B$17,1)) | L92: 제갈량 함께 참전 시 유선 HP+2 | M92: 능력치 | N92: 유선 | O92: HP | P92: 2 | Q92: 제갈량
A93: 92 | B93: ⑥ 이릉 · 남정 (220~225) | C93: 서성의 가짜 성벽 | D93: 徐盛疑城 | E93: =INDEX(칸!$I$2:$I$416,MATCH(A93,칸!$A$2:$A$416,1)) | F93: 하룻밤 새 세운 갈대 성벽에 조비의 대군이 물러갔다. | G93: 조비가 대군으로 광릉에 이르자, 서성은 강가에 갈대와 나무로 수백 리의 가짜 성벽을 하룻밤에 세웠다. 조비는 그 위용에 놀라 「위에 무사가 천 명 있어도 쓸 데가 없다」며 물러났다. | H93: =COUNTIF(칸!$A$2:$A$416,A93) | I93: =SUMIF(칸!$A$2:$A$416,A93,칸!$H$2:$H$416) | J93: =INDEX(비용표!$A$13:$A$17,MATCH(I93,비용표!$B$13:$B$17,1)) | K93: =INDEX(비용표!$C$13:$C$17,MATCH(I93,비용표!$B$13:$B$17,1)) | L93: 서성 지력+1 | M93: 능력치 | N93: 서성 | O93: 지력 | P93: 1
A94: 93 | B94: ⑥ 이릉 · 남정 (220~225) | C94: 칠종칠금 | D94: 七縱七擒 | E94: =INDEX(칸!$I$2:$I$416,MATCH(A94,칸!$A$2:$A$416,1)) | F94: 일곱 번 잡고 일곱 번 놓아주니 남만이 마음으로 복종했다. | G94: 남만의 맹획이 반란을 일으키자 제갈량은 직접 남정에 나섰다. 일곱 번 사로잡고 일곱 번 놓아주니, 맹획은 마침내 마음으로 복종했다. 연의에서는 축융 부인과 오란도 나선다. | H94: =COUNTIF(칸!$A$2:$A$416,A94) | I94: =SUMIF(칸!$A$2:$A$416,A94,칸!$H$2:$H$416) | J94: =INDEX(비용표!$A$13:$A$17,MATCH(I94,비용표!$B$13:$B$17,1)) | K94: =INDEX(비용표!$C$13:$C$17,MATCH(I94,비용표!$B$13:$B$17,1)) | L94: 축융·오란 함께 참전 시 축융·오란 통솔+1 | M94: 능력치 | N94: 축융·오란 | O94: 통솔 | P94: 1 | Q94: 축융·오란
A95: 94 | B95: ⑥ 이릉 · 남정 (220~225) | C95: 출사표 | D95: 出師表 | E95: =INDEX(칸!$I$2:$I$416,MATCH(A95,칸!$A$2:$A$416,1)) | F95: 「신은 본래 포의로서 남양에서 몸소 밭을 갈았습니다.」 | G95: 남만을 평정한 제갈량은 북벌을 앞두고 어린 황제 유선에게 표문을 올렸다. 「신은 본래 포의로서 남양에서 몸소 밭을 갈았습니다」로 시작하는 출사표는 충신의 글로 천 년을 전해졌다. | H95: =COUNTIF(칸!$A$2:$A$416,A95) | I95: =SUMIF(칸!$A$2:$A$416,A95,칸!$H$2:$H$416) | J95: =INDEX(비용표!$A$13:$A$17,MATCH(I95,비용표!$B$13:$B$17,1)) | K95: =INDEX(비용표!$C$13:$C$17,MATCH(I95,비용표!$B$13:$B$17,1)) | L95: 군량 충전 속도 +5% | M95: 도시 | P95: 5 | T95: grainRate
A96: 95 | B96: ⑥ 이릉 · 남정 (220~225) | C96: 오두미도 | D96: 五斗米道 | E96: =INDEX(칸!$I$2:$I$416,MATCH(A96,칸!$A$2:$A$416,1)) | F96: 쌀 다섯 말을 바치면 병을 고쳐 준다던 한중의 교단. | G96: 장로는 한중에서 오두미도를 이끌었다. 병든 자를 고치고 쌀 다섯 말을 받았으며, 길가에 의사(義舍)를 세워 나그네에게 쌀과 고기를 내주었다. 조조에게 항복할 때도 창고를 봉하고 떠났다. | H96: =COUNTIF(칸!$A$2:$A$416,A96) | I96: =SUMIF(칸!$A$2:$A$416,A96,칸!$H$2:$H$416) | J96: =INDEX(비용표!$A$13:$A$17,MATCH(I96,비용표!$B$13:$B$17,1)) | K96: =INDEX(비용표!$C$13:$C$17,MATCH(I96,비용표!$B$13:$B$17,1)) | L96: 병원 치료 시간 −5% | M96: 도시 | P96: 5 | T96: heal
A97: 96 | B97: ⑦ 북벌 (227~234) | C97: 천수의 강유 | D97: 天水姜維 | E97: =INDEX(칸!$I$2:$I$416,MATCH(A97,칸!$A$2:$A$416,1)) | F97: 제갈량의 계략을 꿰뚫은 젊은 장수는 그대로 그의 제자가 되었다. | G97: 첫 북벌에서 제갈량의 계략을 꿰뚫은 천수의 젊은 장수가 있었다. 제갈량은 그 재주를 아껴 계책으로 그를 얻었고, 강유는 그대로 제갈량의 제자가 되었다. | H97: =COUNTIF(칸!$A$2:$A$416,A97) | I97: =SUMIF(칸!$A$2:$A$416,A97,칸!$H$2:$H$416) | J97: =INDEX(비용표!$A$13:$A$17,MATCH(I97,비용표!$B$13:$B$17,1)) | K97: =INDEX(비용표!$C$13:$C$17,MATCH(I97,비용표!$B$13:$B$17,1)) | L97: 강유 통솔+2 | M97: 능력치 | N97: 강유 | O97: 통솔 | P97: 2
A98: 97 | B98: ⑦ 북벌 (227~234) | C98: 가정 | D98: 街亭 | E98: =INDEX(칸!$I$2:$I$416,MATCH(A98,칸!$A$2:$A$416,1)) | F98: 왕평은 산 위에 진을 치지 말라 했다. | G98: 제갈량은 가정을 지키는 중임을 마속에게 맡겼다. 마속은 「산 위에 진을 치지 말라」는 왕평의 말을 듣지 않았고, 장합에게 물길을 끊겨 대패했다. 첫 북벌은 여기서 무너졌다. | H98: =COUNTIF(칸!$A$2:$A$416,A98) | I98: =SUMIF(칸!$A$2:$A$416,A98,칸!$H$2:$H$416) | J98: =INDEX(비용표!$A$13:$A$17,MATCH(I98,비용표!$B$13:$B$17,1)) | K98: =INDEX(비용표!$C$13:$C$17,MATCH(I98,비용표!$B$13:$B$17,1)) | L98: 마속 함께 참전 시 왕평 지력+2 | M98: 능력치 | N98: 왕평 | O98: 지력 | P98: 2 | Q98: 마속
A99: 98 | B99: ⑦ 북벌 (227~234) | C99: 공성계 | D99: 空城計 | E99: =INDEX(칸!$I$2:$I$416,MATCH(A99,칸!$A$2:$A$416,1)) | F99: 성문을 활짝 열고 성루에서 거문고를 탔다. | G99: 가정을 잃고 서성에 남은 제갈량에게 사마의의 대군이 몰려왔다. 제갈량은 성문을 활짝 열고 성루에서 거문고를 탔고, 복병을 의심한 사마의는 물러났다고 연의는 전한다. | H99: =COUNTIF(칸!$A$2:$A$416,A99) | I99: =SUMIF(칸!$A$2:$A$416,A99,칸!$H$2:$H$416) | J99: =INDEX(비용표!$A$13:$A$17,MATCH(I99,비용표!$B$13:$B$17,1)) | K99: =INDEX(비용표!$C$13:$C$17,MATCH(I99,비용표!$B$13:$B$17,1)) | L99: 적진에 사마의 시 제갈량 HP+1 | M99: 능력치 | N99: 제갈량 | O99: HP | P99: 1 | S99: 사마의
A100: 99 | B100: ⑦ 북벌 (227~234) | C100: 진창 수성 | D100: 陳倉守城 | E100: =INDEX(칸!$I$2:$I$416,MATCH(A100,칸!$A$2:$A$416,1)) | F100: 천여 명으로 수만의 촉군을 스무 날 넘게 막아 냈다. | G100: 두 번째 북벌에서 제갈량은 진창성을 쳤다. 지키는 학소는 천여 명뿐이었으나 운제와 충차를 불화살과 돌로 막아 스무 날 넘게 버텼고, 제갈량은 군량이 떨어져 물러났다. | H100: =COUNTIF(칸!$A$2:$A$416,A100) | I100: =SUMIF(칸!$A$2:$A$416,A100,칸!$H$2:$H$416) | J100: =INDEX(비용표!$A$13:$A$17,MATCH(I100,비용표!$B$13:$B$17,1)) | K100: =INDEX(비용표!$C$13:$C$17,MATCH(I100,비용표!$B$13:$B$17,1)) | L100: 학소 HP+2 | M100: 능력치 | N100: 학소 | O100: HP | P100: 2
...

Sheet 한글 제목
A1: # | B1: 타이틀 | C1: 한글 제목
A2: 1 | B2: 도원결의 | C2: 도원결의
A3: 2 | B3: 황건적 토벌 | C3: 황건적 토벌
A4: 3 | B4: 온주참화웅 | C4: 술이 식기 전에
A5: 4 | B5: 호뢰관 삼영전여포 | C5: 세 영웅, 여포와 싸우다
A6: 5 | B6: 반동탁 연합군 | C6: 열여덟 제후, 동탁을 치다
A7: 6 | B7: 장안 천도 | C7: 불타는 낙양
A8: 7 | B8: 칠성보도 헌상 | C8: 조조, 동탁을 노리다
A9: 8 | B9: 진궁의 결별 | C9: 진궁, 조조를 떠나다
A10: 9 | B10: 형양의 추격 | C10: 조홍, 말을 내주다
A11: 10 | B11: 손견과 전국옥새 | C11: 우물 속의 옥새
A12: 11 | B12: 현산의 손견 | C12: 강동의 호랑이 지다
A13: 12 | B13: 백마의종 | C13: 흰 말의 기병대
... A118: 117 | B118: 형주의 유표 | C118: 두 아들 사이에서

Sheet 다국어
A1: # | B1: 타이틀 | C1: 제목_en | D1: 설명_en | E1: 상세_en | F1: 제목_ja | G1: 설명_ja | H1: 상세_ja | I1: 제목_zh_Hant | J1: 설명_zh_Hant | K1: 상세_zh_Hant | L1: 제목_zh_Hans | M1: 설명_zh_Hans | N1: 상세_zh_Hans | O1: 제목_pt_BR | P1: 설명_pt_BR | Q1: 상세_pt_BR | R1: 제목_pt_PT | S1: 설명_pt_PT | T1: 상세_pt_PT | U1: 제목_it | V1: 설명_it | W1: 상세_it | X1: 제목_es_419 | Y1: 설명_es_419 | Z1: 상세_es_419 | AA1: 제목_mn | AB1: 설명_mn | AC1: 상세_mn | AD1: 한자_zh_Hans
A2: 1 | B2: 도원결의 | C2: Oath of the Peach Garden | D2: Where the saga begins. Three men, it is said, swore brotherhood in a garden of peach trees. | E2: In the year the Yellow Turbans rose, Liu Bei, Guan Yu and Zhang Fei of Zhuo swore brotherhood in the peach orchard behind Zhang Fei's house. “We were not born on the same day, but we hope to die on the same day” — that oath bound the three for the rest of their lives. | F2: 桃園の誓い | G2: 三国志のはじまり。三人は桃の咲く庭で義兄弟の契りを結んだという。 | H2: 黄巾の乱が起きた年、涿県の劉備・関羽・張飛は、張飛の屋敷裏の桃園で義兄弟の契りを結んだ。同じ日に生まれることはできなかったが、同じ日に死なんことを願う――その誓いが三人の生涯を結びつけた。 | I2: 桃園三結義 | J2: 三國故事的開端。相傳三人在桃花盛開的園中結為異姓兄弟。 | K2: 黃巾起事那年，涿縣的劉備、關羽、張飛在張飛家後院的桃園結為兄弟。「不求同年同月同日生，但願同年同月同日死」，這句誓言繫住了三人的一生。 | L2: 桃园结义 | M2: 三国故事由此开始。相传三人在桃花园中结为异姓兄弟。 | N2: 黄巾起事那一年，涿县的刘备、关羽、张飞在张飞家后院的桃园中结为兄弟。「不求同年同月同日生，但求同年同月同日死」，这句誓言系住了三人的一生。 | O2: Juramento do Jardim de Pessegueiros | P2: O começo de tudo. Dizem que três homens se tornaram irmãos de juramento num jardim de pessegueiros. | Q2: No ano em que os Turbantes Amarelos se ergueram, Liu Bei, Guan Yu e Zhang Fei, de Zhuo, juraram irmandade no pomar de pessegueiros atrás da casa de Zhang Fei. Não nasceram no mesmo dia, mas desejaram morrer no mesmo dia — e esse juramento uniu os três pelo resto da vida. | R2: Juramento do Jardim dos Pessegueiros | S2: O início dos Três Reinos. Conta-se que três homens se juraram irmãos num jardim de pessegueiros. | T2: No ano em que os Turbantes Amarelos se levantaram, Liu Bei, Guan Yu e Zhang Fei, de Zhuoxian, juraram-se irmãos no pomar de pessegueiros atrás da casa de Zhang Fei. Não tinham nascido no mesmo dia, mas desejavam morrer no mesmo dia — e esse juramento uniu-os para toda a vida. | U2: Il giuramento del giardino dei peschi | V2: L'inizio dei Tre Regni. Si narra che tre uomini giurarono fratellanza in un giardino di peschi. | W2: Nell'anno in cui insorsero i Turbanti Gialli, a Zhuo, Liu Bei, Guan Yu e Zhang Fei si giurarono fratelli nel frutteto di peschi dietro la casa di Zhang Fei. «Non nati nello stesso giorno, ma uniti nel morire nello stesso giorno»: quel giuramento legò le loro vite per sempre. | X2: El juramento del jardín de melocotoneros | Y2: Aquí empieza la historia. Dicen que tres hombres se juraron hermanos en un jardín de melocotoneros. | Z2: El año en que se alzaron los Turbantes Amarillos, Liu Bei, Guan Yu y Zhang Fei, de Zhuo, se juraron hermanos en el huerto de melocotoneros detrás de la casa de Zhang Fei. «No nacimos el mismo día, pero deseamos morir el mismo día»: ese juramento ató a los tres para toda la vida. | AA2: Тоорын цэцэрлэгийн тангараг | AB2: Гурван улсын түүхийн эхлэл. Гурван эр тоорын цэцэрлэгт ах дүүс болохоор тангарагласан гэдэг. | AC2: Шар алчууртны бослого гарсан жил Чжосяний Лю Бэй, Гуань Юй, Чжан Фэй гурав Чжан Фэйн гэрийн арын тоорын цэцэрлэгт ах дүүсийн тангараг өргөв. «Нэг өдөр төрөөгүй ч нэг өдөр үхэхийг хүснэ» гэсэн тангараг гурвын насан туршийг холбосон юм. | AD2: 桃园结义
A3: 2 | B3: 황건적 토벌 | C3: Against the Yellow Turbans | D3: A rebellion raised by Zhang Jue of the Way of Great Peace. Three men who would one day divide the realm stood on the same battlefield. | E3: Zhang Jue, master of the Way of Great Peace, declared that “the Azure Heaven is already dead” and raised hundreds of thousands of followers. Among the imperial troops and volunteers sent against him were Liu Bei, Cao Cao and Sun Jian — the first battlefield of the men who would split the realm in three. | F3: 黄巾賊を討つ | G3: 太平道の張角が起こした乱。のちに天下を分ける三人が、同じ戦場に立った。 | H3: 太平道の教祖・張角が「蒼天すでに死す」と唱え、数十万の信徒を蜂起させた。討伐に出た官軍と義勇兵の中に、劉備・曹操・孫堅がいた――のちに天下を三つに分ける者たちの、最初の戦場である。 | I3: 討伐黃巾賊 | J3: 太平道張角掀起的大亂。日後三分天下的三人，站上了同一片戰場。 | K3: 太平道教主張角高喊「蒼天已死」，聚起數十萬信徒。前往討伐的官軍與義兵之中，有劉備、曹操、孫堅——這是日後三分天下之人的第一片戰場。 | L3: 讨伐黄巾贼 | M3: 太平道张角掀起的大乱。日后三分天下的三人，站上了同一片战场。 | N3: 太平道教主张角喊出「苍天已死」，聚起数十万信众。出征讨伐的官军与义兵之中，有刘备、曹操与孙坚——这是日后三分天下之人的第一战。 | O3: Contra os Turbantes Amarelos | P3: A revolta de Zhang Jiao, do Caminho da Grande Paz. Os três que um dia dividiriam o império lutaram no mesmo campo. | Q3: Zhang Jiao, mestre do Caminho da Grande Paz, proclamou que “o Céu Azul já está morto” e levantou centenas de milhares de fiéis. Entre as tropas imperiais e voluntários que marcharam contra ele estavam Liu Bei, Cao Cao e Sun Jian — o primeiro campo de batalha dos que dividiriam o império em três. | R3: Contra os Turbantes Amarelos | S3: A rebelião lançada por Zhang Jiao, do Caminho da Grande Paz. Os três que um dia dividiriam o império lutaram no mesmo campo de batalha. | T3: Zhang Jiao, mestre do Caminho da Grande Paz, proclamou «o Céu Azul já está morto» e levantou centenas de milhares de fiéis. Entre as tropas imperiais e os voluntários que os combateram estavam Liu Bei, Cao Cao e Sun Jian — o primeiro campo de batalha dos que um dia dividiriam o império em três. | U3: La rivolta dei Turbanti Gialli | V3: La rivolta scatenata da Zhang Jue della Via della Grande Pace. I tre che un giorno si sarebbero spartiti l'impero combatterono sullo stesso campo. | W3: Zhang Jue, capo della Via della Grande Pace, sollevò centinaia di migliaia di seguaci proclamando che «il Cielo Azzurro è già morto». Tra le truppe imperiali e i volontari accorsi a reprimerli c'erano Liu Bei, Cao Cao e Sun Jian: fu il primo campo di battaglia di coloro che avrebbero diviso l'impero in tre. | X3: Contra los Turbantes Amarillos | Y3: La rebelión de Zhang Jue, del Camino de la Gran Paz. Tres hombres que algún día dividirían el reino pisaron el mismo campo de batalla. | Z3: Zhang Jue, maestro del Camino de la Gran Paz, proclamó que «el Cielo Azul ya ha muerto» y levantó a cientos de miles de seguidores. Entre las tropas imperiales y los voluntarios enviados contra él estaban Liu Bei, Cao Cao y Sun Jian: el primer campo de batalla de quienes partirían el reino en tres. | AA3: Шар алчууртныг дарах нь | AB3: Тайпиндаогийн Чжан Цзюэгийн босгосон самуун. Хожим тэнгэрийн дорыг хуваах гурван эр нэг тулааны талбарт зогсов. | AC3: Тайпиндаогийн тэргүүн Чжан Цзюэ «Хөх тэнгэр аль хэдийн үхсэн» хэмээн хэдэн зуун мянган шүтэгчээ босгов. Дарахаар мордсон төрийн цэрэг ба сайн дурынхны дунд Лю Бэй, Цао Цао, Сунь Цзянь байв — хожим тэнгэрийн дорыг гурав хуваах эрсийн анхны тулаан энэ юм. | AD3: 讨黄巾贼
A4: 3 | B4: 온주참화웅 | C4: Before the Wine Grew Cold | D4: He returned with Hua Xiong's head before the warmed wine had cooled. | E4: Before Sishui Pass, Dong Zhuo's champion Hua Xiong cut down one allied officer after another, until Guan Yu, then a mere mounted archer, stepped forward. The Romance tells that he returned with Hua Xiong's head before the warm wine Cao Cao had poured for him had cooled. | F4: 酒が冷めぬうちに | G4: 温めた酒が冷めぬうちに、華雄の首を斬って戻った。 | H4: 汜水関の前で董卓の猛将・華雄が連合軍の将を次々と斬ると、一介の馬弓手にすぎなかった関羽が名乗り出た。曹操が注いだ温かい酒が冷めぬうちに、関羽は華雄の首を提げて戻ったと演義は伝える。 | I4: 酒尚溫時 | J4: 溫好的酒還沒涼，華雄的首級已被提了回來。 | K4: 汜水關前，董卓的猛將華雄接連斬殺聯軍將領，此時身為馬弓手的關羽挺身而出。演義說，曹操斟給他的熱酒尚未變涼，關羽已提著華雄的首級歸來。 | L4: 酒尚温时 | M4: 热酒还未凉，华雄的首级已被提了回来。 | N4: 汜水关前，董卓猛将华雄接连斩杀联军诸将，区区马弓手关羽挺身而出。演义说，曹操斟下的热酒尚未凉，关羽已提着华雄的首级回来了。 | O4: Antes que o Vinho Esfrie | P4: Voltou com a cabeça de Hua Xiong antes que o vinho quente esfriasse. | Q4: Diante do Passo de Sishui, Hua Xiong, o feroz general de Dong Zhuo, abatia um a um os campeões da coalizão, até que Guan Yu, então simples arqueiro montado, se apresentou. Conta o Romance que ele voltou com a cabeça de Hua Xiong antes que esfriasse o vinho quente que Cao Cao lhe servira. | R4: Antes que o Vinho Arrefeça | S4: Voltou com a cabeça de Hua Xiong antes que o vinho aquecido arrefecesse. | T4: Diante da Passagem de Sishui, o feroz Hua Xiong, de Dong Zhuo, abatia um a um os generais da coligação, até que Guan Yu, então simples arqueiro a cavalo, se ofereceu. Segundo o Romance, regressou com a cabeça de Hua Xiong antes que arrefecesse o vinho quente que Cao Cao lhe servira. | U4: Prima che il vino si raffreddi | V4: Tornò con la testa di Hua Xiong prima che il vino caldo si raffreddasse. | W4: Davanti al passo di Sishui, Hua Xiong, feroce generale di Dong Zhuo, abbatteva uno dopo l'altro i campioni della coalizione; allora si fece avanti Guan Yu, semplice arciere a cavallo. Il Romanzo narra che tornò con la testa di Hua Xiong prima ancora che il vino caldo versatogli da Cao Cao si raffreddasse. | X4: Antes de que se enfríe el vino | Y4: Volvió con la cabeza de Hua Xiong antes de que se enfriara el vino caliente. | Z4: Frente al paso de Sishui, Hua Xiong, el campeón de Dong Zhuo, abatía a un oficial aliado tras otro, hasta que dio un paso al frente Guan Yu, entonces un simple arquero montado. La novela cuenta que volvió con la cabeza de Hua Xiong antes de que se enfriara el vino que Cao Cao le había servido. | AA4: Дарс хөрөхөөс өмнө | AB4: Халаасан дарс хөрөхөөс өмнө Хуа Сюны толгойг авч ирэв. | AC4: Сышуй хаалганы өмнө Дун Чжогийн баатар Хуа Сюн холбоотны жанждыг ар араас нь цавчихад, ердийн морьт харваач байсан Гуань Юй гарч ирэв. Цао Цаогийн хийж өгсөн халуун дарс хөрөөгүй байхад Гуань Юй Хуа Сюны толгойг бариад буцаж ирсэн хэмээн туужид өгүүлдэг. | AD4: 温酒斩华雄
A5: 4 | B5: 호뢰관 삼영전여포 | C5: Three Heroes Fight Lü Bu | D5: Only when all three brothers charged together was Lü Bu driven back. | E5: When no one could stand against Lü Bu at Hulao Pass, Zhang Fei rode out to meet him, and Guan Yu and Liu Bei joined the fight one after the other. Only against all three at once did Lü Bu turn his horse — the greatest duel the Romance ever painted. | F5: 三英、呂布と戦う | G5: 三兄弟がそろってかかり、ようやく呂布を退けた。 | H5: 虎牢関に出た呂布に敵う者がなく、まず張飛が打ちかかり、関羽と劉備が次々と加わった。三人が一斉にかかってようやく呂布は馬首を返した――演義が描いた三国随一の一騎打ちである。 | I5: 三英戰呂布 | J5: 三兄弟一起上陣，才逼退了呂布。 | K5: 虎牢關前無人能擋呂布，張飛率先迎戰，關羽與劉備相繼加入。直到三人一齊圍攻，呂布才撥轉馬頭——這是演義描繪的三國第一單挑。 | L5: 三英战吕布 | M5: 三兄弟一齐上阵，才把吕布逼退。 | N5: 虎牢关前吕布无人能敌，张飞率先迎战，关羽、刘备相继杀入。三人合力夹攻，吕布才拨转马头——这是演义描绘的三国第一单挑。 | O5: Três Heróis Contra Lü Bu | P5: Só os três irmãos juntos conseguiram fazer Lü Bu recuar. | Q5: Ninguém resistia a Lü Bu diante do Passo de Hulao, até que Zhang Fei o enfrentou, e Guan Yu e Liu Bei entraram na luta em seguida. Só com os três atacando ao mesmo tempo Lü Bu virou o cavalo — o maior duelo dos Três Reinos, como o Romance o pinta. | R5: Três Heróis Contra Lü Bu | S5: Só os três irmãos juntos conseguiram fazer Lü Bu recuar. | T5: Ninguém resistia a Lü Bu à frente da Passagem de Hulao, até que Zhang Fei o enfrentou, e Guan Yu e Liu Bei se lançaram a seguir. Só com os três ao mesmo tempo Lü Bu fez dar meia-volta ao cavalo — o maior duelo dos Três Reinos, tal como o Romance o pinta. | U5: Tre eroi contro Lü Bu | V5: Solo assalendolo tutti e tre insieme i fratelli riuscirono a respingere Lü Bu. | W5: Al passo di Hulao nessuno reggeva il confronto con Lü Bu; si fece avanti Zhang Fei, poi intervennero Guan Yu e infine Liu Bei. Solo quando i tre lo attaccarono insieme Lü Bu voltò il cavallo: è il duello più celebre che il Romanzo abbia narrato. | X5: Tres héroes contra Lü Bu | Y5: Solo cuando los tres hermanos atacaron juntos retrocedió Lü Bu. | Z5: Nadie podía resistir a Lü Bu en el paso de Hulao, hasta que Zhang Fei lo enfrentó, y luego Guan Yu y Liu Bei se lanzaron uno tras otro. Solo ante los tres a la vez dio Lü Bu media vuelta a su caballo: el duelo más grande que pintó la novela. | AA5: Гурван баатар ба Люй Бу | AB5: Гурван ах дүү хамтдаа дайрч байж л Люй Буг ухрааж чадав. | AC5: Хулао хаалганд гарсан Люй Бутай хэн ч тэнцэхгүй байхад Чжан Фэй түрүүлж тулж, Гуань Юй, Лю Бэй ээлжлэн орж ирэв. Гурвуулаа нэгэн зэрэг дайрч байж л Люй Бу морийнхоо толгойг эргүүлэв — туужийн дүрсэлсэн Гурван улсын хамгийн гайхамшигт ганцаарчилсан тулаан. | AD5: 虎牢关三英战吕布
A6: 5 | B6: 반동탁 연합군 | C6: Eighteen Lords Against Dong Zhuo | D6: Eighteen lords gathered to march on Luoyang, with Yuan Shao as their leader. | E6: When Dong Zhuo deposed the emperor, the lords east of the passes raised their armies and named Yuan Shao their leader. But each watched the others and none would advance, and the alliance broke apart quarrelling over glory. | F6: 十八諸侯、董卓を討つ | G6: 十八の諸侯が洛陽を目指して集い、盟主には袁紹が立った。 | H6: 董卓が皇帝を廃立すると、関東の諸侯が兵を挙げ、袁紹を盟主に推した。だが諸侯は互いに牽制して進まず、連合は功を争ううちに散り散りになった。 | I6: 十八路諸侯討董卓 | J6: 十八路諸侯向洛陽集結，盟主是袁紹。 | K6: 董卓廢立天子，關東諸侯起兵，推袁紹為盟主。然而諸侯彼此牽制、按兵不動，聯軍在爭功之中終於離散。 | L6: 十八路诸侯讨董卓 | M6: 十八路诸侯向洛阳会集，盟主是袁绍。 | N6: 董卓废立天子，关东诸侯起兵，推袁绍为盟主。然而诸侯彼此牵制、按兵不进，联盟在争功中四散。 | O6: Dezoito Senhores Contra Dong Zhuo | P6: Dezoito senhores marcharam rumo a Luoyang, e o líder da aliança era Yuan Shao. | Q6: Quando Dong Zhuo trocou o imperador a seu bel-prazer, os senhores do leste ergueram exércitos e fizeram de Yuan Shao seu líder. Mas vigiavam uns aos outros e não avançavam, e a aliança se desfez disputando os méritos. | R6: Dezoito Senhores Contra Dong Zhuo | S6: Dezoito senhores marcharam sobre Luoyang, com Yuan Shao à cabeça da aliança. | T6: Quando Dong Zhuo depôs o imperador, os senhores a leste dos desfiladeiros ergueram exércitos e fizeram de Yuan Shao o líder da aliança. Mas vigiavam-se uns aos outros e não avançavam, e a coligação desfez-se a disputar glórias. | U6: Diciotto signori contro Dong Zhuo | V6: Diciotto signori marciarono su Luoyang, con Yuan Shao a capo dell'alleanza. | W6: Quando Dong Zhuo depose l'imperatore, i signori a est dei passi levarono le armi e scelsero Yuan Shao come capo della coalizione. Ma i signori si sorvegliavano l'un l'altro senza avanzare, e l'alleanza si sciolse tra le contese per la gloria. | X6: Dieciocho señores contra Dong Zhuo | Y6: Dieciocho señores marcharon hacia Luoyang, con Yuan Shao al frente de la alianza. | Z6: Cuando Dong Zhuo depuso al emperador, los señores del este alzaron sus ejércitos y nombraron a Yuan Shao jefe de la alianza. Pero se vigilaban unos a otros y no avanzaban; la coalición se disolvió disputándose los méritos. | AA6: Дун Чжогийн эсрэг 18 ван | AB6: Арван найман ноён Лоян руу чиглэн цугларч, Юань Шао тэргүүн болов. | AC6: Дун Чжо хааныг сольж тавихад Гуандуны ноёд цэрэг босгож, Юань Шаог холбооны тэргүүнээр өргөмжлөв. Гэвч ноёд бие биенээ хардан урагшилсангүй, холбоо гавьяа булаалдсаар тарж бутрав. | AD6: 反董卓联合军
A7: 6 | B7: 장안 천도 | C7: Luoyang in Flames | D7: Dong Zhuo burned Luoyang and dragged the emperor and the people off to Chang'an. | E7: Pressed by the allied armies, Dong Zhuo set fire to the palaces and homes of Luoyang and drove the emperor and millions of people to Chang'an. Countless fell along the road, and Luoyang was left in ruins. | F7: 燃える洛陽 | G7: 董卓は洛陽を焼き払い、皇帝と民を長安へ連れ去った。 | H7: 連合軍に押された董卓は洛陽の宮殿と民家を焼き払い、皇帝と数百万の民を長安へ引き連れていった。道に倒れた民は数知れず、洛陽は廃墟となった。 | I7: 焚燒的洛陽 | J7: 董卓焚毀洛陽，挾天子與百姓西遷長安。 | K7: 被聯軍逼退的董卓燒盡洛陽的宮殿與民宅，驅趕天子和數百萬百姓前往長安。倒斃路旁的百姓不計其數，洛陽化為一片廢墟。 | L7: 燃烧的洛阳 | M7: 董卓焚毁洛阳，把天子与百姓驱往长安。 | N7: 被联军逼退的董卓焚烧洛阳宫室民宅，挟天子、驱百姓数百万西迁长安。倒毙道旁的百姓不可胜数，洛阳化为一片废墟。 | O7: Luoyang em Chamas | P7: Dong Zhuo incendiou Luoyang e arrastou o imperador e o povo para Chang'an. | Q7: Pressionado pela coalizão, Dong Zhuo queimou os palácios e as casas de Luoyang e arrastou o imperador e milhões de pessoas para Chang'an. Incontáveis caíram pelo caminho, e Luoyang virou ruínas. | R7: Luoyang em Chamas | S7: Dong Zhuo incendiou Luoyang e arrastou o imperador e o povo para Chang'an. | T7: Pressionado pela coligação, Dong Zhuo pegou fogo aos palácios e às casas de Luoyang e arrastou o imperador e milhões de pessoas para Chang'an. Incontáveis caíram pelo caminho, e Luoyang ficou em ruínas. | U7: Luoyang in fiamme | V7: Dong Zhuo diede fuoco a Luoyang e trascinò l'imperatore e il popolo a Chang'an. | W7: Incalzato dalla coalizione, Dong Zhuo incendiò i palazzi e le case di Luoyang e trascinò l'imperatore e milioni di sudditi verso Chang'an. Innumerevoli caddero lungo la strada, e Luoyang divenne un cumulo di rovine. | X7: Luoyang en llamas | Y7: Dong Zhuo quemó Luoyang y arrastró al emperador y al pueblo hasta Chang'an. | Z7: Acosado por la alianza, Dong Zhuo incendió los palacios y las casas de Luoyang y arrastró al emperador y a millones de personas hacia Chang'an. Incontables cayeron por el camino, y Luoyang quedó en ruinas. | AA7: Шатаж буй Лоян | AB7: Дун Чжо Лояныг шатааж, хаан болон ард түмнийг Чанъань руу хөөн авав. | AC7: Холбоотны цэрэгт шахагдсан Дун Чжо Лояны ордон, айл өрхийг галдан шатааж, хаан ба хэдэн сая ардыг Чанъань руу хөөн туув. Замдаа унасан ард тоолшгүй олон байсан бөгөөд Лоян эзгүй балгас болжээ. | AD7: 长安迁都
A8: 7 | B8: 칠성보도 헌상 | C8: Cao Cao's Blade for Dong Zhuo | D8: The blade meant to stab Dong Zhuo became a gift the moment it was seen. | E8: With the Seven Star Sword borrowed from Wang Yun, Cao Cao drew steel in Dong Zhuo's bedchamber — but Dong Zhuo saw him in the mirror and turned. Cao Cao knelt, claiming he had come to present the sword, and fled Luoyang that very day. | F8: 曹操、董卓を狙う | G8: 董卓を刺すはずの刀は、見破られた瞬間に献上品となった。 | H8: 王允から七星宝刀を借りた曹操は董卓の寝所で刀を抜いたが、鏡に映った姿に董卓が振り返った。曹操は刀を献上しに来たと膝をつき、その足で洛陽を逃れた。 | I8: 曹操欲刺董卓 | J8: 本要刺向董卓的刀，在被識破的一瞬成了獻禮。 | K8: 曹操向王允借來七星寶刀，在董卓寢室中拔刀，卻被鏡中的身影驚動了董卓。曹操當即跪下，說是前來獻刀，隨後便逃出了洛陽。 | L8: 曹操刺董卓 | M8: 本要刺向董卓的刀，在败露的一刻成了献礼。 | N8: 曹操向王允借来七星宝刀，在董卓卧房中拔刀，镜中倒影却让董卓回过头来。曹操当即跪下称是来献刀，随即逃出洛阳。 | O8: Cao Cao Mira Dong Zhuo | P8: A espada que devia matar Dong Zhuo virou presente no instante em que foi vista. | Q8: Com a Espada das Sete Estrelas emprestada de Wang Yun, Cao Cao a desembainhou no quarto de Dong Zhuo, mas este o viu refletido no espelho e se virou. Cao Cao ajoelhou-se dizendo que viera oferecer a espada, e fugiu de Luoyang naquele mesmo instante. | R8: Cao Cao Atenta Contra Dong Zhuo | S8: A espada destinada a Dong Zhuo tornou-se oferenda no instante em que foi descoberta. | T8: Com a Espada das Sete Estrelas emprestada por Wang Yun, Cao Cao desembainhou-a nos aposentos de Dong Zhuo, mas este viu o seu reflexo no espelho e voltou-se. Cao Cao ajoelhou-se, dizendo que viera oferecer a espada, e fugiu logo de Luoyang. | U8: Cao Cao punta su Dong Zhuo | V8: Il pugnale destinato a Dong Zhuo, nell'istante in cui fu scoperto, divenne un dono. | W8: Con la Spada delle Sette Stelle avuta da Wang Yun, Cao Cao la sguainò nella camera di Dong Zhuo, ma questi si voltò vedendone il riflesso nello specchio. Cao Cao si inginocchiò dicendo di essere venuto a offrirgli la spada, e quella stessa notte fuggì da Luoyang. | X8: Cao Cao apunta a Dong Zhuo | Y8: El sable destinado a Dong Zhuo se volvió un regalo en el instante en que lo descubrieron. | Z8: Con el sable de las Siete Estrellas que le prestó Wang Yun, Cao Cao desenvainó en la alcoba de Dong Zhuo, pero este vio su reflejo en un espejo y se volvió. Cao Cao se arrodilló diciendo que venía a ofrecerle el sable, y esa misma noche huyó de Luoyang. | AA8: Цао Цао Дун Чжог онилов | AB8: Дун Чжог хатгах гэсэн илд илрэх агшинд бэлэг болон хувирав. | AC8: Ван Юнээс Долоон одны эрдэнэт илдийг зээлсэн Цао Цао Дун Чжогийн унтлагын өрөөнд илдээ сугалсан ч, толинд тусах дүрийг хараад Дун Чжо эргэн харав. Цао Цао илдийг бэлэглэхээр ирлээ хэмээн өвдөг сөгдөөд, тэр дороо Лояныг орхин зугтав. | AD8: 献七星宝刀
A9: 8 | B9: 진궁의 결별 | C9: Chen Gong Leaves Cao Cao | D9: “Better that I betray the world” — that night, Chen Gong left Cao Cao. | E9: The magistrate Chen Gong freed Cao Cao as he fled Dong Zhuo and set out on the road with him. But when Cao Cao killed Lü Boshe's household over a misunderstanding and said, “Better that I betray the world,” Chen Gong left him that same night. | F9: 陳宮、曹操と決別す | G9: 「我、天下の人に背くとも」――陳宮はその夜、曹操のもとを去った。 | H9: 董卓から逃れる曹操を県令の陳宮が見逃し、ともに旅立った。だが誤解から呂伯奢の一家を殺してなお「我が天下の人に背くとも」と言い放つ曹操を見て、陳宮はその夜のうちに去った。 | I9: 陳宮離曹而去 | J9: 「寧教我負天下人」——陳宮當夜離開了曹操。 | K9: 縣令陳宮放走逃避董卓追捕的曹操，與他同行。但曹操因誤會殺了呂伯奢一家，還說「寧教我負天下人」，陳宮便在當夜離去。 | L9: 陈宫离去 | M9: 「宁我负天下人」——陈宫在那一夜离开了曹操。 | N9: 县令陈宫放走逃避董卓的曹操，与他一同上路。可曹操误杀吕伯奢一家后仍说「宁我负天下人」，陈宫当夜便弃他而去。 | O9: Chen Gong Deixa Cao Cao | P9: “Prefiro trair o mundo” — naquela noite, Chen Gong deixou Cao Cao. | Q9: Chen Gong, magistrado do condado, libertou Cao Cao, que fugia de Dong Zhuo, e partiu com ele. Mas ao ver Cao Cao matar por engano a família de Lü Boshe e ainda dizer “prefiro trair o mundo”, Chen Gong o abandonou naquela mesma noite. | R9: Chen Gong Abandona Cao Cao | S9: «Prefiro trair o mundo» — nessa noite, Chen Gong deixou Cao Cao. | T9: O magistrado Chen Gong libertou Cao Cao, que fugia de Dong Zhuo, e partiu com ele. Mas ao ver Cao Cao matar por engano a família de Lü Boshe e ainda dizer «prefiro trair o mundo», Chen Gong foi-se embora nessa mesma noite. | U9: Chen Gong lascia Cao Cao | V9: «Meglio che sia io a tradire il mondo»: quella notte Chen Gong abbandonò Cao Cao. | W9: Il magistrato Chen Gong liberò Cao Cao in fuga da Dong Zhuo e partì con lui. Ma quando Cao Cao, dopo aver sterminato per errore la famiglia di Lü Boshe, disse «meglio che sia io a tradire il mondo», Chen Gong se ne andò quella notte stessa. | X9: Chen Gong deja a Cao Cao | Y9: «Prefiero traicionar yo al mundo» — esa misma noche, Chen Gong abandonó a Cao Cao. | Z9: Cuando Cao Cao huía de Dong Zhuo, el magistrado Chen Gong lo liberó y partió con él. Pero al ver que, tras matar por error a la familia de Lü Boshe, Cao Cao decía «prefiero traicionar yo al mundo», Chen Gong se marchó esa misma noche. | AA9: Чэнь Гун Цао Цаогоос салав | AB9: «Тэнгэрийн дорыг би орхих нь дээр» — Чэнь Гун тэр шөнө Цао Цаогоос салан одов. | AC9: Дун Чжогоос зугтаж явсан Цао Цаог шянь захирагч Чэнь Гун суллаад хамт замд гарав. Гэвч Люй Бошэгийн гэр бүлийг буруу ойлголтоор хөнөөчхөөд «Тэнгэрийн дорыг би орхих нь дээр» гэж хэлсэн Цао Цаог хараад Чэнь Гун тэр шөнөдөө явжээ. | AD9: 陈宫决别
A10: 9 | B10: 형양의 추격 | C10: Cao Hong Gives His Horse | D10: “The realm can do without Cao Hong, but not without you.” — Cao Hong gave up his own horse. | E10: Alone among the allies, Cao Cao pursued Dong Zhuo and was badly beaten by Xu Rong at Xingyang. When he fell without a horse, Cao Hong gave him his own, saying, “The realm can do without Cao Hong, but not without you.” | F10: 曹洪、馬を譲る | G10: 「天下に曹洪なかるべきも、君なかるべからず」――曹洪は自らの馬を差し出した。 | H10: 連合軍でただ一人董卓を追った曹操は、滎陽で徐栄に大敗した。馬を失って倒れた曹操に、曹洪は自らの馬を差し出し「天下に曹洪なかるべきも、君なかるべからず」と言った。 | I10: 曹洪讓馬 | J10: 「天下可無曹洪，不可無公。」——曹洪讓出了自己的馬。 | K10: 聯軍之中唯有曹操獨自追擊董卓，卻在滎陽大敗於徐榮。曹操失馬倒地，曹洪把自己的馬讓給他，說：「天下可無曹洪，不可無公。」 | L10: 曹洪让马 | M10: 「天下可无洪，不可无公。」——曹洪让出了自己的马。 | N10: 联军中唯有曹操独自追击董卓，却在荥阳大败于徐荣。失马倒地的曹操面前，曹洪让出坐骑，说道：「天下可无洪，不可无公。」 | O10: Cao Hong Cede seu Cavalo | P10: “O mundo pode viver sem Cao Hong, mas não sem o senhor.” — e Cao Hong lhe deu o próprio cavalo. | Q10: O único da coalizão a perseguir Dong Zhuo, Cao Cao sofreu dura derrota para Xu Rong em Xingyang. Caído e sem montaria, ouviu Cao Hong dizer, oferecendo-lhe o próprio cavalo: “O mundo pode viver sem Cao Hong, mas não sem o senhor.” | R10: Cao Hong Cede o Cavalo | S10: «O mundo passa sem Cao Hong, mas não sem vós.» — Cao Hong deu-lhe o seu cavalo. | T10: Único da coligação a perseguir Dong Zhuo, Cao Cao foi duramente derrotado por Xu Rong em Xingyang. Caído e sem montada, recebeu de Cao Hong o seu próprio cavalo: «O mundo passa sem Cao Hong, mas não sem vós.» | U10: Cao Hong cede il suo cavallo | V10: «Il mondo può fare a meno di Cao Hong, ma non di voi.» E Cao Hong gli cedette il suo cavallo. | W10: Unico della coalizione a inseguire Dong Zhuo, Cao Cao fu duramente sconfitto da Xu Rong a Xingyang. A Cao Cao, caduto e senza cavallo, Cao Hong diede il proprio dicendo: «Il mondo può fare a meno di Cao Hong, ma non di voi». | X10: Cao Hong cede su caballo | Y10: «El mundo puede pasar sin Cao Hong, pero no sin usted, señor» — y Cao Hong le dio su caballo. | Z10: Solo entre los aliados, Cao Cao persiguió a Dong Zhuo y fue derrotado por Xu Rong en Xingyang. Al verlo caído y sin montura, Cao Hong le cedió su caballo: «El mundo puede pasar sin Cao Hong, pero no sin usted, señor». | AA10: Цао Хун морио өгөв | AB10: «Тэнгэрийн дор Цао Хунгүй байж болно, харин таныг үгүйлж болохгүй» — Цао Хун морио өгөв. | AC10: Холбоотнуудаас ганцаараа Дун Чжог мөрдсөн Цао Цао Синъянд Сюй Жунд бут ниргүүлэв. Мориноосоо салж унасан Цао Цаод Цао Хун өөрийн морио өгөхдөө «Тэнгэрийн дор Цао Хунгүй байж болно, харин таныг үгүйлж болохгүй» гэжээ. | AD10: 荥阳追击
A11: 10 | B11: 손견과 전국옥새 | C11: The Seal in the Well | D11: The imperial seal, drawn up from a well in burnt Luoyang. | E11: First into the burned city of Luoyang, Sun Jian drew the imperial seal out of a palace well. Hiding it as he set off home to Jiangdong, he made enemies of Yuan Shao and Liu Biao. | F11: 井戸の中の玉璽 | G11: 焼け落ちた洛陽の井戸から引き上げられた、皇帝の玉璽。 | H11: 焼けた洛陽に一番乗りした孫堅は、宮中の井戸から皇帝の玉璽を拾い上げた。玉璽を隠したまま江東へ帰ろうとした孫堅は、袁紹・劉表と仇敵になった。 | I11: 井中玉璽 | J11: 從焚毀的洛陽井中撈起的傳國玉璽。 | K11: 孫堅率先進入焚毀的洛陽，在宮中井裡撈出了傳國玉璽。他藏起玉璽打算回江東，從此與袁紹、劉表結下了仇怨。 | L11: 井中玉玺 | M11: 从焚毁的洛阳井中捞起的传国玉玺。 | N11: 孙坚率先进入焚毁的洛阳，在宫中井里捞起了天子玉玺。他私藏玉玺欲回江东，从此与袁绍、刘表结下仇怨。 | O11: O Selo no Fundo do Poço | P11: O selo imperial, retirado de um poço na Luoyang incendiada. | Q11: Primeiro a entrar na Luoyang em cinzas, Sun Jian tirou o selo imperial de um poço do palácio. Escondendo-o para voltar a Jiangdong, ele se tornou inimigo de Yuan Shao e Liu Biao. | R11: O Selo no Fundo do Poço | S11: O selo imperial, retirado de um poço da Luoyang incendiada. | T11: Primeiro a entrar na Luoyang queimada, Sun Jian tirou o selo imperial de um poço do palácio. Escondeu-o e quis regressar a Jiangdong, o que fez de Yuan Shao e de Liu Biao seus inimigos. | U11: Il sigillo nel pozzo | V11: Il sigillo imperiale ripescato da un pozzo di Luoyang in fiamme. | W11: Primo a entrare nella Luoyang bruciata, Sun Jian ripescò il sigillo imperiale da un pozzo del palazzo. Mentre cercava di tornare a Jiangdong tenendolo nascosto, si inimicò Yuan Shao e Liu Biao. | X11: El sello en el fondo del pozo | Y11: El sello imperial, rescatado de un pozo en la Luoyang incendiada. | Z11: El primero en entrar en la Luoyang incendiada fue Sun Jian, que sacó el sello imperial de un pozo del palacio. Por ocultarlo y querer volver con él a Jiangdong, se ganó la enemistad de Yuan Shao y Liu Biao. | AA11: Худгийн ёроол дахь тамга | AB11: Шатсан Лояны худгаас гаргаж авсан хааны хаш тамга. | AC11: Шатсан Лоянд түрүүлж орсон Сунь Цзянь ордны худгаас хааны хаш тамгыг олж гаргав. Тамгыг нууж Цзяндун руу буцахаар зэхсэн Сунь Цзянь Юань Шао, Лю Бяо хоёртой өстөн болжээ. | AD11: 孙坚得玉玺
A12: 11 | B12: 현산의 손견 | C12: The Tiger of Jiangdong Falls | D12: The Tiger of Jiangdong fell at Mount Xian, caught in Kuai Yue's ambush. | E12: Sent by Yuan Shu against Jing Province, Sun Jian drove hard against Liu Biao's general Huang Zu. But by Kuai Yue's plan, hidden troops on Mount Xian struck him with stones and arrows, and the Tiger of Jiangdong fell at thirty-seven. | F12: 江東の虎、斃れる | G12: 江東の虎は蒯越の伏兵にかかり、峴山に斃れた。 | H12: 袁術の命で荊州を攻めた孫堅は、劉表の将・黄祖を追い詰めた。だが蒯越の計で峴山に潜んだ伏兵から石と矢を浴び、江東の虎は三十七歳で斃れた。 | I12: 江東之虎殞落 | J12: 江東之虎中了蒯越的埋伏，倒在峴山。 | K12: 孫堅奉袁術之命攻打荊州，將劉表部將黃祖逼入絕境。然而蒯越設計，伏兵藏於峴山，以亂石箭矢擊中孫堅，江東之虎三十七歲便殞落了。 | L12: 江东猛虎陨落 | M12: 江东猛虎中了蒯越的埋伏，倒在岘山。 | N12: 孙坚奉袁术之命攻荆州，将刘表部将黄祖逼入绝境。但蒯越设计在岘山埋下伏兵，乱石与箭雨之下，江东猛虎陨落，年仅三十七。 | O12: Cai o Tigre de Jiangdong | P12: O Tigre de Jiangdong caiu no monte Xian, na emboscada de Kuai Yue. | Q12: Por ordem de Yuan Shu, Sun Jian atacou Jing e encurralou Huang Zu, general de Liu Biao. Mas, pelo plano de Kuai Yue, tropas escondidas no monte Xian o cobriram de pedras e flechas, e o Tigre de Jiangdong caiu aos trinta e sete anos. | R12: Cai o Tigre de Jiangdong | S12: O Tigre de Jiangdong caiu no monte Xian, na emboscada de Kuai Yue. | T12: Por ordem de Yuan Shu, Sun Jian atacou Jingzhou e encurralou Huang Zu, general de Liu Biao. Mas, por um ardil de Kuai Yue, uma emboscada no monte Xian cobriu-o de pedras e flechas, e o Tigre de Jiangdong tombou aos trinta e sete anos. | U12: Cade la Tigre di Jiangdong | V12: La Tigre di Jiangdong cadde sul monte Xian nell'imboscata di Kuai Yue. | W12: Per ordine di Yuan Shu, Sun Jian attaccò Jingzhou e incalzò Huang Zu, generale di Liu Biao. Ma, secondo il piano di Kuai Yue, i soldati nascosti sul monte Xian lo colpirono con pietre e frecce, e la Tigre di Jiangdong cadde a trentasette anni. | X12: Cae el Tigre de Jiangdong | Y12: El Tigre de Jiangdong cayó en el monte Xian, en la emboscada de Kuai Yue. | Z12: Por orden de Yuan Shu, Sun Jian atacó Jing y acorraló a Huang Zu, general de Liu Biao. Pero, por el plan de Kuai Yue, una emboscada oculta en el monte Xian lo cubrió de piedras y flechas, y el Tigre de Jiangdong cayó a los treinta y siete años. | AA12: Цзяндуны бар унав | AB12: Цзяндуны бар Куай Юэгийн отолтод өртөж Сяньшаньд унав. | AC12: Юань Шугийн тушаалаар Цзинчжоуг довтолсон Сунь Цзянь Лю Бяогийн жанжин Хуан Цзуг шахаж байв. Гэвч Куай Юэгийн заль ёсоор Сяньшаньд нуугдсан отолтынхны чулуу, суманд өртөж, Цзяндуны бар гучин долоон насандаа унажээ. | AD12: 岘山伏兵
A13: 12 | B13: 백마의종 | C13: The White Horse Riders | D13: Gongsun Zan's cavalry rode only white horses, and even the frontier tribes feared them. | E13: Gongsun Zan chose thousands of expert mounted archers on white horses and called them the “White Horse Volunteers.” It is said the Wuhuan of the north fled at the mere sight of white horses, so the name alone guarded the frontier. | F13: 白馬の騎兵隊 | G13: 白馬ばかりを選んで乗る公孫瓚の騎兵隊は、異民族にも恐れられた。 | H13: 公孫瓚は白馬に乗る弓の名手数千を選び、「白馬義従」と呼んだ。北方の烏桓は白馬を見ただけで逃げ出したといい、その名だけで辺境を守った。 | I13: 白馬騎兵 | J13: 公孫瓚專騎白馬的騎兵，連異族都為之畏懼。 | K13: 公孫瓚挑選數千名善射、騎白馬的騎兵，號為「白馬義從」。據說北方的烏桓一見白馬便逃，單憑這個名號就守住了邊境。 | L13: 白马骑兵 | M13: 专骑白马的公孙瓒骑兵，连异族也闻风丧胆。 | N13: 公孙瓒挑选骑白马、善骑射者数千人，号为「白马义从」。北方乌桓一见白马便逃，单凭这个名号就能守住边境。 | O13: A Cavalaria dos Cavalos Brancos | P13: A cavalaria de Gongsun Zan, montada só em cavalos brancos, era temida até pelos povos do norte. | Q13: Gongsun Zan escolheu milhares de arqueiros montados em cavalos brancos e os chamou de “Cavaleiros Leais do Cavalo Branco”. Dizem que os Wuhuan do norte fugiam só de ver um cavalo branco — o nome bastava para guardar a fronteira. | R13: Os Cavaleiros dos Cavalos Brancos | S13: A cavalaria de Gongsun Zan, toda montada em cavalos brancos, era temida pelos povos da fronteira. | T13: Gongsun Zan escolheu milhares de arqueiros a cavalo montados em cavalos brancos e chamou-lhes os Leais dos Cavalos Brancos. Diz-se que os Wuhuan do norte fugiam só de ver um cavalo branco, e esse nome bastava para guardar a fronteira. | U13: La cavalleria dai cavalli bianchi | V13: Persino i barbari temevano la cavalleria di Gongsun Zan, che montava solo cavalli bianchi. | W13: Gongsun Zan scelse migliaia di abili arcieri a cavallo su destrieri bianchi e li chiamò «I Fedeli dai Cavalli Bianchi». Si dice che i Wuhuan del nord fuggissero alla sola vista di un cavallo bianco: quel nome bastava a difendere la frontiera. | X13: Los jinetes del caballo blanco | Y13: Hasta los pueblos bárbaros temían a los jinetes de Gongsun Zan, montados solo en caballos blancos. | Z13: Gongsun Zan escogió a miles de arqueros a caballo sobre monturas blancas y los llamó los «Jinetes Leales del Caballo Blanco». Se dice que los wuhuan del norte huían con solo ver un caballo blanco: aquel nombre bastaba para guardar la frontera. | AA13: Цагаан морьт хүлэг цэрэг | AB13: Зөвхөн цагаан морь унасан Гунсунь Цзаны хүлэг цэргээс харь үндэстэн хүртэл эмээдэг байв. | AC13: Гунсунь Цзань цагаан морь унасан мэргэн харваач хэдэн мянган хүлэг цэрэг шилж, «Цагаан морьт үнэнч дагалдагсад» хэмээн нэрлэв. Хойд зүгийн Ухуань цагаан морь харангуутаа зугтдаг байсан гэдэг тул тэр нэрээр л хил хязгаарыг сахиж байжээ. | AD13: 白马义从
... A118: 117 | B118: 형주의 유표 | C118: Torn Between Two Sons | D118: Liu Biao, one of the Eight Talents, held Jing Province but wavered between his two sons. | E118: Liu Biao was a renowned scholar counted among the Eight Talents, and he made Jing Province a refuge in an age of chaos. But he could not choose an heir between his eldest son Liu Qi and his second son Liu Cong, and after his death Jing Province passed to Cao Cao. | F118: 二人の息子のはざまで | G118: 八俊の一人と称された劉表は荊州を守ったが、二人の息子を前に迷い続けた。 | H118: 劉表は八俊の一人として名高い士人で、荊州を治めて乱世の避難所とした。だが長子・劉琦と次子・劉琮のあいだで後継を定められず、その死後、荊州は曹操の手に渡った。 | I118: 在兩個兒子之間 | J118: 號稱八俊之一的劉表守住了荊州，卻在兩個兒子之間猶豫不決。 | K118: 劉表是名列八俊的名士，治理荊州，使其成為亂世中的避難之地。但他在長子劉琦與次子劉琮之間定不下繼承人，死後荊州便落入曹操之手。 | L118: 两个儿子之间 | M118: 号称「八俊」之一的刘表守住了荆州，却在两个儿子之间犹豫不决。 | N118: 刘表是名列「八俊」的名士，治理荆州，使之成为乱世中的避难之地。但他在长子刘琦与次子刘琮之间迟迟定不下继承人，死后荆州落入曹操之手。 | O118: Entre Dois Filhos | P118: Liu Biao, um dos Oito Notáveis, defendeu Jing, mas hesitou entre os dois filhos. | Q118: Liu Biao, letrado célebre como um dos Oito Notáveis, governou Jing e fez dela um refúgio em tempos de caos. Mas não conseguiu escolher herdeiro entre o primogênito Liu Qi e o segundo filho Liu Cong, e após sua morte Jing caiu nas mãos de Cao Cao. | R118: Entre Dois Filhos | S118: Liu Biao, um dos Oito Notáveis, defendeu Jingzhou mas hesitou entre os dois filhos. | T118: Liu Biao, letrado afamado como um dos Oito Notáveis, governou Jingzhou e fez dela um refúgio em tempos de caos. Mas não conseguiu escolher entre o primogénito Liu Qi e o segundo filho Liu Cong, e após a sua morte Jingzhou passou para Cao Cao. | U118: Tra due figli | V118: Liu Biao, annoverato tra gli Otto Eccellenti, difese Jingzhou ma esitò tra i due figli. | W118: Liu Biao, letterato celebre come uno degli Otto Eccellenti, governò Jingzhou facendone un rifugio in tempi di caos. Ma non seppe scegliere l'erede tra il primogenito Liu Qi e il secondo figlio Liu Cong, e dopo la sua morte Jingzhou passò a Cao Cao. | X118: Entre dos hijos | Y118: Liu Biao, uno de los Ocho Talentos, defendió Jing, pero vaciló entre sus dos hijos. | Z118: Liu Biao, letrado célebre como uno de los Ocho Talentos, gobernó Jing y la convirtió en refugio en tiempos de caos. Pero no supo elegir heredero entre su primogénito Liu Qi y su segundo hijo Liu Cong, y a su muerte Jing pasó a manos de Cao Cao. | AA118: Хоёр хүүгийн дунд | AB118: Найман сайн эрийн нэг гэгдсэн Лю Бяо Цзинчжоуг сахисан ч хоёр хүүгийнхээ дунд эргэлзэв. | AC118: Лю Бяо найман сайн эрийн нэг хэмээн алдаршсан эрдэмтэн бөгөөд Цзинчжоуг засаж самуун цагийн хоргодох газар болгосон юм. Гэвч ууган хүү Лю Ци, отгон хүү Лю Цун хоёрын дундаас залгамжлагчаа тогтоож чадаагүй тул нас барсны дараа Цзинчжоу Цао Цаод шилжжээ. | AD118: 荆州刘表

Sheet 비용표
A1: 구분 | B1: 키 | C1: 값 | D1: 설명
A2: 카드 단가 | B2: S | C2: 10 | D2: S급 카드 1장
A3: 카드 단가 | B3: E | C3: 10 | D3: E급(헌제) 카드 1장
A4: 카드 단가 | B4: A | C4: 6 | D4: A급 카드 1장
A5: 카드 단가 | B5: B | C5: 4 | D5: B급 카드 1장
A6: 카드 단가 | B6: C | C6: 2 | D6: C급 — 가챠에 없고 전투 보상으로만 나온다
A7: 카드 단가 | B7: D | C7: 2 | D7: D급 — 가챠에 없고 전투 보상으로만 나온다
A8: 품목 배수 | B8: 병기 | C8: 3 | D8: 병기 비용 = 대장간 해금 Lv × 이 값
A9: 품목 배수 | B9: 아이템 | C9: 2 | D9: 아이템 비용 = 시장 해금 Lv × 이 값
A11: 등급표
A12: 등급 | B12: 비용 하한 | C12: 점수 | D12: 설명
A13: 일반 | B13: 0 | C13: 50
A14: 희귀 | B14: 15 | C14: 100
A15: 영웅 | B15: 28 | C15: 200
A16: 전설 | B16: 34 | C16: 300 | D16: 고유기술 SP −1 · 진영 SP +1은 전설 이상만
A17: 천하 | B17: 50 | C17: 500 | D17: S급 다섯 — 5칸 상한에서 비용의 천장 (2026-10-14)
A19: 노란 칸(파란 글자)만 고치면 「칸」 · 「컬렉션」 시트의 비용 · 등급 · 점수가 다시 계산된다. 값은 2026-10-13 기획 세션 초안이다(3차: 카드는 컬렉션마다 장수당 1장). 2026-10-14: 칸 5개 상한에 맞춰 전설 42 → 34, 천하 60 → 50.

Sheet 칸
A1: 컬렉션 # | B1: 칸 # | C1: 종류 | D1: 대상 | E1: 수 | F1: 등급 / 해금 Lv | G1: 단가 | H1: 비용 | I1: 조건 누적 (보조)
A2: 1 | B2: 1 | C2: 카드 | D2: 유비 | E2: 1 | F2: S | G2: =IF(C2="카드",INDEX(비용표!$C$2:$C$7,MATCH(F2,비용표!$B$2:$B$7,0)),F2*INDEX(비용표!$C$8:$C$9,MATCH(C2,비용표!$B$8:$B$9,0))) | H2: =G2*E2 | I2: =IF(C2="카드",D2&E2,"["&C2&"] "&D2)
A3: 1 | B3: 2 | C3: 카드 | D3: 관우 | E3: 1 | F3: S | G3: =IF(C3="카드",INDEX(비용표!$C$2:$C$7,MATCH(F3,비용표!$B$2:$B$7,0)),F3*INDEX(비용표!$C$8:$C$9,MATCH(C3,비용표!$B$8:$B$9,0))) | H3: =G3*E3 | I3: =IF(A3=A2,I2&" · ","")&IF(C3="카드",D3&E3,"["&C3&"] "&D3)
A4: 1 | B4: 3 | C4: 카드 | D4: 장비 | E4: 1 | F4: S | G4: =IF(C4="카드",INDEX(비용표!$C$2:$C$7,MATCH(F4,비용표!$B$2:$B$7,0)),F4*INDEX(비용표!$C$8:$C$9,MATCH(C4,비용표!$B$8:$B$9,0))) | H4: =G4*E4 | I4: =IF(A4=A3,I3&" · ","")&IF(C4="카드",D4&E4,"["&C4&"] "&D4)
A5: 2 | B5: 1 | C5: 카드 | D5: 유비 | E5: 1 | F5: S | G5: =IF(C5="카드",INDEX(비용표!$C$2:$C$7,MATCH(F5,비용표!$B$2:$B$7,0)),F5*INDEX(비용표!$C$8:$C$9,MATCH(C5,비용표!$B$8:$B$9,0))) | H5: =G5*E5 | I5: =IF(A5=A4,I4&" · ","")&IF(C5="카드",D5&E5,"["&C5&"] "&D5)
A6: 2 | B6: 2 | C6: 카드 | D6: 조조 | E6: 1 | F6: S | G6: =IF(C6="카드",INDEX(비용표!$C$2:$C$7,MATCH(F6,비용표!$B$2:$B$7,0)),F6*INDEX(비용표!$C$8:$C$9,MATCH(C6,비용표!$B$8:$B$9,0))) | H6: =G6*E6 | I6: =IF(A6=A5,I5&" · ","")&IF(C6="카드",D6&E6,"["&C6&"] "&D6)
A7: 2 | B7: 3 | C7: 카드 | D7: 손견 | E7: 1 | F7: S | G7: =IF(C7="카드",INDEX(비용표!$C$2:$C$7,MATCH(F7,비용표!$B$2:$B$7,0)),F7*INDEX(비용표!$C$8:$C$9,MATCH(C7,비용표!$B$8:$B$9,0))) | H7: =G7*E7 | I7: =IF(A7=A6,I6&" · ","")&IF(C7="카드",D7&E7,"["&C7&"] "&D7)
A8: 2 | B8: 4 | C8: 아이템 | D8: 태평요술 | E8: 1 | F8: 3 | G8: =IF(C8="카드",INDEX(비용표!$C$2:$C$7,MATCH(F8,비용표!$B$2:$B$7,0)),F8*INDEX(비용표!$C$8:$C$9,MATCH(C8,비용표!$B$8:$B$9,0))) | H8: =G8*E8 | I8: =IF(A8=A7,I7&" · ","")&IF(C8="카드",D8&E8,"["&C8&"] "&D8)
A9: 3 | B9: 1 | C9: 카드 | D9: 관우 | E9: 1 | F9: S | G9: =IF(C9="카드",INDEX(비용표!$C$2:$C$7,MATCH(F9,비용표!$B$2:$B$7,0)),F9*INDEX(비용표!$C$8:$C$9,MATCH(C9,비용표!$B$8:$B$9,0))) | H9: =G9*E9 | I9: =IF(A9=A8,I8&" · ","")&IF(C9="카드",D9&E9,"["&C9&"] "&D9)
A10: 3 | B10: 2 | C10: 카드 | D10: 화웅 | E10: 1 | F10: A | G10: =IF(C10="카드",INDEX(비용표!$C$2:$C$7,MATCH(F10,비용표!$B$2:$B$7,0)),F10*INDEX(비용표!$C$8:$C$9,MATCH(C10,비용표!$B$8:$B$9,0))) | H10: =G10*E10 | I10: =IF(A10=A9,I9&" · ","")&IF(C10="카드",D10&E10,"["&C10&"] "&D10)
A11: 3 | B11: 3 | C11: 카드 | D11: 조조 | E11: 1 | F11: S | G11: =IF(C11="카드",INDEX(비용표!$C$2:$C$7,MATCH(F11,비용표!$B$2:$B$7,0)),F11*INDEX(비용표!$C$8:$C$9,MATCH(C11,비용표!$B$8:$B$9,0))) | H11: =G11*E11 | I11: =IF(A11=A10,I10&" · ","")&IF(C11="카드",D11&E11,"["&C11&"] "&D11)
A12: 4 | B12: 1 | C12: 카드 | D12: 여포 | E12: 1 | F12: S | G12: =IF(C12="카드",INDEX(비용표!$C$2:$C$7,MATCH(F12,비용표!$B$2:$B$7,0)),F12*INDEX(비용표!$C$8:$C$9,MATCH(C12,비용표!$B$8:$B$9,0))) | H12: =G12*E12 | I12: =IF(A12=A11,I11&" · ","")&IF(C12="카드",D12&E12,"["&C12&"] "&D12)
A13: 4 | B13: 2 | C13: 카드 | D13: 유비 | E13: 1 | F13: S | G13: =IF(C13="카드",INDEX(비용표!$C$2:$C$7,MATCH(F13,비용표!$B$2:$B$7,0)),F13*INDEX(비용표!$C$8:$C$9,MATCH(C13,비용표!$B$8:$B$9,0))) | H13: =G13*E13 | I13: =IF(A13=A12,I12&" · ","")&IF(C13="카드",D13&E13,"["&C13&"] "&D13)
A14: 4 | B14: 3 | C14: 카드 | D14: 관우 | E14: 1 | F14: S | G14: =IF(C14="카드",INDEX(비용표!$C$2:$C$7,MATCH(F14,비용표!$B$2:$B$7,0)),F14*INDEX(비용표!$C$8:$C$9,MATCH(C14,비용표!$B$8:$B$9,0))) | H14: =G14*E14 | I14: =IF(A14=A13,I13&" · ","")&IF(C14="카드",D14&E14,"["&C14&"] "&D14)
A15: 4 | B15: 4 | C15: 카드 | D15: 장비 | E15: 1 | F15: S | G15: =IF(C15="카드",INDEX(비용표!$C$2:$C$7,MATCH(F15,비용표!$B$2:$B$7,0)),F15*INDEX(비용표!$C$8:$C$9,MATCH(C15,비용표!$B$8:$B$9,0))) | H15: =G15*E15 | I15: =IF(A15=A14,I14&" · ","")&IF(C15="카드",D15&E15,"["&C15&"] "&D15)
A16: 5 | B16: 1 | C16: 카드 | D16: 원소 | E16: 1 | F16: C | G16: =IF(C16="카드",INDEX(비용표!$C$2:$C$7,MATCH(F16,비용표!$B$2:$B$7,0)),F16*INDEX(비용표!$C$8:$C$9,MATCH(C16,비용표!$B$8:$B$9,0))) | H16: =G16*E16 | I16: =IF(A16=A15,I15&" · ","")&IF(C16="카드",D16&E16,"["&C16&"] "&D16)
A17: 5 | B17: 2 | C17: 카드 | D17: 조조 | E17: 1 | F17: S | G17: =IF(C17="카드",INDEX(비용표!$C$2:$C$7,MATCH(F17,비용표!$B$2:$B$7,0)),F17*INDEX(비용표!$C$8:$C$9,MATCH(C17,비용표!$B$8:$B$9,0))) | H17: =G17*E17 | I17: =IF(A17=A16,I16&" · ","")&IF(C17="카드",D17&E17,"["&C17&"] "&D17)
A18: 5 | B18: 3 | C18: 카드 | D18: 손견 | E18: 1 | F18: S | G18: =IF(C18="카드",INDEX(비용표!$C$2:$C$7,MATCH(F18,비용표!$B$2:$B$7,0)),F18*INDEX(비용표!$C$8:$C$9,MATCH(C18,비용표!$B$8:$B$9,0))) | H18: =G18*E18 | I18: =IF(A18=A17,I17&" · ","")&IF(C18="카드",D18&E18,"["&C18&"] "&D18)
A19: 5 | B19: 4 | C19: 카드 | D19: 공손찬 | E19: 1 | F19: C | G19: =IF(C19="카드",INDEX(비용표!$C$2:$C$7,MATCH(F19,비용표!$B$2:$B$7,0)),F19*INDEX(비용표!$C$8:$C$9,MATCH(C19,비용표!$B$8:$B$9,0))) | H19: =G19*E19 | I19: =IF(A19=A18,I18&" · ","")&IF(C19="카드",D19&E19,"["&C19&"] "&D19)
A20: 5 | B20: 5 | C20: 카드 | D20: 원술 | E20: 1 | F20: B | G20: =IF(C20="카드",INDEX(비용표!$C$2:$C$7,MATCH(F20,비용표!$B$2:$B$7,0)),F20*INDEX(비용표!$C$8:$C$9,MATCH(C20,비용표!$B$8:$B$9,0))) | H20: =G20*E20 | I20: =IF(A20=A19,I19&" · ","")&IF(C20="카드",D20&E20,"["&C20&"] "&D20)
... A26: 7 | B26: 2 | C26: 카드 | D26: 동탁 | E26: 1 | F26: A | G26: =IF(C26="카드",INDEX(비용표!$C$2:$C$7,MATCH(F26,비용표!$B$2:$B$7,0)),F26*INDEX(비용표!$C$8:$C$9,MATCH(C26,비용표!$B$8:$B$9,0))) | H26: =G26*E26 | I26: =IF(A26=A25,I25&" · ","")&IF(C26="카드",D26&E26,"["&C26&"] "&D26)
A27: 7 | B27: 3 | C27: 병기 | D27: 칠성보도 | E27: 1 | F27: 3 | G27: =IF(C27="카드",INDEX(비용표!$C$2:$C$7,MATCH(F27,비용표!$B$2:$B$7,0)),F27*INDEX(비용표!$C$8:$C$9,MATCH(C27,비용표!$B$8:$B$9,0))) | H27: =G27*E27 | I27: =IF(A27=A26,I26&" · ","")&IF(C27="카드",D27&E27,"["&C27&"] "&D27)
A28: 8 | B28: 1 | C28: 카드 | D28: 진궁 | E28: 1 | F28: B | G28: =IF(C28="카드",INDEX(비용표!$C$2:$C$7,MATCH(F28,비용표!$B$2:$B$7,0)),F28*INDEX(비용표!$C$8:$C$9,MATCH(C28,비용표!$B$8:$B$9,0))) | H28: =G28*E28 | I28: =IF(A28=A27,I27&" · ","")&IF(C28="카드",D28&E28,"["&C28&"] "&D28)
A29: 8 | B29: 2 | C29: 카드 | D29: 조조 | E29: 1 | F29: S | G29: =IF(C29="카드",INDEX(비용표!$C$2:$C$7,MATCH(F29,비용표!$B$2:$B$7,0)),F29*INDEX(비용표!$C$8:$C$9,MATCH(C29,비용표!$B$8:$B$9,0))) | H29: =G29*E29 | I29: =IF(A29=A28,I28&" · ","")&IF(C29="카드",D29&E29,"["&C29&"] "&D29)
A30: 9 | B30: 1 | C30: 카드 | D30: 조조 | E30: 1 | F30: S | G30: =IF(C30="카드",INDEX(비용표!$C$2:$C$7,MATCH(F30,비용표!$B$2:$B$7,0)),F30*INDEX(비용표!$C$8:$C$9,MATCH(C30,비용표!$B$8:$B$9,0))) | H30: =G30*E30 | I30: =IF(A30=A29,I29&" · ","")&IF(C30="카드",D30&E30,"["&C30&"] "&D30)
A31: 9 | B31: 2 | C31: 카드 | D31: 조홍 | E31: 1 | F31: B | G31: =IF(C31="카드",INDEX(비용표!$C$2:$C$7,MATCH(F31,비용표!$B$2:$B$7,0)),F31*INDEX(비용표!$C$8:$C$9,MATCH(C31,비용표!$B$8:$B$9,0))) | H31: =G31*E31 | I31: =IF(A31=A30,I30&" · ","")&IF(C31="카드",D31&E31,"["&C31&"] "&D31)
A32: 9 | B32: 3 | C32: 카드 | D32: 서영 | E32: 1 | F32: D | G32: =IF(C32="카드",INDEX(비용표!$C$2:$C$7,MATCH(F32,비용표!$B$2:$B$7,0)),F32*INDEX(비용표!$C$8:$C$9,MATCH(C32,비용표!$B$8:$B$9,0))) | H32: =G32*E32 | I32: =IF(A32=A31,I31&" · ","")&IF(C32="카드",D32&E32,"["&C32&"] "&D32)
A33: 10 | B33: 1 | C33: 카드 | D33: 손견 | E33: 1 | F33: S | G33: =IF(C33="카드",INDEX(비용표!$C$2:$C$7,MATCH(F33,비용표!$B$2:$B$7,0)),F33*INDEX(비용표!$C$8:$C$9,MATCH(C33,비용표!$B$8:$B$9,0))) | H33: =G33*E33 | I33: =IF(A33=A32,I32&" · ","")&IF(C33="카드",D33&E33,"["&C33&"] "&D33)
A34: 10 | B34: 2 | C34: 카드 | D34: 정보 | E34: 1 | F34: A | G34: =IF(C34="카드",INDEX(비용표!$C$2:$C$7,MATCH(F34,비용표!$B$2:$B$7,0)),F34*INDEX(비용표!$C$8:$C$9,MATCH(C34,비용표!$B$8:$B$9,0))) | H34: =G34*E34 | I34: =IF(A34=A33,I33&" · ","")&IF(C34="카드",D34&E34,"["&C34&"] "&D34)
A35: 10 | B35: 3 | C35: 카드 | D35: 황개 | E35: 1 | F35: A | G35: =IF(C35="카드",INDEX(비용표!$C$2:$C$7,MATCH(F35,비용표!$B$2:$B$7,0)),F35*INDEX(비용표!$C$8:$C$9,MATCH(C35,비용표!$B$8:$B$9,0))) | H35: =G35*E35 | I35: =IF(A35=A34,I34&" · ","")&IF(C35="카드",D35&E35,"["&C35&"] "&D35)
A36: 10 | B36: 4 | C36: 카드 | D36: 한당 | E36: 1 | F36: C | G36: =IF(C36="카드",INDEX(비용표!$C$2:$C$7,MATCH(F36,비용표!$B$2:$B$7,0)),F36*INDEX(비용표!$C$8:$C$9,MATCH(C36,비용표!$B$8:$B$9,0))) | H36: =G36*E36 | I36: =IF(A36=A35,I35&" · ","")&IF(C36="카드",D36&E36,"["&C36&"] "&D36)
A37: 11 | B37: 1 | C37: 카드 | D37: 손견 | E37: 1 | F37: S | G37: =IF(C37="카드",INDEX(비용표!$C$2:$C$7,MATCH(F37,비용표!$B$2:$B$7,0)),F37*INDEX(비용표!$C$8:$C$9,MATCH(C37,비용표!$B$8:$B$9,0))) | H37: =G37*E37 | I37: =IF(A37=A36,I36&" · ","")&IF(C37="카드",D37&E37,"["&C37&"] "&D37)
A38: 11 | B38: 2 | C38: 카드 | D38: 유표 | E38: 1 | F38: B | G38: =IF(C38="카드",INDEX(비용표!$C$2:$C$7,MATCH(F38,비용표!$B$2:$B$7,0)),F38*INDEX(비용표!$C$8:$C$9,MATCH(C38,비용표!$B$8:$B$9,0))) | H38: =G38*E38 | I38: =IF(A38=A37,I37&" · ","")&IF(C38="카드",D38&E38,"["&C38&"] "&D38)
A39: 11 | B39: 3 | C39: 카드 | D39: 괴월 | E39: 1 | F39: B | G39: =IF(C39="카드",INDEX(비용표!$C$2:$C$7,MATCH(F39,비용표!$B$2:$B$7,0)),F39*INDEX(비용표!$C$8:$C$9,MATCH(C39,비용표!$B$8:$B$9,0))) | H39: =G39*E39 | I39: =IF(A39=A38,I38&" · ","")&IF(C39="카드",D39&E39,"["&C39&"] "&D39)
... A43: 12 | B43: 3 | C43: 카드 | D43: 엄강 | E43: 1 | F43: C | G43: =IF(C43="카드",INDEX(비용표!$C$2:$C$7,MATCH(F43,비용표!$B$2:$B$7,0)),F43*INDEX(비용표!$C$8:$C$9,MATCH(C43,비용표!$B$8:$B$9,0))) | H43: =G43*E43 | I43: =IF(A43=A42,I42&" · ","")&IF(C43="카드",D43&E43,"["&C43&"] "&D43)
A44: 12 | B44: 4 | C44: 아이템 | D44: 대완마 | E44: 1 | F44: 2 | G44: =IF(C44="카드",INDEX(비용표!$C$2:$C$7,MATCH(F44,비용표!$B$2:$B$7,0)),F44*INDEX(비용표!$C$8:$C$9,MATCH(C44,비용표!$B$8:$B$9,0))) | H44: =G44*E44 | I44: =IF(A44=A43,I43&" · ","")&IF(C44="카드",D44&E44,"["&C44&"] "&D44)
A45: 13 | B45: 1 | C45: 카드 | D45: 국의 | E45: 1 | F45: C | G45: =IF(C45="카드",INDEX(비용표!$C$2:$C$7,MATCH(F45,비용표!$B$2:$B$7,0)),F45*INDEX(비용표!$C$8:$C$9,MATCH(C45,비용표!$B$8:$B$9,0))) | H45: =G45*E45 | I45: =IF(A45=A44,I44&" · ","")&IF(C45="카드",D45&E45,"["&C45&"] "&D45)
A46: 13 | B46: 2 | C46: 카드 | D46: 원소 | E46: 1 | F46: C | G46: =IF(C46="카드",INDEX(비용표!$C$2:$C$7,MATCH(F46,비용표!$B$2:$B$7,0)),F46*INDEX(비용표!$C$8:$C$9,MATCH(C46,비용표!$B$8:$B$9,0))) | H46: =G46*E46 | I46: =IF(A46=A45,I45&" · ","")&IF(C46="카드",D46&E46,"["&C46&"] "&D46)
A47: 13 | B47: 3 | C47: 카드 | D47: 공손찬 | E47: 1 | F47: C | G47: =IF(C47="카드",INDEX(비용표!$C$2:$C$7,MATCH(F47,비용표!$B$2:$B$7,0)),F47*INDEX(비용표!$C$8:$C$9,MATCH(C47,비용표!$B$8:$B$9,0))) | H47: =G47*E47 | I47: =IF(A47=A46,I46&" · ","")&IF(C47="카드",D47&E47,"["&C47&"] "&D47)
A48: 14 | B48: 1 | C48: 카드 | D48: 이각 | E48: 1 | F48: C | G48: =IF(C48="카드",INDEX(비용표!$C$2:$C$7,MATCH(F48,비용표!$B$2:$B$7,0)),F48*INDEX(비용표!$C$8:$C$9,MATCH(C48,비용표!$B$8:$B$9,0))) | H48: =G48*E48 | I48: =IF(A48=A47,I47&" · ","")&IF(C48="카드",D48&E48,"["&C48&"] "&D48)
A49: 14 | B49: 2 | C49: 카드 | D49: 곽사 | E49: 1 | F49: C | G49: =IF(C49="카드",INDEX(비용표!$C$2:$C$7,MATCH(F49,비용표!$B$2:$B$7,0)),F49*INDEX(비용표!$C$8:$C$9,MATCH(C49,비용표!$B$8:$B$9,0))) | H49: =G49*E49 | I49: =IF(A49=A48,I48&" · ","")&IF(C49="카드",D49&E49,"["&C49&"] "&D49)
A50: 15 | B50: 1 | C50: 카드 | D50: 헌제 | E50: 1 | F50: E | G50: =IF(C50="카드",INDEX(비용표!$C$2:$C$7,MATCH(F50,비용표!$B$2:$B$7,0)),F50*INDEX(비용표!$C$8:$C$9,MATCH(C50,비용표!$B$8:$B$9,0))) | H50: =G50*E50 | I50: =IF(A50=A49,I49&" · ","")&IF(C50="카드",D50&E50,"["&C50&"] "&D50)
A51: 15 | B51: 2 | C51: 카드 | D51: 조조 | E51: 1 | F51: S | G51: =IF(C51="카드",INDEX(비용표!$C$2:$C$7,MATCH(F51,비용표!$B$2:$B$7,0)),F51*INDEX(비용표!$C$8:$C$9,MATCH(C51,비용표!$B$8:$B$9,0))) | H51: =G51*E51 | I51: =IF(A51=A50,I50&" · ","")&IF(C51="카드",D51&E51,"["&C51&"] "&D51)
A52: 15 | B52: 3 | C52: 카드 | D52: 서황 | E52: 1 | F52: S | G52: =IF(C52="카드",INDEX(비용표!$C$2:$C$7,MATCH(F52,비용표!$B$2:$B$7,0)),F52*INDEX(비용표!$C$8:$C$9,MATCH(C52,비용표!$B$8:$B$9,0))) | H52: =G52*E52 | I52: =IF(A52=A51,I51&" · ","")&IF(C52="카드",D52&E52,"["&C52&"] "&D52)
A53: 15 | B53: 4 | C53: 카드 | D53: 한섬 | E53: 1 | F53: D | G53: =IF(C53="카드",INDEX(비용표!$C$2:$C$7,MATCH(F53,비용표!$B$2:$B$7,0)),F53*INDEX(비용표!$C$8:$C$9,MATCH(C53,비용표!$B$8:$B$9,0))) | H53: =G53*E53 | I53: =IF(A53=A52,I52&" · ","")&IF(C53="카드",D53&E53,"["&C53&"] "&D53)
A54: 15 | B54: 5 | C54: 카드 | D54: 순욱 | E54: 1 | F54: S | G54: =IF(C54="카드",INDEX(비용표!$C$2:$C$7,MATCH(F54,비용표!$B$2:$B$7,0)),F54*INDEX(비용표!$C$8:$C$9,MATCH(C54,비용표!$B$8:$B$9,0))) | H54: =G54*E54 | I54: =IF(A54=A53,I53&" · ","")&IF(C54="카드",D54&E54,"["&C54&"] "&D54)
A55: 16 | B55: 1 | C55: 카드 | D55: 한호 | E55: 1 | F55: C | G55: =IF(C55="카드",INDEX(비용표!$C$2:$C$7,MATCH(F55,비용표!$B$2:$B$7,0)),F55*INDEX(비용표!$C$8:$C$9,MATCH(C55,비용표!$B$8:$B$9,0))) | H55: =G55*E55 | I55: =IF(A55=A54,I54&" · ","")&IF(C55="카드",D55&E55,"["&C55&"] "&D55)
A56: 16 | B56: 2 | C56: 카드 | D56: 모개 | E56: 1 | F56: C | G56: =IF(C56="카드",INDEX(비용표!$C$2:$C$7,MATCH(F56,비용표!$B$2:$B$7,0)),F56*INDEX(비용표!$C$8:$C$9,MATCH(C56,비용표!$B$8:$B$9,0))) | H56: =G56*E56 | I56: =IF(A56=A55,I55&" · ","")&IF(C56="카드",D56&E56,"["&C56&"] "&D56)
... A71: 21 | B71: 1 | C71: 카드 | D71: 여포 | E71: 1 | F71: S | G71: =IF(C71="카드",INDEX(비용표!$C$2:$C$7,MATCH(F71,비용표!$B$2:$B$7,0)),F71*INDEX(비용표!$C$8:$C$9,MATCH(C71,비용표!$B$8:$B$9,0))) | H71: =G71*E71 | I71: =IF(A71=A70,I70&" · ","")&IF(C71="카드",D71&E71,"["&C71&"] "&D71)
A72: 21 | B72: 2 | C72: 병기 | D72: 방천화극 | E72: 1 | F72: 5 | G72: =IF(C72="카드",INDEX(비용표!$C$2:$C$7,MATCH(F72,비용표!$B$2:$B$7,0)),F72*INDEX(비용표!$C$8:$C$9,MATCH(C72,비용표!$B$8:$B$9,0))) | H72: =G72*E72 | I72: =IF(A72=A71,I71&" · ","")&IF(C72="카드",D72&E72,"["&C72&"] "&D72)
A73: 21 | B73: 3 | C73: 아이템 | D73: 적토마 | E73: 1 | F73: 5 | G73: =IF(C73="카드",INDEX(비용표!$C$2:$C$7,MATCH(F73,비용표!$B$2:$B$7,0)),F73*INDEX(비용표!$C$8:$C$9,MATCH(C73,비용표!$B$8:$B$9,0))) | H73: =G73*E73 | I73: =IF(A73=A72,I72&" · ","")&IF(C73="카드",D73&E73,"["&C73&"] "&D73)
A74: 21 | B74: 4 | C74: 카드 | D74: 진궁 | E74: 1 | F74: B | G74: =IF(C74="카드",INDEX(비용표!$C$2:$C$7,MATCH(F74,비용표!$B$2:$B$7,0)),F74*INDEX(비용표!$C$8:$C$9,MATCH(C74,비용표!$B$8:$B$9,0))) | H74: =G74*E74 | I74: =IF(A74=A73,I73&" · ","")&IF(C74="카드",D74&E74,"["&C74&"] "&D74)
A75: 21 | B75: 5 | C75: 카드 | D75: 고순 | E75: 1 | F75: C | G75: =IF(C75="카드",INDEX(비용표!$C$2:$C$7,MATCH(F75,비용표!$B$2:$B$7,0)),F75*INDEX(비용표!$C$8:$C$9,MATCH(C75,비용표!$B$8:$B$9,0))) | H75: =G75*E75 | I75: =IF(A75=A74,I74&" · ","")&IF(C75="카드",D75&E75,"["&C75&"] "&D75)
A76: 22 | B76: 1 | C76: 카드 | D76: 고순 | E76: 1 | F76: C | G76: =IF(C76="카드",INDEX(비용표!$C$2:$C$7,MATCH(F76,비용표!$B$2:$B$7,0)),F76*INDEX(비용표!$C$8:$C$9,MATCH(C76,비용표!$B$8:$B$9,0))) | H76: =G76*E76 | I76: =IF(A76=A75,I75&" · ","")&IF(C76="카드",D76&E76,"["&C76&"] "&D76)
A77: 22 | B77: 2 | C77: 카드 | D77: 여포 | E77: 1 | F77: S | G77: =IF(C77="카드",INDEX(비용표!$C$2:$C$7,MATCH(F77,비용표!$B$2:$B$7,0)),F77*INDEX(비용표!$C$8:$C$9,MATCH(C77,비용표!$B$8:$B$9,0))) | H77: =G77*E77 | I77: =IF(A77=A76,I76&" · ","")&IF(C77="카드",D77&E77,"["&C77&"] "&D77)
A78: 23 | B78: 1 | C78: 카드 | D78: 여포 | E78: 1 | F78: S | G78: =IF(C78="카드",INDEX(비용표!$C$2:$C$7,MATCH(F78,비용표!$B$2:$B$7,0)),F78*INDEX(비용표!$C$8:$C$9,MATCH(C78,비용표!$B$8:$B$9,0))) | H78: =G78*E78 | I78: =IF(A78=A77,I77&" · ","")&IF(C78="카드",D78&E78,"["&C78&"] "&D78)
A79: 23 | B79: 2 | C79: 카드 | D79: 진궁 | E79: 1 | F79: B | G79: =IF(C79="카드",INDEX(비용표!$C$2:$C$7,MATCH(F79,비용표!$B$2:$B$7,0)),F79*INDEX(비용표!$C$8:$C$9,MATCH(C79,비용표!$B$8:$B$9,0))) | H79: =G79*E79 | I79: =IF(A79=A78,I78&" · ","")&IF(C79="카드",D79&E79,"["&C79&"] "&D79)
A80: 23 | B80: 3 | C80: 카드 | D80: 고순 | E80: 1 | F80: C | G80: =IF(C80="카드",INDEX(비용표!$C$2:$C$7,MATCH(F80,비용표!$B$2:$B$7,0)),F80*INDEX(비용표!$C$8:$C$9,MATCH(C80,비용표!$B$8:$B$9,0))) | H80: =G80*E80 | I80: =IF(A80=A79,I79&" · ","")&IF(C80="카드",D80&E80,"["&C80&"] "&D80)
A81: 23 | B81: 4 | C81: 카드 | D81: 장료 | E81: 1 | F81: S | G81: =IF(C81="카드",INDEX(비용표!$C$2:$C$7,MATCH(F81,비용표!$B$2:$B$7,0)),F81*INDEX(비용표!$C$8:$C$9,MATCH(C81,비용표!$B$8:$B$9,0))) | H81: =G81*E81 | I81: =IF(A81=A80,I80&" · ","")&IF(C81="카드",D81&E81,"["&C81&"] "&D81)
A82: 23 | B82: 5 | C82: 카드 | D82: 후성 | E82: 1 | F82: C | G82: =IF(C82="카드",INDEX(비용표!$C$2:$C$7,MATCH(F82,비용표!$B$2:$B$7,0)),F82*INDEX(비용표!$C$8:$C$9,MATCH(C82,비용표!$B$8:$B$9,0))) | H82: =G82*E82 | I82: =IF(A82=A81,I81&" · ","")&IF(C82="카드",D82&E82,"["&C82&"] "&D82)
A83: 24 | B83: 1 | C83: 카드 | D83: 진등 | E83: 1 | F83: C | G83: =IF(C83="카드",INDEX(비용표!$C$2:$C$7,MATCH(F83,비용표!$B$2:$B$7,0)),F83*INDEX(비용표!$C$8:$C$9,MATCH(C83,비용표!$B$8:$B$9,0))) | H83: =G83*E83 | I83: =IF(A83=A82,I82&" · ","")&IF(C83="카드",D83&E83,"["&C83&"] "&D83)
A84: 24 | B84: 2 | C84: 카드 | D84: 여포 | E84: 1 | F84: S | G84: =IF(C84="카드",INDEX(비용표!$C$2:$C$7,MATCH(F84,비용표!$B$2:$B$7,0)),F84*INDEX(비용표!$C$8:$C$9,MATCH(C84,비용표!$B$8:$B$9,0))) | H84: =G84*E84 | I84: =IF(A84=A83,I83&" · ","")&IF(C84="카드",D84&E84,"["&C84&"] "&D84)
A85: 24 | B85: 3 | C85: 카드 | D85: 유비 | E85: 1 | F85: S | G85: =IF(C85="카드",INDEX(비용표!$C$2:$C$7,MATCH(F85,비용표!$B$2:$B$7,0)),F85*INDEX(비용표!$C$8:$C$9,MATCH(C85,비용표!$B$8:$B$9,0))) | H85: =G85*E85 | I85: =IF(A85=A84,I84&" · ","")&IF(C85="카드",D85&E85,"["&C85&"] "&D85)
... A94: 27 | B94: 1 | C94: 카드 | D94: 태사자 | E94: 1 | F94: S | G94: =IF(C94="카드",INDEX(비용표!$C$2:$C$7,MATCH(F94,비용표!$B$2:$B$7,0)),F94*INDEX(비용표!$C$8:$C$9,MATCH(C94,비용표!$B$8:$B$9,0))) | H94: =G94*E94 | I94: =IF(A94=A93,I93&" · ","")&IF(C94="카드",D94&E94,"["&C94&"] "&D94)
A95: 27 | B95: 2 | C95: 병기 | D95: 수극 | E95: 1 | F95: 1 | G95: =IF(C95="카드",INDEX(비용표!$C$2:$C$7,MATCH(F95,비용표!$B$2:$B$7,0)),F95*INDEX(비용표!$C$8:$C$9,MATCH(C95,비용표!$B$8:$B$9,0))) | H95: =G95*E95 | I95: =IF(A95=A94,I94&" · ","")&IF(C95="카드",D95&E95,"["&C95&"] "&D95)
A96: 28 | B96: 1 | C96: 카드 | D96: 손권 | E96: 1 | F96: S | G96: =IF(C96="카드",INDEX(비용표!$C$2:$C$7,MATCH(F96,비용표!$B$2:$B$7,0)),F96*INDEX(비용표!$C$8:$C$9,MATCH(C96,비용표!$B$8:$B$9,0))) | H96: =G96*E96 | I96: =IF(A96=A95,I95&" · ","")&IF(C96="카드",D96&E96,"["&C96&"] "&D96)
A97: 28 | B97: 2 | C97: 카드 | D97: 장소 | E97: 1 | F97: A | G97: =IF(C97="카드",INDEX(비용표!$C$2:$C$7,MATCH(F97,비용표!$B$2:$B$7,0)),F97*INDEX(비용표!$C$8:$C$9,MATCH(C97,비용표!$B$8:$B$9,0))) | H97: =G97*E97 | I97: =IF(A97=A96,I96&" · ","")&IF(C97="카드",D97&E97,"["&C97&"] "&D97)
A98: 28 | B98: 3 | C98: 카드 | D98: 주유 | E98: 1 | F98: S | G98: =IF(C98="카드",INDEX(비용표!$C$2:$C$7,MATCH(F98,비용표!$B$2:$B$7,0)),F98*INDEX(비용표!$C$8:$C$9,MATCH(C98,비용표!$B$8:$B$9,0))) | H98: =G98*E98 | I98: =IF(A98=A97,I97&" · ","")&IF(C98="카드",D98&E98,"["&C98&"] "&D98)
A99: 29 | B99: 1 | C99: 카드 | D99: 장수 | E99: 1 | F99: B | G99: =IF(C99="카드",INDEX(비용표!$C$2:$C$7,MATCH(F99,비용표!$B$2:$B$7,0)),F99*INDEX(비용표!$C$8:$C$9,MATCH(C99,비용표!$B$8:$B$9,0))) | H99: =G99*E99 | I99: =IF(A99=A98,I98&" · ","")&IF(C99="카드",D99&E99,"["&C99&"] "&D99)
A100: 29 | B100: 2 | C100: 카드 | D100: 가후 | E100: 1 | F100: S | G100: =IF(C100="카드",INDEX(비용표!$C$2:$C$7,MATCH(F100,비용표!$B$2:$B$7,0)),F100*INDEX(비용표!$C$8:$C$9,MATCH(C100,비용표!$B$8:$B$9,0))) | H100: =G100*E100 | I100: =IF(A100=A99,I99&" · ","")&IF(C100="카드",D100&E100,"["&C100&"] "&D100)
A101: 29 | B101: 3 | C101: 카드 | D101: 조조 | E101: 1 | F101: S | G101: =IF(C101="카드",INDEX(비용표!$C$2:$C$7,MATCH(F101,비용표!$B$2:$B$7,0)),F101*INDEX(비용표!$C$8:$C$9,MATCH(C101,비용표!$B$8:$B$9,0))) | H101: =G101*E101 | I101: =IF(A101=A100,I100&" · ","")&IF(C101="카드",D101&E101,"["&C101&"] "&D101)
A102: 29 | B102: 4 | C102: 아이템 | D102: 절영 | E102: 1 | F102: 4 | G102: =IF(C102="카드",INDEX(비용표!$C$2:$C$7,MATCH(F102,비용표!$B$2:$B$7,0)),F102*INDEX(비용표!$C$8:$C$9,MATCH(C102,비용표!$B$8:$B$9,0))) | H102: =G102*E102 | I102: =IF(A102=A101,I101&" · ","")&IF(C102="카드",D102&E102,"["&C102&"] "&D102)
A103: 30 | B103: 1 | C103: 카드 | D103: 가후 | E103: 1 | F103: S | G103: =IF(C103="카드",INDEX(비용표!$C$2:$C$7,MATCH(F103,비용표!$B$2:$B$7,0)),F103*INDEX(비용표!$C$8:$C$9,MATCH(C103,비용표!$B$8:$B$9,0))) | H103: =G103*E103 | I103: =IF(A103=A102,I102&" · ","")&IF(C103="카드",D103&E103,"["&C103&"] "&D103)
A104: 30 | B104: 2 | C104: 카드 | D104: 장수 | E104: 1 | F104: B | G104: =IF(C104="카드",INDEX(비용표!$C$2:$C$7,MATCH(F104,비용표!$B$2:$B$7,0)),F104*INDEX(비용표!$C$8:$C$9,MATCH(C104,비용표!$B$8:$B$9,0))) | H104: =G104*E104 | I104: =IF(A104=A103,I103&" · ","")&IF(C104="카드",D104&E104,"["&C104&"] "&D104)
A105: 31 | B105: 1 | C105: 카드 | D105: 조조 | E105: 1 | F105: S | G105: =IF(C105="카드",INDEX(비용표!$C$2:$C$7,MATCH(F105,비용표!$B$2:$B$7,0)),F105*INDEX(비용표!$C$8:$C$9,MATCH(C105,비용표!$B$8:$B$9,0))) | H105: =G105*E105 | I105: =IF(A105=A104,I104&" · ","")&IF(C105="카드",D105&E105,"["&C105&"] "&D105)
A106: 31 | B106: 2 | C106: 카드 | D106: 유비 | E106: 1 | F106: S | G106: =IF(C106="카드",INDEX(비용표!$C$2:$C$7,MATCH(F106,비용표!$B$2:$B$7,0)),F106*INDEX(비용표!$C$8:$C$9,MATCH(C106,비용표!$B$8:$B$9,0))) | H106: =G106*E106 | I106: =IF(A106=A105,I105&" · ","")&IF(C106="카드",D106&E106,"["&C106&"] "&D106)
A107: 32 | B107: 1 | C107: 카드 | D107: 헌제 | E107: 1 | F107: E | G107: =IF(C107="카드",INDEX(비용표!$C$2:$C$7,MATCH(F107,비용표!$B$2:$B$7,0)),F107*INDEX(비용표!$C$8:$C$9,MATCH(C107,비용표!$B$8:$B$9,0))) | H107: =G107*E107 | I107: =IF(A107=A106,I106&" · ","")&IF(C107="카드",D107&E107,"["&C107&"] "&D107)
A108: 32 | B108: 2 | C108: 카드 | D108: 유비 | E108: 1 | F108: S | G108: =IF(C108="카드",INDEX(비용표!$C$2:$C$7,MATCH(F108,비용표!$B$2:$B$7,0)),F108*INDEX(비용표!$C$8:$C$9,MATCH(C108,비용표!$B$8:$B$9,0))) | H108: =G108*E108 | I108: =IF(A108=A107,I107&" · ","")&IF(C108="카드",D108&E108,"["&C108&"] "&D108)
A109: 32 | B109: 3 | C109: 카드 | D109: 마등 | E109: 1 | F109: A | G109: =IF(C109="카드",INDEX(비용표!$C$2:$C$7,MATCH(F109,비용표!$B$2:$B$7,0)),F109*INDEX(비용표!$C$8:$C$9,MATCH(C109,비용표!$B$8:$B$9,0))) | H109: =G109*E109 | I109: =IF(A109=A108,I108&" · ","")&IF(C109="카드",D109&E109,"["&C109&"] "&D109)
A110: 33 | B110: 1 | C110: 카드 | D110: 관우 | E110: 1 | F110: S | G110: =IF(C110="카드",INDEX(비용표!$C$2:$C$7,MATCH(F110,비용표!$B$2:$B$7,0)),F110*INDEX(비용표!$C$8:$C$9,MATCH(C110,비용표!$B$8:$B$9,0))) | H110: =G110*E110 | I110: =IF(A110=A109,I109&" · ","")&IF(C110="카드",D110&E110,"["&C110&"] "&D110)
A111: 33 | B111: 2 | C111: 카드 | D111: 장료 | E111: 1 | F111: S | G111: =IF(C111="카드",INDEX(비용표!$C$2:$C$7,MATCH(F111,비용표!$B$2:$B$7,0)),F111*INDEX(비용표!$C$8:$C$9,MATCH(C111,비용표!$B$8:$B$9,0))) | H111: =G111*E111 | I111: =IF(A111=A110,I110&" · ","")&IF(C111="카드",D111&E111,"["&C111&"] "&D111)
A112: 33 | B112: 3 | C112: 카드 | D112: 조조 | E112: 1 | F112: S | G112: =IF(C112="카드",INDEX(비용표!$C$2:$C$7,MATCH(F112,비용표!$B$2:$B$7,0)),F112*INDEX(비용표!$C$8:$C$9,MATCH(C112,비용표!$B$8:$B$9,0))) | H112: =G112*E112 | I112: =IF(A112=A111,I111&" · ","")&IF(C112="카드",D112&E112,"["&C112&"] "&D112)
A113: 34 | B113: 1 | C113: 카드 | D113: 곽가 | E113: 1 | F113: S | G113: =IF(C113="카드",INDEX(비용표!$C$2:$C$7,MATCH(F113,비용표!$B$2:$B$7,0)),F113*INDEX(비용표!$C$8:$C$9,MATCH(C113,비용표!$B$8:$B$9,0))) | H113: =G113*E113 | I113: =IF(A113=A112,I112&" · ","")&IF(C113="카드",D113&E113,"["&C113&"] "&D113)
A114: 34 | B114: 2 | C114: 카드 | D114: 조조 | E114: 1 | F114: S | G114: =IF(C114="카드",INDEX(비용표!$C$2:$C$7,MATCH(F114,비용표!$B$2:$B$7,0)),F114*INDEX(비용표!$C$8:$C$9,MATCH(C114,비용표!$B$8:$B$9,0))) | H114: =G114*E114 | I114: =IF(A114=A113,I113&" · ","")&IF(C114="카드",D114&E114,"["&C114&"] "&D114)
... A139: 40 | B139: 4 | C139: 카드 | D139: 하후돈 | E139: 1 | F139: S | G139: =IF(C139="카드",INDEX(비용표!$C$2:$C$7,MATCH(F139,비용표!$B$2:$B$7,0)),F139*INDEX(비용표!$C$8:$C$9,MATCH(C139,비용표!$B$8:$B$9,0))) | H139: =G139*E139 | I139: =IF(A139=A138,I138&" · ","")&IF(C139="카드",D139&E139,"["&C139&"] "&D139)
A140: 40 | B140: 5 | C140: 병기 | D140: 청룡언월도 | E140: 1 | F140: 5 | G140: =IF(C140="카드",INDEX(비용표!$C$2:$C$7,MATCH(F140,비용표!$B$2:$B$7,0)),F140*INDEX(비용표!$C$8:$C$9,MATCH(C140,비용표!$B$8:$B$9,0))) | H140: =G140*E140 | I140: =IF(A140=A139,I139&" · ","")&IF(C140="카드",D140&E140,"["&C140&"] "&D140)
A141: 41 | B141: 1 | C141: 카드 | D141: 관우 | E141: 1 | F141: S | G141: =IF(C141="카드",INDEX(비용표!$C$2:$C$7,MATCH(F141,비용표!$B$2:$B$7,0)),F141*INDEX(비용표!$C$8:$C$9,MATCH(C141,비용표!$B$8:$B$9,0))) | H141: =G141*E141 | I141: =IF(A141=A140,I140&" · ","")&IF(C141="카드",D141&E141,"["&C141&"] "&D141)
A142: 41 | B142: 2 | C142: 카드 | D142: 장비 | E142: 1 | F142: S | G142: =IF(C142="카드",INDEX(비용표!$C$2:$C$7,MATCH(F142,비용표!$B$2:$B$7,0)),F142*INDEX(비용표!$C$8:$C$9,MATCH(C142,비용표!$B$8:$B$9,0))) | H142: =G142*E142 | I142: =IF(A142=A141,I141&" · ","")&IF(C142="카드",D142&E142,"["&C142&"] "&D142)
A143: 41 | B143: 3 | C143: 카드 | D143: 유비 | E143: 1 | F143: S | G143: =IF(C143="카드",INDEX(비용표!$C$2:$C$7,MATCH(F143,비용표!$B$2:$B$7,0)),F143*INDEX(비용표!$C$8:$C$9,MATCH(C143,비용표!$B$8:$B$9,0))) | H143: =G143*E143 | I143: =IF(A143=A142,I142&" · ","")&IF(C143="카드",D143&E143,"["&C143&"] "&D143)
A144: 41 | B144: 4 | C144: 카드 | D144: 조운 | E144: 1 | F144: S | G144: =IF(C144="카드",INDEX(비용표!$C$2:$C$7,MATCH(F144,비용표!$B$2:$B$7,0)),F144*INDEX(비용표!$C$8:$C$9,MATCH(C144,비용표!$B$8:$B$9,0))) | H144: =G144*E144 | I144: =IF(A144=A143,I143&" · ","")&IF(C144="카드",D144&E144,"["&C144&"] "&D144)
A145: 41 | B145: 5 | C145: 카드 | D145: 주창 | E145: 1 | F145: A | G145: =IF(C145="카드",INDEX(비용표!$C$2:$C$7,MATCH(F145,비용표!$B$2:$B$7,0)),F145*INDEX(비용표!$C$8:$C$9,MATCH(C145,비용표!$B$8:$B$9,0))) | H145: =G145*E145 | I145: =IF(A145=A144,I144&" · ","")&IF(C145="카드",D145&E145,"["&C145&"] "&D145)
A146: 42 | B146: 1 | C146: 카드 | D146: 하후돈 | E146: 1 | F146: S | G146: =IF(C146="카드",INDEX(비용표!$C$2:$C$7,MATCH(F146,비용표!$B$2:$B$7,0)),F146*INDEX(비용표!$C$8:$C$9,MATCH(C146,비용표!$B$8:$B$9,0))) | H146: =G146*E146 | I146: =IF(A146=A145,I145&" · ","")&IF(C146="카드",D146&E146,"["&C146&"] "&D146)
A147: 42 | B147: 2 | C147: 카드 | D147: 조성 | E147: 1 | F147: C | G147: =IF(C147="카드",INDEX(비용표!$C$2:$C$7,MATCH(F147,비용표!$B$2:$B$7,0)),F147*INDEX(비용표!$C$8:$C$9,MATCH(C147,비용표!$B$8:$B$9,0))) | H147: =G147*E147 | I147: =IF(A147=A146,I146&" · ","")&IF(C147="카드",D147&E147,"["&C147&"] "&D147)
A148: 43 | B148: 1 | C148: 카드 | D148: 장료 | E148: 1 | F148: S | G148: =IF(C148="카드",INDEX(비용표!$C$2:$C$7,MATCH(F148,비용표!$B$2:$B$7,0)),F148*INDEX(비용표!$C$8:$C$9,MATCH(C148,비용표!$B$8:$B$9,0))) | H148: =G148*E148 | I148: =IF(A148=A147,I147&" · ","")&IF(C148="카드",D148&E148,"["&C148&"] "&D148)
A149: 43 | B149: 2 | C149: 카드 | D149: 허저 | E149: 1 | F149: S | G149: =IF(C149="카드",INDEX(비용표!$C$2:$C$7,MATCH(F149,비용표!$B$2:$B$7,0)),F149*INDEX(비용표!$C$8:$C$9,MATCH(C149,비용표!$B$8:$B$9,0))) | H149: =G149*E149 | I149: =IF(A149=A148,I148&" · ","")&IF(C149="카드",D149&E149,"["&C149&"] "&D149)
A150: 43 | B150: 3 | C150: 카드 | D150: 서황 | E150: 1 | F150: S | G150: =IF(C150="카드",INDEX(비용표!$C$2:$C$7,MATCH(F150,비용표!$B$2:$B$7,0)),F150*INDEX(비용표!$C$8:$C$9,MATCH(C150,비용표!$B$8:$B$9,0))) | H150: =G150*E150 | I150: =IF(A150=A149,I149&" · ","")&IF(C150="카드",D150&E150,"["&C150&"] "&D150)
A151: 43 | B151: 4 | C151: 아이템 | D151: 대완마 | E151: 1 | F151: 2 | G151: =IF(C151="카드",INDEX(비용표!$C$2:$C$7,MATCH(F151,비용표!$B$2:$B$7,0)),F151*INDEX(비용표!$C$8:$C$9,MATCH(C151,비용표!$B$8:$B$9,0))) | H151: =G151*E151 | I151: =IF(A151=A150,I150&" · ","")&IF(C151="카드",D151&E151,"["&C151&"] "&D151)
A152: 44 | B152: 1 | C152: 카드 | D152: 유비 | E152: 1 | F152: S | G152: =IF(C152="카드",INDEX(비용표!$C$2:$C$7,MATCH(F152,비용표!$B$2:$B$7,0)),F152*INDEX(비용표!$C$8:$C$9,MATCH(C152,비용표!$B$8:$B$9,0))) | H152: =G152*E152 | I152: =IF(A152=A151,I151&" · ","")&IF(C152="카드",D152&E152,"["&C152&"] "&D152)
A153: 44 | B153: 2 | C153: 카드 | D153: 채모 | E153: 1 | F153: B | G153: =IF(C153="카드",INDEX(비용표!$C$2:$C$7,MATCH(F153,비용표!$B$2:$B$7,0)),F153*INDEX(비용표!$C$8:$C$9,MATCH(C153,비용표!$B$8:$B$9,0))) | H153: =G153*E153 | I153: =IF(A153=A152,I152&" · ","")&IF(C153="카드",D153&E153,"["&C153&"] "&D153)
A154: 44 | B154: 3 | C154: 카드 | D154: 괴월 | E154: 1 | F154: B | G154: =IF(C154="카드",INDEX(비용표!$C$2:$C$7,MATCH(F154,비용표!$B$2:$B$7,0)),F154*INDEX(비용표!$C$8:$C$9,MATCH(C154,비용표!$B$8:$B$9,0))) | H154: =G154*E154 | I154: =IF(A154=A153,I153&" · ","")&IF(C154="카드",D154&E154,"["&C154&"] "&D154)
...

Sheet 규칙
A1: 항목 | B1: 규칙
A2: 칸 | B2: 조건 하나가 칸 하나. 카드 칸은 장수 카드, 병기 칸은 대장간 병기, 아이템 칸은 시장 아이템만 받는다.
A3: 등록 | B3: 칸마다 하나씩, 부분 등록 가능. 요건이 되는 칸을 누르면 「등록하시겠습니까?」. 되돌릴 수 없다.
A4: 카드 수 | B4: 한 컬렉션에 같은 장수 카드는 1장뿐이다 — 칸 하나 = 장수 하나 = 카드 1장 (2026-10-13 3차).
A5: 장수 카드 | B5: 풀의 본체를 1장으로 센다 — 여분 카드가 1장이라도 있으면 등록할 수 있고 여분만 쓴다. 본체는 빠지지 않는다.
A6: 완성 | B6: 모든 칸이 차면 완성 — 그때 점수와 효과가 생긴다. 부분 등록은 점수도 효과도 없다.
A7: 병기 | B7: 등록한 자루는 보유 목록에서 빠지므로 대장간 종류당 상한 = 만든 수 − 넣은 수. 장수에게 지급된 자루는 해제한 뒤에만 등록.
A8: 아이템 | B8: 가장 오래 산 것부터 빠진다. 이번 판에 들려 보낼 것으로 잡힌 수량은 등록할 수 없다.
A9: 능력치 상한 | B9: 등급별 능력치 값의 상한: 일반 1 · 희귀 2 · 영웅 2 · 전설 3 · 천하 3, 조건(함께 참전 · 적진에)이 걸리면 +1. HP는 2, MP는 1이 천장.
A10: 겹침 | B10: 같은 장수 × 같은 능력치를 받는 컬렉션은 하나뿐(데이터 검사로 고정). 진영 SP +1은 여럿 켜져도 +1. 도시 효과는 더한다.
A11: 금화 | B11: 도시 효과는 금화를 건드리지 않는다(얻기 · 할인 · 매물 늘리기 없음).
A12: 전투력 | B12: 컬렉션 효과는 battlePower()에 넣지 않는다.
... A16: 칸 수 | B16: 한 컬렉션의 칸은 장수 카드 · 병기 · 아이템을 합쳐 5개까지 — 상세 두루마리에 한 줄로 서도록 (2026-10-13).
